Workbook

Sheet README
A1: How to read this workbook
A3: Purpose | B3: Test whether European gas prices drive / predict moves on the German yield curve through inflation expectations and ECB rate expectations, with focus on the Iran-war regime (from 2 Mar 2026).
A4: Start here | B4: Executive_Summary (results & economic meaning) -> Economic_Intuition (the chain) -> Benchmarks (why these instruments) -> Test_Catalog (every test, one line each) -> Charts.
A5: Result sheets | B5: One sheet per test family, exported from Python. Green fill = p < 0.05 (in Diagnostics: a problem detected).
A6: Units | B6: Rates: bp. Prices: % log change. 'bp_per_10pct_ttf' = bp move for a +10% TTF move.
A7: Colour code | B7: Green text = live formula linking to another sheet. Black = values/text. Formulas in Event_Study compute changes from levels.
A8: Reproduce | B8: .venv/bin/python src/clean.py && .venv/bin/python src/econometrics.py && .venv/bin/python src/figures.py && .venv/bin/python src/build_workbook.py
A9: Data | B9: Raw exports archived under canonical names in data/raw/; clean panels in data/clean/.
A10: Prepared | B10: 11 Oct 2026, data to 9 Oct 2026 close.

Sheet Executive_Summary
A1: Gas -> Inflation Expectations -> ECB Pricing -> Bund Curve: Results Recap
A2: Sample: daily Oct 2014 - 9 Oct 2026 (€STR OIS from Oct 2019, 1Y ILS from Apr 2022). Iran-war regime from 2 Mar 2026 (143 trading days / 32 weeks). Green numbers link live to the result sheets.
A4: Link in the chain | B4: Metric | C4: Estimate | D4: p-value | E4: Verdict | F4: Economic meaning
A5: 1. Gas -> realised inflation | B5: HICP y/y per +10% TTF, 9 months later (pp) | C5: ='HICP_Passthrough'!$E$30 | D5: ='HICP_Passthrough'!$D$30 | E5: SUPPORTED, WITH A LAG | F5: Gas reaches consumer prices through retail gas/electricity tariffs that reset slowly; the effect is ~0 on impact and builds to ~0.2pp of y/y HICP per +10% after 9-12 months. Oil, by contrast, passes through immediately. Gas is therefore a LEADING indicator of headline inflation at exactly the 1-year horizon the ECB targets.
A6: 1b. ... vs oil (benchmark) | B6: HICP y/y per +10% Brent, same month (pp) | C6: ='HICP_Passthrough'!$H$21 | D6: ='HICP_Passthrough'!$G$21 | E6: CONTEXT | F6: Oil is the faster, larger inflation driver; any 'gas' result must control for Brent (all regressions do).
A7: 2. Gas -> market inflation expectations | B7: Infl. swap 1Y, bp per +10% TTF, war regime | C7: ='Transmission_Daily'!$F$9 | D7: ='Transmission_Daily'!$H$9 | E7: SUPPORTED, AMPLIFIED IN WAR | F7: Inflation swaps reprice the same day. Sensitivity in the war (~7bp per +10%) is ~4x the 2023-26 level. The 1y1y forward moves much less (~1.8bp) and reverses within ~20 trading days (local projections, short sample): markets treat most of the gas spike as a near-term price-level shock rather than persistent inflation.
A8: 2b. ... forward expectations | B8: Infl. swap 1y1y, bp per +10% TTF, war regime | C8: ='Transmission_Daily'!$F$14 | D8: ='Transmission_Daily'!$H$14 | E8: SUPPORTED (WEAKER) | F8: The forward the ECB cares about responds, but modestly, and Brent explains more of it than gas.
A9: 3. Expectations -> ECB rate pricing | B9: €STR OIS 1y1y, bp per +10% TTF, war regime (weekly) | C9: ='Transmission_Weekly'!$E$23 | D9: ='Transmission_Weekly'!$G$23 | E9: SUPPORTED | F9: Gas moves the expected policy path in the war (~2.3bp daily, ~4.8bp weekly per +10%). About a third of the daily effect runs through inflation swaps; the rest is priced directly - the market reads energy headlines straight into the ECB reaction function. A break test dates the shift to early March 2026 without being told the war date.
A10: 3b. Break in policy sensitivity | B10: sup-Wald stat, €STR OIS 2Y (5% cv = 8.68) | C10: ='Structural_Breaks'!$H$13 | D10: ='Structural_Breaks'!$G$13 | E10: CONFIRMED (1%) | F10: The estimated break date is in the first week of the war (see Structural_Breaks).
A11: 4. Policy pricing -> Bund front end | B11: Bund 2Y, bp per +10% TTF, war regime (daily; Holm-corrected p within the rates family) | C11: ='Transmission_Daily'!$F$34 | D11: ='Transmission_Daily'!$J$34 | E11: SUPPORTED | F11: A +10% gas day lifts the Schatz ~4bp in the war (raw p = 0.003; weekly: ~3.6bp, p = 0.001). After Holm correction it stays significant within the 13 rate series (p = 0.036) and is borderline across all 20 series tested (p = 0.057). Weekly mediation: OIS 1y1y passes ~0.7bp per bp into the 2Y Bund.
A12: 4b. Curve shape | B12: Slope 2s30s, bp per +10% TTF, war regime (daily) | C12: ='Transmission_Daily'!$F$84 | D12: ='Transmission_Daily'!$H$84 | E12: SUPPORTED: BEAR FLATTENING | F12: The 30Y barely moves (~0.2bp) while the front end rises: gas shocks are priced as POLICY shocks, not as term-premium or long-run inflation shocks. Confirmed by the PCA slope factor and by weekly 5s30s (-2.6bp, p < 0.001).
A13: 4c. Which flattener | B13: Slope 2s30s, weekly, bp per +10% TTF, war | C13: ='Curve_Slopes'!$J$11 | D13: ='Curve_Slopes'!$K$11 | E13: 2s30s LARGEST; 2s10s CLEANEST | F13: All six slopes flatten on gas in the war. 2s30s is the largest and is significant daily and weekly, but Brent flattens it too. 2s10s (-2.8bp daily) and 2s5s (-2.1bp daily) respond to gas but not to oil, so they are the purest gas expressions; 2s5s fades within the week. Before 2021 gas slightly STEEPENED the curve (front end pinned at the lower bound).
A14: 5. Regime dependence | B14: Bund 2Y, bp per +10% TTF, 2021-22 gas crisis (daily) | C14: ='Transmission_Daily'!$F$32 | D14: ='Transmission_Daily'!$H$32 | E14: STRONGLY SUPPORTED | F14: In 2021-22 higher gas meant LOWER Bund and OIS rates: markets priced recession risk and an ECB that called inflation transitory. In 2026 the ECB is seen as reactive (it hiked in June and September), so gas is a hawkish signal. The sign of the gas-rates beta is set by the perceived central-bank reaction function, not by gas itself.
A15: 5b. War vs base difference test | B15: Bund 2Y: war minus base effect, bp per +10% | C15: ='Regime_Tests'!$E$15 | D15: ='Regime_Tests'!$G$15 | E15: SIGNIFICANT | F15: Formal test that the war-regime sensitivity differs from normal times.
A16: 6. Predictivity of curve moves | B16: OOS R2, next-week Bund 2Y, gas model vs no-change (war) | C16: ='OOS_Forecast'!$I$34 | D16: ='OOS_Forecast'!$K$34 | E16: NOT SUPPORTED (market frequency) | F16: Gas EXPLAINS same-day curve moves but does not FORECAST later ones: local projections show no drift after day 1-2, Granger tests (weekly) find no lead from TTF to Bunds, and OOS forecasts do not beat a random walk. Only next-week €STR OIS shows a fragile gain in the war (31 forecasts). The predictive channel is macro: gas -> HICP 6-12 months out.
A17: 7. Oil vs gas | B17: Brent effect on €STR OIS 1y1y, bp per +10%, war (daily) | C17: ='Transmission_Daily'!$M$24 | D17: ='Transmission_Daily'!$O$24 | E17: CAVEAT | F17: Brent's effect on inflation and policy pricing is 3-5x gas's. In the Hormuz shock oil and gas co-move (corr ~0.67), so their separate contributions are only partly identified (VAR FEVD: TTF share of OIS 1y1y variance 2% if Brent is ordered first, 40% if TTF is first). The gas effect on the Bund front end survives the Brent control.
A19: Bottom line
A20: • | B20: The thesis holds in the current regime: since 2 March 2026, gas has been a significant driver of euro inflation swaps, of the expected ECB path and of the Bund front end, and it bear-flattens the curve.
A21: • | B21: It is conditional, not structural: before 2021 the link was ~0 and in 2021-22 it had the opposite sign. Any trade or model built on it must monitor the rolling sensitivity (Rolling_Betas / chart f3).
A22: • | B22: Gas explains curve moves contemporaneously; it does not give a tradable lead at daily/weekly frequency. Its genuine predictive content is for realised inflation 6-12 months ahead, i.e. for the data the ECB will react to.
A24: Methodological safeguards applied
A25: • | B25: Model in changes: all levels are I(1) (ADF/KPSS/Zivot-Andrews), no robust cointegration.
A26: • | B26: Newey-West HAC inference everywhere (fat tails, heteroskedasticity, ARCH and serial correlation detected).
A27: • | B27: Front-month roll days removed from TTF/Brent/NBP/HH returns (open-interest based detection).
A28: • | B28: Bundesbank yields are observed ~half a day before LSEG closes: daily Bund regressions include previous-day market moves; full-chain mediation/VAR with Bunds run weekly; predictive tests skip the overlapping day.
A29: • | B29: Brent and EURUSD controls in every regression; Holm correction for multiple testing; block-bootstrap CIs.
A31: Limits
A32: • | B32: One war episode: 143 daily / 32 weekly observations. Estimates are precise enough to reject zero but not to pin down magnitudes tightly.
A33: • | B33: Co-movement conditional on controls is not full causal identification: geopolitical news moves gas, oil and rates together. A cleaner design would instrument gas with LNG-specific outage news or use intraday event windows.
A34: • | B34: RESET flags some non-linearity (large gas days may matter disproportionately) - a threshold model is a natural extension.

Sheet Economic_Intuition
A1: Economic intuition: the transmission chain and how each link is tested
A2: Each row is one link of the thesis: mechanism, expected sign, what would falsify it, the benchmark used, the tests, and the outcome.
A4: # | B4: Link | C4: Mechanism (why) | D4: Expected sign | E4: What would falsify it | F4: Benchmarks used | G4: Tests | H4: Outcome
A5: 1 | B5: Gas price -> realised inflation | C5: Gas sets the marginal price of electricity (merit order) and feeds household gas tariffs, fertiliser, chemicals and industrial costs. Retail tariffs are regulated or contracted and reset with a lag of months. | D5: + (lagged) | E5: No relation between TTF and HICP at any lag once oil is controlled for. | F5: TTF (EUR), HICP y/y and m/m, Brent (EUR) | G5: Distributed-lag regression (13 lags), Granger, y/y lag scan | H5: Supported: ~0 on impact, +0.2pp y/y per +10% after 9-12 months (p <= 0.02). Oil passes through immediately.
A6: 2 | B6: Gas -> market inflation expectations | C6: Forward-looking investors price the future HICP prints today via inflation-linked swaps (HICPxT). The 1Y spot swap captures the near-term price level; the 1y1y forward captures persistence into the ECB's horizon. | D6: + | E6: Inflation swaps do not react to gas once Brent is controlled for. | F6: ILS 1Y (EUCPIZ1Y=TWEB), ILS 1y1y (EUIL1YF1Y=R) | G6: Regime regressions (HAC), interaction Wald, LP, break tests | H6: Supported. ILS 1Y ~+7bp per +10% TTF in the war (p < 0.001); 1y1y ~+1.8bp; Brent dominates both.
A7: 3 | B7: Inflation expectations -> ECB rate expectations | C7: A central bank with a credible inflation-targeting reaction function raises the expected policy path when expected inflation rises, especially if second-round effects or de-anchoring are feared. | D7: + (only if the ECB is seen as reactive) | E7: OIS does not move with gas/ILS, or moves down (growth fears dominate). | F7: €STR OIS 1M/3M/1Y/2Y, OIS 1y1y forward (derived) | G7: Mediation with block bootstrap, VAR/Granger, sup-Wald break | H7: Supported in the war: OIS 1y1y +2.3bp (daily) / +4.8bp (weekly) per +10% TTF; ~1/3 via ILS. Negative in 2021-22.
A8: 4 | B8: ECB expectations -> Bund curve | C8: The 2Y Schatz tracks the expected policy path (plus a scarcity premium); long maturities add term premium and long-run inflation risk. A policy shock lifts the front end more than the long end = bear flattening. | D8: 2Y +, slope - | E8: Long end reacts as much as the front (term-premium shock) or curve steepens. | F8: Bundesbank 2Y-30Y yields, slopes, PCA factors, Bund-OIS spread, 5Y swap spread | G8: Transmission regressions, PCA, weekly mediation | H8: Supported: 2Y ~+4bp, 30Y ~0, 2s30s ~-3.9bp per +10% TTF; PCA slope factor significant.
A9: 5 | B9: Regime dependence | C9: The SIGN of the gas-rates link depends on how markets expect the ECB to react. If gas is read as a growth shock and the ECB as patient (2022 'transitory'), yields fall; if the ECB is seen as reactive (2026 hikes), yields rise. | D9: Varies by regime | E9: Constant beta across regimes. | F9: All of the above | G9: Regime splits, interaction tests, Chow/sup-Wald, rolling betas | H9: Strongly supported: negative in 2021-22, ~0 in normal times, positive in the war.
A10: 6 | B10: Predictivity | C10: Efficient markets should price public gas information immediately, so a tradable lead-lag is not expected. Predictivity is plausible only via slow-moving fundamentals (inflation prints) or limited attention. | D10: None at market frequency; + for macro data | E10: Gas moves today predict curve moves next days/weeks. | F10: Same series | G10: Local projections, Granger, out-of-sample Clark-West tests | H10: Not supported for curve moves (no drift after day 1-2, no OOS gain for Bunds); supported for HICP 6-12m ahead.
A11: C | B11: Confounders | C11: Oil (Hormuz hits both), EUR exchange rate (energy priced in USD), global risk-off (flight to Bund quality), German fiscal supply (long end). | D11: - | E11: - | F11: Brent, EURUSD, 5Y swap spread, Bund-OIS spread | G11: Controls in every regression, VAR orderings, swap-spread regressions | H11: Gas effect on front end survives Brent control; oil and gas effects are only partly separable in the war.
A13: Chain diagram
B14: Hormuz / Qatar LNG supply shock
B15: -> TTF gas price (and Brent)
B16: -> realised HICP (energy, with a 6-12 month lag) [link 1]
B17: -> inflation swaps 1Y / 1y1y (priced immediately) [link 2]
B18: -> €STR OIS 1y1y = expected ECB path [link 3]
B19: -> Bund 2Y up more than Bund 30Y = bear flattening [link 4]

Sheet Benchmarks
A1: Benchmarks used, why these, and what was rejected
A2: Clean variable names as used in data/clean/*.csv. Full definitions: Data_Dictionary sheet.
A4: Role in the chain | B4: Clean name | C4: Instrument / source | D4: Unit | E4: History | F4: Why this benchmark | G4: Alternatives considered | H4: Treatment / caveat
A5: Gas | B5: gas_ttf_m1_eurmwh | C5: ICE Endex Dutch TTF front-month (LSEG TFMBMc1) | D5: EUR/MWh | E5: Oct 2014 - | F5: THE euro-area wholesale gas benchmark; in EUR, so no FX noise; most liquid European gas contract; front month is what headlines and retail tariff indexation track. | G5: NBP (UK hub, GBp/therm - kept for robustness), Henry Hub (US, not a euro-area cost), IMF EU monthly average (monthly, USD, revised). | H5: Continuation contract: roll days removed (OI jump).
A6: Oil (control) | B6: oil_brent_m1_usdbbl | C6: ICE Brent front-month (LSEG LCOc1) | D6: USD/bbl | E6: Oct 2014 - | F6: Main confounder: Hormuz hits oil and gas together, and inflation swaps are historically oil-driven. | G6: WTI (US benchmark, less relevant for Europe). | H6: Roll days removed.
A7: FX (control) | B7: fx_eurusd | C7: EUR/USD spot (LSEG EUR=) | D7: USD per EUR | E7: Oct 2014 - | F7: Energy is priced in USD; EUR moves change the euro cost of oil and risk sentiment. | G7: - | H7: Mid of bid/ask.
A8: Inflation expectations (near) | B8: ils_eur_1y | C8: EUR 1Y zero-coupon inflation swap, HICPxT (LSEG/Tradeweb EUCPIZ1Y=TWEB) | D8: % | E8: Apr 2022 - | F8: Captures expected inflation over the next year: where gas pass-through shows up first. | G8: HICP flash surveys (monthly, not market-based). | H8: Short history (from 2022).
A9: Inflation expectations (forward) | B9: ils_eur_1y1y | C9: EUR inflation swap 1y forward 1y (LSEG EUIL1YF1Y=R) | D9: % | E9: Jan 2016 - | F9: Inflation 1-2 years ahead = the ECB's policy horizon; strips out the mechanical near-term carry. | G9: 5y5y (long-run anchoring - not available, suggested addition). | H9: File was mislabelled '1Y'; renamed.
A10: Rate-hike expectations | B10: ois_estr_1y1y / ois_estr_2y | C10: €STR OIS 1M, 3M, 1Y, 2Y (LSEG EUREST*=); 1y1y derived | D10: % | E10: Sep 2019 - | F10: OIS is the cleanest market measure of the expected ECB path: no credit, scarcity or collateral premium (unlike Bunds). 1y1y = expected rate one year ahead. | G10: Euribor futures (contain bank credit premium), ECB-dated OIS (not available). | H10: Mid of bid/ask.
A11: Bund curve | B11: bund_2y ... bund_30y | C11: Bundesbank daily yields of current federal securities (BBSSY) | D11: % | E11: 2Y/5Y/10Y/30Y from 2014; 7Y/15Y from 2020; 20Y from Jan 2026 | F11: Official, free, long history. 2Y Schatz = policy-sensitive end; 30Y = term premium / long-run end. | G11: Zero-coupon fitted curve (would remove on-the-run roll effects - suggested robustness). | H11: Snapshot taken ~half a day before LSEG closes: timing-adjusted.
A12: Curve shape | B12: slope_2s10s, slope_2s30s, slope_5s30s, fly_2s5s10s, PCA | C12: Derived from Bund yields | D12: bp | E12: - | F12: Tests the 'specific moves' part of the thesis: policy shocks flatten, term-premium shocks steepen. | G12: - | H12: -
A13: Safety / scarcity premia | B13: swapsprd_de5y_bp, sprd_bund2y_ois2y | C13: 5Y IRS - Bund (LSEG DE5IRS5Y=RR); Bund 2Y - OIS 2Y | D13: bp | E13: 2014 - / 2019 - | F13: Separates genuine policy repricing from flight-to-quality into Bunds. | G13: - | H13: -
A14: Realised inflation | B14: hicp_ea_idx / _yoy / _mom | C14: Euro-area HICP index (2025=100) | D14: index / % | E14: Dec 1999 - | F14: First link of the chain at its natural (monthly) frequency. | G14: HICP energy sub-index (suggested addition). | H14: Base-splice break removed; NSA - month dummies used.
A15: Robustness only | B15: gas_nbp_m1_*, gas_hh_m1_usdmmbtu, gas_eu_imf_usdmmbtu_mavg | C15: NBP, Henry Hub, IMF EU gas | D15: various | E15: various | F15: Cross-checks; HH is the US leg of the LNG arbitrage. | G15: - | H15: Not used in headline tests.

Sheet Test_Catalog
A1: Catalog of econometric tests: what each answers, result, and economic meaning
A2: Ordered from data properties to identification to predictivity. 'Sheet' points to the full table.
A4: Category | B4: Test | C4: Question | D4: Null hypothesis (H0) | E4: Result | F4: Economic meaning / consequence | G4: Sheet
A5: Data properties | B5: Jarque-Bera | C5: Are daily changes normal? | D5: Normality | E5: Rejected for all series (excess kurtosis up to 15). | F5: Fat tails -> rely on robust (HAC) inference and bootstrap CIs. | G5: Descriptive
A6: Data properties | B6: Ljung-Box Q(10) | C6: Are changes autocorrelated? | D6: No autocorrelation | E6: Rejected in the full sample for 2Y Bund, TTF, ILS; not in the war regime. | F6: Mild serial dependence -> Newey-West SEs. | G6: Descriptive
A7: Data properties | B7: ARCH-LM(5) | C7: Volatility clustering? | D7: No ARCH | E7: Strongly rejected in full sample. | F7: Volatility regimes -> HAC SEs; regime split. | G7: Descriptive
A8: Stationarity | B8: ADF / KPSS / Zivot-Andrews | C8: Levels or changes? | D8: Unit root (ADF, ZA) / stationary (KPSS) | E8: All levels I(1); all changes I(0) (OIS 2Y borderline on ADF only). | F8: Regressions in levels would be spurious -> model changes. | G8: Unit_Roots
A9: Long-run relation | B9: Engle-Granger, Johansen | C9: Do gas and yields share a long-run equilibrium? | D9: No cointegration | E9: No pairwise cointegration; Johansen rank > 0 is likely break-driven (2022). | F9: No stable levels relationship: gas is a shock driver, not an anchor for yields. | G9: Cointegration
A10: Transmission | B10: OLS with Newey-West HAC, by regime | C10: How much do rates move per gas move? | D10: beta = 0 | E10: War: ILS 1Y, OIS, Bund 2Y, 2s30s significant; 2021-22 negative; normal times ~0. | F10: Core result: gas is a front-end policy driver in the war. | G10: Transmission_Daily / _Weekly
A11: Multiple testing | B11: Holm correction | C11: Are results artefacts of testing many series? | D11: All betas = 0 | E11: War regime: ILS 1Y survives across all 20 series (p = 0.005); Bund 2Y survives within the rates family (p = 0.036), borderline across all 20 (p = 0.057); 2s5s survives within the curve-shape family (p = 0.045). | F11: The headline is not a data-mining artefact, but individual slope results are suggestive. | G11: Transmission_Daily
A12: Regime | B12: Interaction Wald test | C12: Is the war beta different from normal? | D12: Equal betas | E12: Rejected for Bund 2Y, ILS 1Y, 2s10s, 2s30s. | F12: The link is regime-specific. | G12: Regime_Tests
A13: Regime | B13: Chow, HAC Wald, Quandt-Andrews sup-Wald | C13: Is there a break, and when? | D13: No break | E13: OIS 1y1y / OIS 2Y: break dated 5-11 Mar 2026 (1%). Slopes: break in Feb-Mar 2025 (German fiscal shock). | F13: The data locate the regime change at the war onset on their own. | G13: Structural_Breaks
A14: Regime | B14: CUSUM | C14: Are full-sample coefficients stable? | D14: Stable | E14: Rejected for Bund levels in the full sample. | F14: A single full-sample beta is misleading. | G14: Diagnostics
A15: Residuals | B15: Durbin-Watson, Breusch-Godfrey, Ljung-Box | C15: Serial correlation in residuals? | D15: None | E15: Present in the full sample; in the war regime only for OIS 1y1y and Bund 10Y. | F15: Handled by HAC SEs. | G15: Diagnostics
... A27: Events | B27: Event study | C27: What happened on key dates? | D27: - | E27: War onset (2-day): Bund 2Y +16bp vs 30Y +6bp, 2s10s -5bp. Ceasefire: OIS 1y1y -23bp, 2s10s +7bp (reversal). | F27: Narrative check of the regressions. | G27: Event_Study

Sheet Charts
A1: Charts
A2: Rendered by src/figures.py; PNGs in output/figures/.

Sheet Descriptive
A1: Descriptive statistics of daily changes
A2: Rates in bp/day, prices in %/day (log). Jarque-Bera: H0 normal. Ljung-Box Q(10): H0 no autocorrelation. ARCH-LM(5): H0 no volatility clustering.
A3: Source: src/econometrics.py -> output/tables/01_descriptive_stats.csv. Green cells: p < 0.05.
A5: regime | B5: series | C5: n | D5: mean | E5: std | F5: skew | G5: excess_kurtosis | H5: min | I5: max | J5: acf_lag1 | K5: jarque_bera_p | L5: ljung_box_q10_p | M5: arch_lm5_p
A6: Full sample | B6: r_gas_ttf_m1_eurmwh | C6: 2906 | D6: -0.030016373 | E6: 4.3519598 | F6: 0.30857923 | G6: 10.83094 | H6: -35.242114 | I6: 41.278433 | J6: 0.019944491 | K6: 0 | L6: 1.5037619e-06 | M6: 2.5007293e-142
A7: Full sample | B7: r_oil_brent_m1_usdbbl | C7: 2914 | D7: 0.041326891 | E7: 2.5486162 | F7: -0.88532521 | G7: 13.936819 | H7: -27.97615 | I7: 19.077401 | J7: 0.013252685 | K7: 0 | L7: 0.030529305 | M7: 2.4827544e-32
A8: Full sample | B8: d_ils_eur_1y1y | C8: 2733 | D8: 0.051061105 | E8: 3.7313329 | F8: -0.57170816 | G8: 9.1537539 | H8: -33.58 | I8: 23.45 | J8: 0.0724852 | K8: 0 | L8: 1.221248e-05 | M8: 1.5689689e-56
A9: Full sample | B9: d_ois_estr_1y1y | C9: 1784 | D9: 0.22201512 | E9: 6.0815181 | F9: -0.28275193 | G9: 4.3915885 | H9: -34.526408 | I9: 31.808072 | J9: 0.020130158 | K9: 0 | L9: 0.083434088 | M9: 6.2055224e-59
A10: Full sample | B10: d_bund_2y | C10: 3041 | D10: 0.10358435 | E10: 4.1229609 | F10: -0.5490209 | G10: 15.253767 | H10: -43 | I10: 34 | J10: -0.031378925 | K10: 0 | L10: 1.4500629e-05 | M10: 1.510814e-98
A11: Full sample | B11: d_bund_10y | C11: 3041 | D11: 0.084840513 | E11: 4.5188243 | F11: -0.022796307 | G11: 4.4650005 | H11: -31 | I11: 28 | J11: -0.0072682594 | K11: 0 | L11: 0.30471559 | M11: 4.033675e-60
A12: Full sample | B12: d_bund_30y | C12: 3041 | D12: 0.066425518 | E12: 4.6088652 | F12: 0.03477846 | G12: 3.3762837 | H12: -26 | I12: 31 | J12: -0.0019643043 | K12: 0 | L12: 0.17490738 | M12: 9.5804082e-70
A13: Full sample | B13: d_slope_2s10s | C13: 3041 | D13: -0.018743834 | E13: 3.0126887 | F13: 0.39417249 | G13: 4.4104344 | H13: -17 | I13: 22 | J13: -0.030195186 | K13: 0 | L13: 0.43272527 | M13: 5.5086123e-54
A14: 2014-21 pre-crisis | B14: r_gas_ttf_m1_eurmwh | C14: 1620 | D14: -0.080463233 | E14: 2.8783339 | F14: 0.089310924 | G14: 6.9123277 | H14: -19.598744 | I14: 20.921308 | J14: 0.034258184 | K14: 0 | L14: 3.6595874e-05 | M14: 8.2947044e-55
A15: 2014-21 pre-crisis | B15: r_oil_brent_m1_usdbbl | C15: 1626 | D15: 0.0057718796 | E15: 2.6723812 | F15: -0.9459228 | G15: 18.399381 | H15: -27.97615 | I15: 19.077401 | J15: 0.012143548 | K15: 0 | L15: 0.19840389 | M15: 4.5524093e-18
A16: 2014-21 pre-crisis | B16: d_ils_eur_1y1y | C16: 1387 | D16: 0.02777938 | E16: 2.4164677 | F16: -0.72583427 | G16: 7.7801421 | H16: -18.12 | I16: 15.86 | J16: 0.077174811 | K16: 0 | L16: 0.00058393166 | M16: 3.1282384e-14
A17: 2014-21 pre-crisis | B17: d_ois_estr_1y1y | C17: 438 | D17: 0.047529175 | E17: 1.6441371 | F17: 0.18548711 | G17: 2.6682798 | H17: -6.4998582 | I17: 7.3402073 | J17: -0.013329702 | K17: 1.7362879e-29 | L17: 0.00020981615 | M17: 5.428318e-15
... A45: Iran war (Mar 2026+) | B45: d_slope_2s10s | C45: 157 | D45: -0.17834395 | E45: 2.8159418 | F45: 0.073937679 | G45: 1.4694366 | H45: -9 | I45: 10 | J45: -0.07404954 | K45: 0.00079748265 | L45: 0.82323267 | M45: 0.0019107777

Sheet Unit_Roots
A1: Stationarity: ADF, KPSS and Zivot-Andrews (weekly levels & changes)
A2: ADF / Zivot-Andrews H0: unit root. KPSS H0: stationary. 'stationary' = ADF rejects and KPSS does not. Zivot-Andrews allows one endogenous break (break date reported).
A3: Source: src/econometrics.py -> output/tables/02_unit_roots.csv. Green cells: p < 0.05.
A5: series | B5: form | C5: n_weeks | D5: adf_stat | E5: adf_p | F5: kpss_stat | G5: kpss_p | H5: za_stat | I5: za_p | J5: za_break_date | K5: verdict
A6: bund_2y | B6: level | C6: 626 | D6: 0.23646385 | E6: 0.97423416 | F6: 2.6936867 | G6: 0.01 | H6: -5.7517788 | I6: 0.0015323937 | J6: 2022-03-04 | K6: unit root
A7: bund_2y | B7: first difference | C7: 625 | D7: -9.8966206 | E7: 3.4443487e-17 | F7: 0.38921357 | G7: 0.081804494 | H7: -10.916834 | I7: 1e-05 | J7: 2023-03-03 | K7: stationary
A8: bund_10y | B8: level | C8: 626 | D8: 0.39908966 | E8: 0.98146087 | F8: 2.4198054 | G8: 0.01 | H8: -4.6791971 | I8: 0.074471909 | J8: 2022-03-04 | K8: unit root
A9: bund_10y | B9: first difference | C9: 625 | D9: -10.472184 | E9: 1.2758537e-18 | F9: 0.41451192 | G9: 0.070900033 | H9: -11.043947 | I9: 1e-05 | J9: 2023-03-03 | K9: stationary
A10: bund_30y | B10: level | C10: 626 | D10: -0.071916588 | E10: 0.9521649 | F10: 2.0626869 | G10: 0.01 | H10: -3.8290202 | I10: 0.46012255 | J10: 2022-03-04 | K10: unit root
A11: bund_30y | B11: first difference | C11: 625 | D11: -24.033485 | E11: 0 | F11: 0.42506437 | G11: 0.066351563 | H11: -10.772353 | I11: 1e-05 | J11: 2023-10-27 | K11: stationary
A12: slope_2s10s | B12: level | C12: 626 | D12: -1.7573482 | E12: 0.40183314 | F12: 1.5817503 | G12: 0.01 | H12: -3.3267329 | I12: 0.7810992 | J12: 2024-07-19 | K12: unit root
A13: slope_2s10s | B13: first difference | C13: 625 | D13: -18.845901 | E13: 0 | F13: 0.087628756 | G13: 0.1 | H13: -19.126035 | I13: 1e-05 | J13: 2023-06-30 | K13: stationary
A14: ln_ttf | B14: level | C14: 626 | D14: -1.78718 | E14: 0.38684478 | F14: 1.4994769 | G14: 0.01 | H14: -4.0738235 | I14: 0.30728428 | J14: 2021-03-19 | K14: unit root
A15: ln_ttf | B15: first difference | C15: 625 | D15: -6.1704572 | E15: 6.8253416e-08 | F15: 0.10696912 | G15: 0.1 | H15: -7.178263 | I15: 1e-05 | J15: 2022-08-26 | K15: stationary
A16: ln_brent | B16: level | C16: 626 | D16: -2.3215791 | E16: 0.16510271 | F16: 1.5612514 | G16: 0.01 | H16: -4.1626944 | I16: 0.25824997 | J16: 2020-10-30 | K16: unit root
A17: ln_brent | B17: first difference | C17: 625 | D17: -18.118134 | E17: 2.5261262e-30 | F17: 0.10370991 | G17: 0.1 | H17: -18.394453 | I17: 1e-05 | J17: 2020-04-24 | K17: stationary
... A25: swapsprd_de5y_bp | B25: first difference | C25: 625 | D25: -13.742082 | E25: 1.0896206e-25 | F25: 0.11293644 | G25: 0.1 | H25: -14.406208 | I25: 1e-05 | J25: 2022-10-14 | K25: stationary

Sheet Cointegration
A1: Cointegration: Engle-Granger (pairs) and Johansen (systems)
A2: H0 (EG): no cointegration. Johansen: sequential trace test at 5%. Weekly levels.
A3: Source: src/econometrics.py -> output/tables/03_cointegration.csv. Green cells: p < 0.05.
A5: test | B5: system | C5: n_weeks | D5: stat | E5: p_value | F5: rank_at_5pct | G5: verdict
A6: Engle-Granger | B6: bund_2y ~ ln_ttf | C6: 627 | D6: -1.1679487 | E6: 0.86609493 | F6: 0 | G6: no cointegration
A7: Engle-Granger | B7: ils_eur_1y1y ~ ln_ttf | C7: 562 | D7: -2.4043636 | E7: 0.32279107 | F7: 0 | G7: no cointegration
A8: Engle-Granger | B8: ils_eur_1y1y ~ ln_brent | C8: 562 | D8: -3.3090603 | E8: 0.05350274 | F8: 0 | G8: no cointegration
A9: Engle-Granger | B9: ois_estr_1y1y ~ ils_eur_1y1y | C9: 367 | D9: -1.3472284 | E9: 0.81502904 | F9: 0 | G9: no cointegration
A10: Engle-Granger | B10: bund_2y ~ ois_estr_2y | C10: 368 | D10: -1.097212 | E10: 0.88280525 | F10: 0 | G10: no cointegration
A11: Engle-Granger | B11: bund_2y ~ ils_eur_1y1y | C11: 562 | D11: -1.9269605 | E11: 0.56627291 | F11: 0 | G11: no cointegration
A12: Johansen trace | B12: bund_2y , ils_eur_1y1y , ln_ttf , ln_brent | C12: 562 | D12: 64.54914 | F12: 3 | G12: rank 3 (trace r=0: 64.5 vs 5% cv 47.9)
A13: Johansen trace | B13: bund_2y , ois_estr_1y1y , ils_eur_1y1y , ln_ttf | C13: 367 | D13: 56.576462 | F13: 1 | G13: rank 1 (trace r=0: 56.6 vs 5% cv 47.9)

Sheet Transmission_Daily
A1: Transmission regressions, daily: change in rate on TTF, Brent, EURUSD - by regime
A2: bp_per_10pct_ttf = total effect of a +10% TTF move in bp (same day + previous day for Bundesbank yields, which are snapshotted before the market close). Newey-West HAC SEs.
A3: Multiple testing (Holm, within each regime): p_ttf_holm = across all 20 dependent variables (strictest); p_ttf_holm_family = within its family (rates & spreads: 13 series; curve shape: 7 series).
A4: Source: src/econometrics.py -> output/tables/04_transmission_daily.csv. Green cells: p < 0.05.
A6: dependent | B6: family | C6: regime | D6: n | E6: async_adjusted | F6: bp_per_10pct_ttf | G6: t_ttf | H6: p_ttf | I6: p_ttf_holm | J6: p_ttf_holm_family | K6: beta_ttf_same_day | L6: beta_ttf_prev_day | M6: bp_per_10pct_brent | N6: t_brent | O6: p_brent | P6: r2
A7: Infl. swap 1Y | B7: rates & spreads | C7: 2021-22 gas crisis | D7: 169 | E7: FALSE | F7: 6.4891979 | G7: 2.9221611 | H7: 0.0034761174 | I7: 0.069522348 | J7: 0.045189526 | K7: 0.68085045 | M7: 17.380099 | N7: 3.1836971 | O7: 0.001454071 | P7: 0.20154335
A8: Infl. swap 1Y | B8: rates & spreads | C8: 2023-Feb26 normalisation | D8: 735 | E8: FALSE | F8: 1.5550916 | G8: 3.2896547 | H8: 0.0010031038 | I8: 0.019058972 | J8: 0.012037246 | K8: 0.16316113 | M8: 12.48597 | N8: 8.4868453 | O8: 2.1232206e-17 | P8: 0.2229971
A9: Infl. swap 1Y | B9: rates & spreads | C9: Iran war (Mar 2026+) | D9: 142 | E9: FALSE | F9: 6.8789576 | G9: 3.6801715 | H9: 0.00023307715 | I9: 0.004661543 | J9: 0.0030300029 | K9: 0.72174427 | M9: 17.393151 | N9: 10.65773 | O9: 1.6046576e-26 | P9: 0.6724957
A10: Infl. swap 1Y | B10: rates & spreads | C10: Full sample | D10: 1046 | E10: FALSE | F10: 3.8547641 | G10: 4.6379116 | H10: 3.519473e-06 | I10: 7.0389459e-05 | J10: 4.5753149e-05 | K10: 0.40444411 | M10: 15.35564 | N10: 13.215344 | O10: 7.1558049e-40 | P10: 0.29104635
A11: Infl. swap 1y1y | B11: rates & spreads | C11: 2014-21 pre-crisis | D11: 1271 | E11: FALSE | F11: 0.34640216 | G11: 1.8672121 | H11: 0.061871969 | I11: 0.72486258 | J11: 0.56316347 | K11: 0.036344717 | M11: 3.4070986 | N11: 6.9923419 | O11: 2.7033501e-12 | P11: 0.19489918
A12: Infl. swap 1y1y | B12: rates & spreads | C12: 2021-22 gas crisis | D12: 352 | E12: FALSE | F12: 1.5628497 | G12: 2.7745418 | H12: 0.0055279532 | I12: 0.10503111 | J12: 0.066335438 | K12: 0.16397511 | M12: 8.5477774 | N12: 5.5761918 | O12: 2.4584086e-08 | P12: 0.22689919
A13: Infl. swap 1y1y | B13: rates & spreads | C13: 2023-Feb26 normalisation | D13: 735 | E13: FALSE | F13: 1.0641887 | G13: 3.8137744 | H13: 0.00013686041 | I13: 0.0027372082 | J13: 0.0017791854 | K13: 0.1116553 | M13: 7.240404 | N13: 8.3950103 | O13: 4.6585337e-17 | P13: 0.214967
A14: Infl. swap 1y1y | B14: rates & spreads | C14: Iran war (Mar 2026+) | D14: 143 | E14: FALSE | F14: 1.7705902 | G14: 2.2740406 | H14: 0.022963549 | I14: 0.34445323 | J14: 0.25259903 | K14: 0.18577136 | M14: 4.9141169 | N14: 6.9975301 | O14: 2.6051407e-12 | P14: 0.42468057
A15: Infl. swap 1y1y | B15: rates & spreads | C15: Full sample | D15: 2501 | E15: FALSE | F15: 1.2896689 | G15: 3.5176062 | H15: 0.00043545812 | I15: 0.0082737043 | J15: 0.0052254974 | K15: 0.13531282 | M15: 4.9165004 | N15: 10.531256 | O15: 6.2001581e-26 | P15: 0.19898585
A16: €STR OIS 1Y | B16: rates & spreads | C16: 2014-21 pre-crisis | D16: 403 | E16: FALSE | F16: 0.036903478 | G16: 0.47872392 | H16: 0.63213504 | I16: 1 | J16: 1 | K16: 0.0038719346 | M16: 0.36998707 | N16: 1.1988237 | O16: 0.2305965 | P16: 0.046907894
A17: €STR OIS 1Y | B17: rates & spreads | C17: 2021-22 gas crisis | D17: 352 | E17: FALSE | F17: -0.42744555 | G17: -1.7346281 | H17: 0.082806707 | I17: 0.95091246 | J17: 0.44706576 | K17: -0.044847837 | M17: 2.1082221 | N17: 2.0335972 | O17: 0.041992222 | P17: 0.020077917
A18: €STR OIS 1Y | B18: rates & spreads | C18: 2023-Feb26 normalisation | D18: 735 | E18: FALSE | F18: 0.13435143 | G18: 0.40331071 | H18: 0.68671966 | I18: 1 | J18: 1 | K18: 0.014096231 | M18: 3.4547174 | N18: 3.0700631 | O18: 0.0021401356 | P18: 0.032510444
... A30: €STR OIS 2Y | B30: rates & spreads | C30: Full sample | D30: 1634 | E30: FALSE | F30: 0.14368548 | G30: 0.50730145 | H30: 0.61194332 | I30: 1 | J30: 1 | K30: 0.015075565 | M30: 3.5772975 | N30: 4.7119295 | O30: 2.4538222e-06 | P30: 0.053006524
A31: Bund 2Y | B31: rates & spreads | C31: 2014-21 pre-crisis | D31: 1473 | E31: TRUE | F31: 0.31087629 | G31: 1.5931991 | H31: 0.11111553 | I31: 1 | J31: 0.88892422 | K31: 0.0059823954 | L31: 0.026634927 | M31: 0.62133206 | N31: 1.5490442 | O31: 0.12137109 | P31: 0.02394434
A32: Bund 2Y | B32: rates & spreads | C32: 2021-22 gas crisis | D32: 335 | E32: TRUE | F32: -1.2393012 | G32: -2.224082 | H32: 0.026142926 | I32: 0.44442975 | J32: 0.26142926 | K32: -0.1224204 | L32: -0.007607804 | M32: 4.4054262 | N32: 2.4407122 | O32: 0.01465833 | P32: 0.035779889
A33: Bund 2Y | B33: rates & spreads | C33: 2023-Feb26 normalisation | D33: 699 | E33: TRUE | F33: -0.33541895 | G33: -0.31066848 | H33: 0.75605266 | I33: 1 | J33: 1 | K33: 0.061522628 | L33: -0.096714981 | M33: 7.3896377 | N33: 3.7844741 | O33: 0.00015403397 | P33: 0.046769145
A34: Bund 2Y | B34: rates & spreads | C34: Iran war (Mar 2026+) | D34: 135 | E34: TRUE | F34: 4.0791826 | G34: 2.970368 | H34: 0.0029744321 | I34: 0.056514211 | J34: 0.035693186 | K34: 0.40410906 | L34: 0.023881176 | M34: 5.7569207 | N34: 5.2029907 | O34: 1.9610669e-07 | P34: 0.39710496
A35: Bund 2Y | B35: rates & spreads | C35: Full sample | D35: 2642 | E35: TRUE | F35: -0.18862415 | G35: -0.48580209 | H35: 0.62710749 | I35: 1 | J35: 1 | K35: -0.0013306519 | L35: -0.018459905 | M35: 3.2251624 | N35: 5.3083142 | O35: 1.1064379e-07 | P35: 0.02279815
A36: Bund 5Y | B36: rates & spreads | C36: 2014-21 pre-crisis | D36: 1473 | E36: TRUE | F36: 0.53441222 | G36: 1.9085796 | H36: 0.056316347 | I36: 0.72486258 | J36: 0.56316347 | K36: 0.020879383 | L36: 0.035191461 | M36: 0.81586839 | N36: 1.361722 | O36: 0.17328564 | P36: 0.025207525
A37: Bund 5Y | B37: rates & spreads | C37: 2021-22 gas crisis | D37: 335 | E37: TRUE | F37: -1.3523229 | G37: -2.0165117 | H37: 0.043746493 | I37: 0.6561974 | J37: 0.34997194 | K37: -0.11974135 | L37: -0.022145163 | M37: 5.6812094 | N37: 2.8580739 | O37: 0.0042622115 | P37: 0.046023531
A38: Bund 5Y | B38: rates & spreads | C38: 2023-Feb26 normalisation | D38: 699 | E38: TRUE | F38: -0.40194285 | G38: -0.3891089 | H38: 0.69719559 | I38: 1 | J38: 1 | K38: 0.047076642 | L38: -0.089248722 | M38: 7.867434 | N38: 4.1391104 | O38: 3.486551e-05 | P38: 0.060930803
A39: Bund 5Y | B39: rates & spreads | C39: Iran war (Mar 2026+) | D39: 135 | E39: TRUE | F39: 2.0104565 | G39: 1.6429324 | H39: 0.10039693 | I39: 0.80317543 | J39: 0.7027785 | K39: 0.24810054 | L39: -0.037162267 | M39: 5.9599347 | N39: 5.6754494 | O39: 1.3832502e-08 | P39: 0.37731504
A40: Bund 5Y | B40: rates & spreads | C40: Full sample | D40: 2642 | E40: TRUE | F40: -0.17988582 | G40: -0.43005661 | H40: 0.66715446 | I40: 1 | J40: 1 | K40: -0.0045542794 | L40: -0.014319446 | M40: 3.3990607 | N40: 5.0517205 | O40: 4.3784808e-07 | P40: 0.023613972
A41: Bund 7Y | B41: rates & spreads | C41: 2014-21 pre-crisis | D41: 251 | E41: TRUE | F41: 0.30503532 | G41: 0.64260365 | H41: 0.52048132 | I41: 1 | J41: 1 | K41: 0.02630177 | L41: 0.0057027146 | M41: 2.9729382 | N41: 2.2798591 | O41: 0.022616047 | P41: 0.064572937
A42: Bund 7Y | B42: rates & spreads | C42: 2021-22 gas crisis | D42: 335 | E42: TRUE | F42: -1.4623426 | G42: -2.3002024 | H42: 0.021436756 | I42: 0.3858616 | J42: 0.23580431 | K42: -0.12940294 | L42: -0.024026906 | M42: 5.196393 | N42: 2.8769969 | O42: 0.0040147958 | P42: 0.051885051
... A95: Fly 2s5s10s | B95: curve shape | C95: Full sample | D95: 2642 | E95: TRUE | F95: 0.027361479 | G95: 0.1580628 | H95: 0.87440731 | I95: 1 | J95: 1 | K95: -0.0035822762 | L95: 0.0064530587 | M95: -0.090220629 | N95: -0.3127824 | O95: 0.75444599 | P95: 0.0055193743
A96: 5Y swap spread (IRS-Bund) | B96: rates & spreads | C96: 2014-21 pre-crisis | D96: 1552 | E96: FALSE | F96: 0.10402398 | G96: 1.0713724 | H96: 0.28400204 | I96: 1 | J96: 1 | K96: 0.010914257 | M96: -0.43771984 | N96: -1.8218581 | O96: 0.068476512 | P96: 0.017313736
A97: 5Y swap spread (IRS-Bund) | B97: rates & spreads | C97: 2021-22 gas crisis | D97: 352 | E97: FALSE | F97: 0.12254097 | G97: 0.89192056 | H97: 0.37243551 | I97: 1 | J97: 0.47422074 | K97: 0.01285707 | M97: -0.039501705 | N97: -0.086133469 | O97: 0.93136032 | P97: 0.062802814
A98: 5Y swap spread (IRS-Bund) | B98: rates & spreads | C98: 2023-Feb26 normalisation | D98: 699 | E98: FALSE | F98: 0.074129305 | G98: 0.43545346 | H98: 0.66323331 | I98: 1 | J98: 1 | K98: 0.0077776902 | M98: -0.91296432 | N98: -1.8465627 | O98: 0.064810546 | P98: 0.010475314
A99: 5Y swap spread (IRS-Bund) | B99: rates & spreads | C99: Iran war (Mar 2026+) | D99: 95 | E99: FALSE | F99: 1.3127012 | G99: 0.64453487 | H99: 0.51922865 | I99: 1 | J99: 1 | K99: 0.13772938 | M99: 4.7463289 | N99: 2.1703336 | O99: 0.029981586 | P99: 0.21295817
A100: 5Y swap spread (IRS-Bund) | B100: rates & spreads | C100: Full sample | D100: 2698 | E100: FALSE | F100: 0.25087804 | G100: 2.1540146 | H100: 0.031239025 | I100: 0.56230245 | J100: 0.34362928 | K100: 0.026322271 | M100: 0.054943156 | N100: 0.16914483 | O100: 0.86568273 | P100: 0.013777198
A101: Bund2Y - OIS2Y | B101: rates & spreads | C101: 2014-21 pre-crisis | D101: 385 | E101: TRUE | F101: -0.27038383 | G101: -0.95121198 | H101: 0.34149678 | I101: 1 | J101: 1 | K101: -0.03533237 | L101: 0.0069635395 | M101: 0.72273498 | N101: 1.9190923 | O101: 0.054972659 | P101: 0.060008892
A102: Bund2Y - OIS2Y | B102: rates & spreads | C102: 2021-22 gas crisis | D102: 335 | E102: TRUE | F102: 0.62119399 | G102: 1.1822403 | H102: 0.23711037 | I102: 1 | J102: 0.47422074 | K102: -0.021024147 | L102: 0.086200185 | M102: -0.15302282 | N102: -0.11174094 | O102: 0.91102882 | P102: 0.026927716
A103: Bund2Y - OIS2Y | B103: rates & spreads | C103: 2023-Feb26 normalisation | D103: 699 | E103: TRUE | F103: 0.17682881 | G103: 0.28198861 | H103: 0.77795225 | I103: 1 | J103: 1 | K103: 0.042826919 | L103: -0.024273936 | M103: 1.7058334 | N103: 1.2283185 | O103: 0.21932741 | P103: 0.018929027
A104: Bund2Y - OIS2Y | B104: rates & spreads | C104: Iran war (Mar 2026+) | D104: 135 | E104: TRUE | F104: -0.31642086 | G104: -0.1266001 | H104: 0.89925692 | I104: 1 | J104: 1 | K104: 0.082389759 | L104: -0.11558882 | M104: 0.40966178 | N104: 0.20869816 | O104: 0.83468388 | P104: 0.32470848
A105: Bund2Y - OIS2Y | B105: rates & spreads | C105: Full sample | D105: 1554 | E105: TRUE | F105: 0.26661842 | G105: 0.80703537 | H105: 0.41964611 | I105: 1 | J105: 1 | K105: -0.006039661 | L105: 0.034013423 | M105: 0.65457088 | N105: 1.3778469 | O105: 0.16825055 | P105: 0.029544457

Sheet Transmission_Weekly
A1: Transmission regressions, weekly (Fri-Fri): robustness to data timing
A2: Gas/Brent weekly returns = sum of roll-cleaned daily returns. For Bundesbank yields the market window is lagged one business day (Fri-Thu).
A3: Source: src/econometrics.py -> output/tables/04_transmission_weekly.csv. Green cells: p < 0.05.
A5: dependent | B5: family | C5: regime | D5: n | E5: bp_per_10pct_ttf | F5: t_ttf | G5: p_ttf | H5: p_ttf_holm | I5: p_ttf_holm_family | J5: bp_per_10pct_brent | K5: t_brent | L5: p_brent | M5: r2
A6: Infl. swap 1Y | B6: rates & spreads | C6: 2021-22 gas crisis | D6: 38 | E6: 18.002657 | F6: 3.0308648 | G6: 0.002438544 | H6: 0.04877088 | I6: 0.031701072 | J6: 20.776113 | K6: 2.0849075 | L6: 0.037077698 | M6: 0.29872992
A7: Infl. swap 1Y | B7: rates & spreads | C7: 2023-Feb26 normalisation | D7: 162 | E7: 1.9709252 | F7: 1.073087 | G7: 0.28323209 | H7: 1 | I7: 1 | J7: 20.071524 | K7: 4.5893437 | L7: 4.4464178e-06 | M7: 0.16520292
A8: Infl. swap 1Y | B8: rates & spreads | C8: Iran war (Mar 2026+) | D8: 32 | E8: 4.0416809 | F8: 1.360002 | G8: 0.1738293 | H8: 0.68845635 | I8: 0.51634226 | J8: 27.7581 | K8: 5.6824795 | L8: 1.3275582e-08 | M8: 0.69467213
A9: Infl. swap 1Y | B9: rates & spreads | C9: Full sample | D9: 232 | E9: 8.8984465 | F9: 2.8164272 | G9: 0.0048561044 | H9: 0.097122088 | I9: 0.063129357 | J9: 18.095253 | K9: 6.3315358 | L9: 2.4273283e-10 | M9: 0.24302294
A10: Infl. swap 1y1y | B10: rates & spreads | C10: 2014-21 pre-crisis | D10: 282 | E10: 0.4311393 | F10: 1.2410343 | G10: 0.21459309 | H10: 1 | I10: 1 | J10: 4.001519 | K10: 4.3614599 | L10: 1.2919747e-05 | M10: 0.22584588
A11: Infl. swap 1y1y | B11: rates & spreads | C11: 2021-22 gas crisis | D11: 79 | E11: 0.065410016 | F11: 0.04661242 | G11: 0.96282213 | H11: 1 | I11: 1 | J11: 15.382026 | K11: 4.2184843 | L11: 2.4595008e-05 | M11: 0.26230618
A12: Infl. swap 1y1y | B12: rates & spreads | C12: 2023-Feb26 normalisation | D12: 162 | E12: 0.11173075 | F12: 0.1694752 | G12: 0.86542287 | H12: 1 | I12: 1 | J12: 7.6882207 | K12: 3.4152416 | L12: 0.00063725468 | M12: 0.18715388
A13: Infl. swap 1y1y | B13: rates & spreads | C13: Iran war (Mar 2026+) | D13: 32 | E13: 2.5697766 | F13: 3.2809471 | G13: 0.0010345916 | H13: 0.016553466 | I13: 0.011380508 | J13: 3.0534834 | K13: 1.8251575 | L13: 0.067977269 | M13: 0.46696087
A14: Infl. swap 1y1y | B14: rates & spreads | C14: Full sample | D14: 555 | E14: 0.64670365 | F14: 0.82654053 | G14: 0.40849754 | H14: 1 | I14: 1 | J14: 6.1946997 | K14: 5.4841551 | L14: 4.1545018e-08 | M14: 0.17311385
A15: €STR OIS 1Y | B15: rates & spreads | C15: 2014-21 pre-crisis | D15: 89 | E15: 0.19773701 | F15: 1.1842981 | G15: 0.23629506 | H15: 1 | I15: 1 | J15: 0.41983044 | K15: 1.1940006 | L15: 0.23247773 | M15: 0.095688795
A16: €STR OIS 1Y | B16: rates & spreads | C16: 2021-22 gas crisis | D16: 79 | E16: -1.7276137 | F16: -2.5876375 | G16: 0.0096636623 | H16: 0.1546186 | I16: 0.08697296 | J16: -0.36441499 | K16: -0.23918481 | L16: 0.81096228 | M16: 0.10727717
A17: €STR OIS 1Y | B17: rates & spreads | C17: 2023-Feb26 normalisation | D17: 162 | E17: -0.053387615 | F17: -0.066340826 | G17: 0.94710648 | H17: 1 | I17: 1 | J17: 6.4971652 | K17: 2.4105988 | L17: 0.015926356 | M17: 0.10639936
... A104: Bund2Y - OIS2Y | B104: rates & spreads | C104: Full sample | D104: 363 | E104: -0.394574 | F104: -1.2106741 | G104: 0.22602034 | H104: 1 | I104: 1 | J104: 0.78480171 | K104: 1.256809 | L104: 0.20882282 | M104: 0.013118101

Sheet Regime_Tests
A1: Is the gas effect different in the war and in 2021-22? Pooled model with regime interactions
A2: Base = 2014-21 + 2023-Feb26 combined. H0: regime total effect = base total effect (HAC Wald).
A3: Source: src/econometrics.py -> output/tables/05_regime_interaction.csv. Green cells: p < 0.05.
A5: dependent | B5: regime_vs_base | C5: base_bp_per_10pct | D5: regime_bp_per_10pct | E5: difference_bp_per_10pct | F5: wald_t | G5: wald_p | H5: n
A6: Infl. swap 1Y | B6: 2021-22 gas crisis | C6: 1.5550916 | D6: 6.4891979 | E6: 4.9341063 | F6: 2.1182538 | G6: 0.034153583 | H6: 1046
A7: Infl. swap 1Y | B7: Iran war (Mar 2026+) | C7: 1.5550916 | D7: 6.8789576 | E7: 5.323866 | F7: 2.7280272 | G7: 0.0063714361 | H7: 1046
A8: Infl. swap 1y1y | B8: 2021-22 gas crisis | C8: 0.82020397 | D8: 1.5628497 | E8: 0.74264577 | F8: 1.1870829 | G8: 0.23519494 | H8: 2501
A9: Infl. swap 1y1y | B9: Iran war (Mar 2026+) | C9: 0.82020397 | D9: 1.7705902 | E9: 0.95038619 | F9: 1.2783356 | G9: 0.20113111 | H9: 2501
A10: €STR OIS 1y1y | B10: 2021-22 gas crisis | C10: 0.52904765 | D10: -1.0438441 | E10: -1.5728917 | F10: -2.2251724 | G10: 0.026069664 | H10: 1633
A11: €STR OIS 1y1y | B11: Iran war (Mar 2026+) | C11: 0.52904765 | D11: 2.3244218 | E11: 1.7953742 | F11: 1.6973263 | G11: 0.089634988 | H11: 1633
A12: €STR OIS 2Y | B12: 2021-22 gas crisis | C12: 0.34562499 | D12: -0.73416191 | E12: -1.0797869 | F12: -2.1680189 | G12: 0.030157251 | H12: 1634
A13: €STR OIS 2Y | B13: Iran war (Mar 2026+) | C13: 0.34562499 | D13: 2.0709758 | E13: 1.7253508 | F13: 1.8974569 | G13: 0.057767662 | H13: 1634
A14: Bund 2Y | B14: 2021-22 gas crisis | C14: 0.15690936 | D14: -1.2393012 | E14: -1.3962105 | F14: -1.8742966 | G14: 0.060889553 | H14: 2642
A15: Bund 2Y | B15: Iran war (Mar 2026+) | C15: 0.15690936 | D15: 4.0791826 | E15: 3.9222733 | F15: 2.8708627 | G15: 0.0040935327 | H15: 2642
A16: Bund 10Y | B16: 2021-22 gas crisis | C16: 0.35447385 | D16: -1.3471922 | E16: -1.7016661 | F16: -2.1001534 | G16: 0.035715348 | H16: 2642
A17: Bund 10Y | B17: Iran war (Mar 2026+) | C17: 0.35447385 | D17: 1.3227823 | E17: 0.96830848 | F17: 0.67652021 | G17: 0.49871042 | H17: 2642
... A33: 5Y swap spread (IRS-Bund) | B33: Iran war (Mar 2026+) | C33: 0.079779451 | D33: 1.3127012 | E33: 1.2329218 | F33: 0.63447372 | G33: 0.52577171 | H33: 2698

Sheet Diagnostics
A1: Residual diagnostics of the transmission regressions
A2: Durbin-Watson (~2 = no AR(1)); Breusch-Godfrey(5) & Ljung-Box(10): H0 no serial correlation; Breusch-Pagan & White: H0 homoskedastic; ARCH-LM(5): H0 no ARCH; Jarque-Bera: H0 normal; Ramsey RESET: H0 correct functional form; CUSUM: H0 stable coefficients; VIF > 5 = collinearity.
A3: Here green = rejection of the null, i.e. a problem detected (handled by HAC SEs / regime split).
A4: Source: src/econometrics.py -> output/tables/06_residual_diagnostics.csv. Green cells: p < 0.05.
A6: dependent | B6: sample | C6: n | D6: durbin_watson | E6: breusch_godfrey_5_p | F6: ljung_box_10_p | G6: breusch_pagan_p | H6: white_p | I6: arch_lm5_p | J6: jarque_bera_p | K6: reset_p | L6: cusum_p | M6: vif_ttf | N6: vif_brent | O6: corr_ttf_brent | P6: issues | Q6: remedy
A7: Infl. swap 1y1y | B7: Full sample | C7: 2501 | D7: 1.8341726 | E7: 0.0001076238 | F7: 1.3909457e-05 | G7: 0.12639346 | H7: 4.1166325e-69 | I7: 3.1941727e-66 | J7: 0 | K7: 0.10489843 | L7: 0.62795883 | M7: 1.055632 | N7: 1.0460485 | O7: 0.20981278 | P7: serial correlation, heteroskedasticity, ARCH, fat tails | Q7: Newey-West HAC SEs (robust to heteroskedasticity + autocorrelation); regime split for instability
A8: Infl. swap 1y1y | B8: Iran war (Mar 2026+) | C8: 143 | D8: 2.1723596 | E8: 0.06988554 | F8: 0.24904422 | G8: 0.016119169 | H8: 0.00043165478 | I8: 1.5351804e-07 | J8: 0.0321906 | K8: 0.15946902 | L8: 0.30013876 | M8: 1.8385994 | N8: 1.9044599 | O8: 0.67430507 | P8: heteroskedasticity, ARCH, fat tails | Q8: Newey-West HAC SEs (robust to heteroskedasticity + autocorrelation); regime split for instability
A9: €STR OIS 1y1y | B9: Full sample | C9: 1633 | D9: 2.0081378 | E9: 0.7224065 | F9: 0.068896124 | G9: 2.4391544e-05 | H9: 9.9485594e-35 | I9: 1.2795937e-48 | J9: 1.3979885e-308 | K9: 0.0003992349 | L9: 0.2975679 | M9: 1.0624478 | N9: 1.0493442 | O9: 0.21626936 | P9: heteroskedasticity, ARCH, fat tails, functional form | Q9: Newey-West HAC SEs (robust to heteroskedasticity + autocorrelation); regime split for instability
A10: €STR OIS 1y1y | B10: Iran war (Mar 2026+) | C10: 143 | D10: 2.3449973 | E10: 0.00029746957 | F10: 3.9460899e-05 | G10: 0.12608637 | H10: 0.00081802313 | I10: 0.0086146213 | J10: 0.0084203698 | K10: 0.55453733 | L10: 0.99610294 | M10: 1.8385994 | N10: 1.9044599 | O10: 0.67430507 | P10: serial correlation, heteroskedasticity, ARCH, fat tails | Q10: Newey-West HAC SEs (robust to heteroskedasticity + autocorrelation); regime split for instability
A11: Bund 2Y | B11: Full sample | C11: 2642 | D11: 2.0952629 | E11: 1.387787e-05 | F11: 3.2928892e-08 | G11: 0.0050100705 | H11: 2.4115367e-12 | I11: 2.2591263e-86 | J11: 0 | K11: 0.010618373 | L11: 0.025139329 | M11: 1.0529718 | N11: 1.0408844 | O11: 0.19658266 | P11: serial correlation, heteroskedasticity, ARCH, fat tails, functional form, parameter instability | Q11: Newey-West HAC SEs (robust to heteroskedasticity + autocorrelation); regime split for instability
A12: Bund 2Y | B12: Iran war (Mar 2026+) | C12: 135 | D12: 2.1999446 | E12: 0.27722799 | F12: 0.068452334 | G12: 0.14507416 | H12: 3.1927521e-07 | I12: 7.9706134e-06 | J12: 1.1280403e-06 | K12: 0.033555829 | L12: 0.9192047 | M12: 2.3462491 | N12: 2.1651937 | O12: 0.68897168 | P12: heteroskedasticity, ARCH, fat tails, functional form | Q12: Newey-West HAC SEs (robust to heteroskedasticity + autocorrelation); regime split for instability
A13: Bund 10Y | B13: Full sample | C13: 2642 | D13: 2.0237471 | E13: 0.12670893 | F13: 0.31135935 | G13: 6.3865948e-05 | H13: 7.3745869e-38 | I13: 2.9595056e-46 | J13: 0 | K13: 0.00057279323 | L13: 0.020272724 | M13: 1.0529718 | N13: 1.0408844 | O13: 0.19658266 | P13: heteroskedasticity, ARCH, fat tails, functional form, parameter instability | Q13: Newey-West HAC SEs (robust to heteroskedasticity + autocorrelation); regime split for instability
A14: Bund 10Y | B14: Iran war (Mar 2026+) | C14: 135 | D14: 1.8977733 | E14: 0.078900903 | F14: 0.00560644 | G14: 0.30259033 | H14: 0.011331064 | I14: 0.29057717 | J14: 0.22369166 | K14: 0.72919219 | L14: 0.97780678 | M14: 2.3462491 | N14: 2.1651937 | O14: 0.68897168 | P14: serial correlation, heteroskedasticity | Q14: Newey-West HAC SEs (robust to heteroskedasticity + autocorrelation); regime split for instability
A15: Bund 30Y | B15: Full sample | C15: 2642 | D15: 2.0232395 | E15: 0.27667779 | F15: 0.49152103 | G15: 3.5022714e-05 | H15: 5.6128708e-41 | I15: 1.005359e-56 | J15: 0 | K15: 0.0014837484 | L15: 0.016226733 | M15: 1.0529718 | N15: 1.0408844 | O15: 0.19658266 | P15: heteroskedasticity, ARCH, fat tails, functional form, parameter instability | Q15: Newey-West HAC SEs (robust to heteroskedasticity + autocorrelation); regime split for instability
A16: Bund 30Y | B16: Iran war (Mar 2026+) | C16: 135 | D16: 1.7789923 | E16: 0.26309856 | F16: 0.055840839 | G16: 0.41860058 | H16: 0.64103598 | I16: 0.82154716 | J16: 0.87655869 | K16: 0.44511835 | L16: 0.98936875 | M16: 2.3462491 | N16: 2.1651937 | O16: 0.68897168 | P16: none | Q16: OLS SEs valid
A17: Slope 2s10s | B17: Full sample | C17: 2642 | D17: 2.0536599 | E17: 0.65017967 | F17: 0.080136357 | G17: 0.014731772 | H17: 5.8211794e-29 | I17: 3.9022712e-45 | J17: 0 | K17: 0.00016594805 | L17: 0.71886311 | M17: 1.0529718 | N17: 1.0408844 | O17: 0.19658266 | P17: heteroskedasticity, ARCH, fat tails, functional form | Q17: Newey-West HAC SEs (robust to heteroskedasticity + autocorrelation); regime split for instability
A18: Slope 2s10s | B18: Iran war (Mar 2026+) | C18: 135 | D18: 2.2404114 | E18: 0.27738341 | F18: 0.38028552 | G18: 0.022846003 | H18: 8.3444607e-07 | I18: 0.036629915 | J18: 0.015978965 | K18: 0.016402546 | L18: 0.72638902 | M18: 2.3462491 | N18: 2.1651937 | O18: 0.68897168 | P18: heteroskedasticity, ARCH, fat tails, functional form | Q18: Newey-West HAC SEs (robust to heteroskedasticity + autocorrelation); regime split for instability

Sheet Structural_Breaks
A1: Structural breaks in the gas sensitivity (2023 - 2026)
A2: Chow F at 2 Mar 2026 (all coefficients). Robust Wald: shift in the total TTF effect at the war date (HAC). Quandt-Andrews sup-Wald: break date unknown, 15% trimming; 5% critical value 8.68 (Andrews 1993).
A3: Source: src/econometrics.py -> output/tables/07_structural_breaks.csv. Green cells: p < 0.05.
A5: dependent | B5: sample | C5: n | D5: chow_F_at_2026_03_02 | E5: chow_p | F5: ttf_effect_shift_bp_per_10pct | G5: robust_wald_p | H5: sup_wald_stat | I5: sup_wald_break_date | J5: sup_wald_cv_5pct | K5: sup_wald_significance | L5: searchable_window
A6: Bund 2Y | B6: 2023-01-05 to 2026-10-09 | C6: 834 | D6: 1.6702483 | E6: 0.11287295 | F6: 3.7486853 | G6: 0.04144925 | H6: 4.4199698 | I6: 2026-02-09 | J6: 8.68 | K6: not significant | L6: 2023-07-27 to 2026-03-17
A7: Bund 10Y | B7: 2023-01-05 to 2026-10-09 | C7: 834 | D7: 0.55571189 | E7: 0.79206123 | F7: 0.76609727 | G7: 0.67084763 | H7: 2.5027314 | I7: 2024-10-23 | J7: 8.68 | K7: not significant | L7: 2023-07-27 to 2026-03-17
A8: Slope 2s5s | B8: 2023-01-05 to 2026-10-09 | C8: 834 | D8: 2.2269367 | E8: 0.030215596 | F8: -2.3345893 | G8: 0.0044887715 | H8: 9.8462825 | I8: 2025-01-20 | J8: 8.68 | K8: 5% | L8: 2023-07-27 to 2026-03-17
A9: Slope 2s10s | B9: 2023-01-05 to 2026-10-09 | C9: 834 | D9: 2.2456618 | E9: 0.028842763 | F9: -2.982588 | G9: 0.020709106 | H9: 11.015624 | I9: 2025-02-14 | J9: 8.68 | K9: 5% | L9: 2023-07-27 to 2026-03-17
A10: Slope 2s30s | B10: 2023-01-05 to 2026-10-09 | C10: 834 | D10: 3.5938994 | E10: 0.00080523903 | F10: -4.9625032 | G10: 0.0023750211 | H10: 9.8435557 | I10: 2025-03-19 | J10: 8.68 | K10: 5% | L10: 2023-07-27 to 2026-03-17
A11: Infl. swap 1y1y | B11: 2023-01-04 to 2026-10-09 | C11: 878 | D11: 1.3730629 | E11: 0.24138041 | F11: -0.19690287 | G11: 0.78840662 | H11: 1.5237994 | I11: 2025-05-14 | J11: 8.68 | K11: not significant | L11: 2023-07-26 to 2026-03-18
A12: €STR OIS 1y1y | B12: 2023-01-04 to 2026-10-09 | C12: 878 | D12: 7.0719458 | E12: 1.3255863e-05 | F12: 4.3133553 | G12: 0.00037058823 | H12: 14.607346 | I12: 2026-03-11 | J12: 8.68 | K12: 1% | L12: 2023-07-26 to 2026-03-18
A13: €STR OIS 2Y | B13: 2023-01-04 to 2026-10-09 | C13: 878 | D13: 8.2975638 | E13: 1.4354138e-06 | F13: 3.8224095 | G13: 0.0001891266 | H13: 16.089202 | I13: 2026-03-05 | J13: 8.68 | K13: 1% | L13: 2023-07-26 to 2026-03-18

Sheet Timing
A1: Data timing & lead/lag (Dimson) tests
A2: Rows 1-3: Bundesbank yields load equally on previous- and same-day LSEG OIS moves => yields are observed ~half a day earlier. Remaining rows: TTF at t-1, t, t+1.
A3: Source: src/econometrics.py -> output/tables/09_lead_lag_timing.csv. Green cells: p < 0.05.
A5: test | B5: dependent | C5: regressor | D5: sample | E5: n | F5: beta_t-1 | G5: p_t-1 | H5: beta_t | I5: p_t | J5: beta_t+1 | K5: p_t+1 | L5: r2 | M5: dimson_sum_bp_per_10pct | N5: dimson_sum_p | O5: xcorr_gas(t-3) | P5: xcorr_gas(t-2) | Q5: xcorr_gas(t-1) | R5: xcorr_gas(t+0) | S5: xcorr_gas(t+1) | T5: xcorr_gas(t+2) | U5: xcorr_gas(t+3)
A6: timing vs OIS 2Y (LSEG close) | B6: Bund 2Y | C6: €STR OIS 2Y | D6: Oct 2019 - Oct 2026 | E6: 1782 | F6: 0.5258603 | G6: 1.5289613e-55 | H6: 0.4910978 | I6: 1.8881268e-27 | J6: -0.0095893273 | K6: 0.7649011 | L6: 0.42706371
A7: timing vs OIS 2Y (LSEG close) | B7: Bund 10Y | C7: €STR OIS 2Y | D7: Oct 2019 - Oct 2026 | E7: 1782 | F7: 0.45040388 | G7: 1.2586461e-45 | H7: 0.39051107 | I7: 8.3324643e-26 | J7: -0.0097730862 | K7: 0.73213353 | L7: 0.3068451
A8: timing vs OIS 2Y (LSEG close) | B8: Infl. swap 1y1y | C8: €STR OIS 2Y | D8: Oct 2019 - Oct 2026 | E8: 1782 | F8: 0.0011367729 | G8: 0.96915921 | H8: 0.25201711 | I8: 9.3641895e-09 | J8: 0.020074746 | K8: 0.50019482 | L8: 0.073990116
A9: Dimson TTF lead/lag | B9: Bund 2Y | C9: TTF | D9: Full sample | E9: 2629 | F9: -0.00011685457 | G9: 0.99671555 | H9: 0.0038240822 | I9: 0.92256633 | J9: -0.06195575 | K9: 0.061362008 | L9: 0.013284833 | M9: -0.55516771 | N9: 0.25719147 | O9: -0.032211038 | P9: -0.037249207 | Q9: 0.006322004 | R9: 0.012280427 | S9: -0.067915262 | T9: 0.0031133076 | U9: -0.017356076
A10: Dimson TTF lead/lag | B10: Bund 2Y | C10: TTF | D10: Iran war (Mar 2026+) | E10: 134 | F10: 0.18799063 | G10: 0.0066025947 | H10: 0.47818563 | I10: 7.5378839e-06 | J10: -0.027304457 | K10: 0.77158451 | L10: 0.34577589 | M10: 6.0890986 | N10: 0.00014762659 | O10: 0.023363104 | P10: -0.032356398 | Q10: 0.19263045 | R10: 0.45660777 | S10: -0.11016843 | T10: -0.077397598 | U10: -0.070860437
A11: Dimson TTF lead/lag | B11: Bund 10Y | C11: TTF | D11: Full sample | E11: 2629 | F11: 0.0037311749 | G11: 0.88427578 | H11: -0.0013298763 | I11: 0.97377164 | J11: -0.052576306 | K11: 0.085348075 | L11: 0.012663545 | M11: -0.4782189 | N11: 0.35938162 | O11: -0.0063265592 | P11: -0.030580184 | Q11: 0.0038852831 | R11: 0.010142444 | S11: -0.054815408 | T11: -0.00083849098 | U11: -0.010730268
A12: Dimson TTF lead/lag | B12: Bund 10Y | C12: TTF | D12: Iran war (Mar 2026+) | E12: 134 | F12: 0.14650117 | G12: 0.011479598 | H12: 0.33463645 | I12: 0.00013916418 | J12: 0.01800386 | K12: 0.81822533 | L12: 0.27007621 | M12: 4.7573264 | N12: 0.00013437831 | O12: 0.077062954 | P12: -0.07089838 | Q12: 0.19037149 | R12: 0.35816355 | S12: -0.077031085 | T12: -0.057807587 | U12: -0.06785788
A13: Dimson TTF lead/lag | B13: Infl. swap 1y1y | C13: TTF | D13: Full sample | E13: 2363 | F13: 0.018617843 | G13: 0.43400587 | H13: 0.12904765 | I13: 0.00012457336 | J13: -0.014878448 | K13: 0.43796052 | L13: 0.20171221 | M13: 1.2655957 | N13: 0.024146814 | O13: -0.0303003 | P13: -0.029557914 | Q13: 0.011554546 | R13: 0.23642622 | S13: 0.0055863015 | T13: -0.069120319 | U13: -0.028502996
A14: Dimson TTF lead/lag | B14: Infl. swap 1y1y | C14: TTF | D14: Iran war (Mar 2026+) | E14: 134 | F14: 0.0044329448 | G14: 0.91571249 | H14: 0.17754034 | I14: 0.037680451 | J14: 0.022245281 | K14: 0.84466732 | L14: 0.41403326 | M14: 1.9464108 | N14: 0.16174738 | O14: 0.16283133 | P14: -0.17913878 | Q14: -0.021190806 | R14: 0.50291562 | S14: 0.01241124 | T14: -0.12486278 | U14: -0.053387828
A15: Dimson TTF lead/lag | B15: €STR OIS 1y1y | C15: TTF | D15: Full sample | E15: 1544 | F15: -0.082853132 | G15: 0.0083351852 | H15: 0.028042891 | I15: 0.49098439 | J15: -0.063158951 | K15: 0.10641677 | L15: 0.057726567 | M15: -1.1243665 | N15: 0.072963393 | O15: 0.01569135 | P15: -0.005283398 | Q15: -0.052168291 | R15: 0.054839914 | S15: -0.04797179 | T15: -0.0046546966 | U15: -0.0095815243
A16: Dimson TTF lead/lag | B16: €STR OIS 1y1y | C16: TTF | D16: Iran war (Mar 2026+) | E16: 134 | F16: -0.11913019 | G16: 0.080001744 | H16: 0.23295871 | I16: 0.047005393 | J16: -0.014469783 | K16: 0.91275529 | L16: 0.59580228 | M16: 0.9469899 | N16: 0.58578381 | O16: 0.21749567 | P16: -0.071237536 | Q16: -0.089139137 | R16: 0.53132429 | S16: -0.019516609 | T16: 0.02973827 | U16: -0.14654517
A17: Dimson TTF lead/lag | B17: Slope 2s10s | C17: TTF | D17: Full sample | E17: 2629 | F17: 0.0038480295 | G17: 0.79092599 | H17: -0.0051539586 | I17: 0.75423912 | J17: 0.0093794438 | K17: 0.52049384 | L17: 0.0011725076 | M17: 0.076948813 | N17: 0.74104013 | O17: 0.034435118 | P17: 0.00542768 | Q17: -0.0028533457 | R17: -0.0014979418 | S17: 0.010903359 | T17: -0.0055030808 | U17: 0.0077090081
A18: Dimson TTF lead/lag | B18: Slope 2s10s | C18: TTF | D18: Iran war (Mar 2026+) | E18: 134 | F18: -0.041489463 | G18: 0.30454446 | H18: -0.14354917 | I18: 0.11052147 | J18: 0.045308316 | K18: 0.50601669 | L18: 0.11658289 | M18: -1.3317722 | N18: 0.31792324 | O18: 0.070806038 | P18: -0.040996616 | Q18: -0.07788894 | R18: -0.31692459 | S18: 0.091223145 | T18: 0.058555932 | U18: 0.031435197

Sheet Mediation
A1: Mediation: how much of the gas effect runs through inflation expectations and policy pricing?
A2: Daily rows: TTF -> inflation swap -> €STR OIS 1y1y (all LSEG closes, synchronous).
A3: Weekly rows: full serial chain TTF -> ILS 1y1y -> OIS 1y1y -> Bund 2Y. CIs: moving-block bootstrap, 2,000 draws.
A4: Effects in bp per 1% TTF (bp_per_10pct_ttf column x10%); path b / d21 coefficients in bp per bp.
A5: Source: src/econometrics.py -> output/tables/10_mediation.csv. Green cells: p < 0.05.
A7: frequency | B7: sample | C7: mediator | D7: n | E7: effect | F7: estimate | G7: ci95_lo | H7: ci95_hi | I7: significant_95 | J7: bp_per_10pct_ttf | K7: share_of_total
A8: daily | B8: Iran war (Mar 2026+) | C8: Infl. swap 1y1y | D8: 143 | E8: Total: TTF -> OIS 1y1y | F8: 0.2438797 | G8: 0.070075952 | H8: 0.47685659 | I8: TRUE | J8: 2.3244218 | K8: 1
A9: daily | B9: Iran war (Mar 2026+) | C9: Infl. swap 1y1y | D9: 143 | E9: Direct: TTF -> OIS 1y1y (not via ILS) | F9: 0.1671112 | G9: -0.025145157 | H9: 0.41101345 | I9: FALSE | J9: 1.5927398 | K9: 0.68521978
A10: daily | B10: Iran war (Mar 2026+) | C10: Infl. swap 1y1y | D10: 143 | E10: Indirect: TTF -> Infl. swap 1y1y -> OIS 1y1y | F10: 0.076768508 | G10: 0.0093217736 | H10: 0.21636921 | I10: TRUE | J10: 0.73168203 | K10: 0.31478022
A11: daily | B11: Iran war (Mar 2026+) | C11: Infl. swap 1y1y | D11: 143 | E11: path a: TTF -> Infl. swap 1y1y (bp per 1%) | F11: 0.18577136 | G11: 0.028332411 | H11: 0.40032733 | I11: TRUE
A12: daily | B12: Iran war (Mar 2026+) | C12: Infl. swap 1y1y | D12: 143 | E12: path b: Infl. swap 1y1y -> OIS 1y1y (bp per bp) | F12: 0.41324189 | G12: 0.1643677 | H12: 0.71007088 | I12: TRUE
A13: daily | B13: Iran war (Mar 2026+) | C13: Infl. swap 1Y | D13: 142 | E13: Total: TTF -> OIS 1y1y | F13: 0.23840099 | G13: 0.06664517 | H13: 0.48717994 | I13: TRUE | J13: 2.2722042 | K13: 1
A14: daily | B14: Iran war (Mar 2026+) | C14: Infl. swap 1Y | D14: 142 | E14: Direct: TTF -> OIS 1y1y (not via ILS) | F14: 0.22229635 | G14: 0.012481463 | H14: 0.45868937 | I14: TRUE | J14: 2.1187105 | K14: 0.93244723
A15: daily | B15: Iran war (Mar 2026+) | C15: Infl. swap 1Y | D15: 142 | E15: Indirect: TTF -> Infl. swap 1Y -> OIS 1y1y | F15: 0.016104648 | G15: -0.023559624 | H15: 0.15905018 | I15: FALSE | J15: 0.15349369 | K15: 0.06755277
A16: daily | B16: Iran war (Mar 2026+) | C16: Infl. swap 1Y | D16: 142 | E16: path a: TTF -> Infl. swap 1Y (bp per 1%) | F16: 0.72174427 | G16: 0.29983878 | H16: 1.1734028 | I16: TRUE
A17: daily | B17: Iran war (Mar 2026+) | C17: Infl. swap 1Y | D17: 142 | E17: path b: Infl. swap 1Y -> OIS 1y1y (bp per bp) | F17: 0.022313509 | G17: -0.041041231 | H17: 0.18464672 | I17: FALSE
A18: daily | B18: Oct 2019 - Oct 2026 | C18: Infl. swap 1y1y | D18: 1633 | E18: Total: TTF -> OIS 1y1y | F18: 0.015596317 | G18: -0.067254112 | H18: 0.09393363 | I18: FALSE | J18: 0.14864877 | K18: 1
A19: daily | B19: Oct 2019 - Oct 2026 | C19: Infl. swap 1y1y | D19: 1633 | E19: Direct: TTF -> OIS 1y1y (not via ILS) | F19: -0.032619945 | G19: -0.11711821 | H19: 0.0527001 | I19: FALSE | J19: -0.31090128 | K19: -2.091516
A20: daily | B20: Oct 2019 - Oct 2026 | C20: Infl. swap 1y1y | D20: 1633 | E20: Indirect: TTF -> Infl. swap 1y1y -> OIS 1y1y | F20: 0.048216261 | G20: 0.019055778 | H20: 0.080877527 | I20: TRUE | J20: 0.45955005 | K20: 3.091516
A21: daily | B21: Oct 2019 - Oct 2026 | C21: Infl. swap 1y1y | D21: 1633 | E21: path a: TTF -> Infl. swap 1y1y (bp per 1%) | F21: 0.14415707 | G21: 0.066288944 | H21: 0.22076432 | I21: TRUE
A22: daily | B22: Oct 2019 - Oct 2026 | C22: Infl. swap 1y1y | D22: 1633 | E22: path b: Infl. swap 1y1y -> OIS 1y1y (bp per bp) | F22: 0.33447031 | G22: 0.17140584 | H22: 0.50817309 | I22: TRUE
A23: daily | B23: Oct 2019 - Oct 2026 | C23: Infl. swap 1Y | D23: 1046 | E23: Total: TTF -> OIS 1y1y | F23: 0.047672033 | G23: -0.061705968 | H23: 0.15130683 | I23: FALSE | J23: 0.454363 | K23: 1
A24: daily | B24: Oct 2019 - Oct 2026 | C24: Infl. swap 1Y | D24: 1046 | E24: Direct: TTF -> OIS 1y1y (not via ILS) | F24: -0.053022249 | G24: -0.15963876 | H24: 0.045170697 | I24: FALSE | J24: -0.50535601 | K24: -1.1122297
A25: daily | B25: Oct 2019 - Oct 2026 | C25: Infl. swap 1Y | D25: 1046 | E25: Indirect: TTF -> Infl. swap 1Y -> OIS 1y1y | F25: 0.10069428 | G25: 0.064929946 | H25: 0.14206813 | I25: TRUE | J25: 0.95971901 | K25: 2.1122297
A26: daily | B26: Oct 2019 - Oct 2026 | C26: Infl. swap 1Y | D26: 1046 | E26: path a: TTF -> Infl. swap 1Y (bp per 1%) | F26: 0.40444411 | G26: 0.2337823 | H26: 0.59698434 | I26: TRUE
A27: daily | B27: Oct 2019 - Oct 2026 | C27: Infl. swap 1Y | D27: 1046 | E27: path b: Infl. swap 1Y -> OIS 1y1y (bp per bp) | F27: 0.24896958 | G27: 0.17462069 | H27: 0.35478777 | I27: TRUE
A28: daily | B28: Apr 2022 - Oct 2026 | C28: Infl. swap 1y1y | D28: 1047 | E28: Total: TTF -> OIS 1y1y | F28: 0.048245878 | G28: -0.064607572 | H28: 0.15079786 | I28: FALSE | J28: 0.45983233 | K28: 1
A29: daily | B29: Apr 2022 - Oct 2026 | C29: Infl. swap 1y1y | D29: 1047 | E29: Direct: TTF -> OIS 1y1y (not via ILS) | F29: 0.016773492 | G29: -0.092217912 | H29: 0.11225756 | I29: FALSE | J29: 0.15986846 | K29: 0.34766685
A30: daily | B30: Apr 2022 - Oct 2026 | C30: Infl. swap 1y1y | D30: 1047 | E30: Indirect: TTF -> Infl. swap 1y1y -> OIS 1y1y | F30: 0.031472385 | G30: 0.0040590935 | H30: 0.074963274 | I30: TRUE | J30: 0.29996387 | K30: 0.65233315
A31: daily | B31: Apr 2022 - Oct 2026 | C31: Infl. swap 1y1y | D31: 1047 | E31: path a: TTF -> Infl. swap 1y1y (bp per 1%) | F31: 0.073292829 | G31: 0.011580301 | H31: 0.1394004 | I31: TRUE
A32: daily | B32: Apr 2022 - Oct 2026 | C32: Infl. swap 1y1y | D32: 1047 | E32: path b: Infl. swap 1y1y -> OIS 1y1y (bp per bp) | F32: 0.42940607 | G32: 0.23803943 | H32: 0.63890659 | I32: TRUE
A33: daily | B33: Apr 2022 - Oct 2026 | C33: Infl. swap 1Y | D33: 1046 | E33: Total: TTF -> OIS 1y1y | F33: 0.047672033 | G33: -0.064325324 | H33: 0.15194554 | I33: FALSE | J33: 0.454363 | K33: 1
A34: daily | B34: Apr 2022 - Oct 2026 | C34: Infl. swap 1Y | D34: 1046 | E34: Direct: TTF -> OIS 1y1y (not via ILS) | F34: -0.053022249 | G34: -0.16365595 | H34: 0.047600864 | I34: FALSE | J34: -0.50535601 | K34: -1.1122297
A35: daily | B35: Apr 2022 - Oct 2026 | C35: Infl. swap 1Y | D35: 1046 | E35: Indirect: TTF -> Infl. swap 1Y -> OIS 1y1y | F35: 0.10069428 | G35: 0.065133119 | H35: 0.14082545 | I35: TRUE | J35: 0.95971901 | K35: 2.1122297
A36: daily | B36: Apr 2022 - Oct 2026 | C36: Infl. swap 1Y | D36: 1046 | E36: path a: TTF -> Infl. swap 1Y (bp per 1%) | F36: 0.40444411 | G36: 0.2366183 | H36: 0.609807 | I36: TRUE
A37: daily | B37: Apr 2022 - Oct 2026 | C37: Infl. swap 1Y | D37: 1046 | E37: path b: Infl. swap 1Y -> OIS 1y1y (bp per bp) | F37: 0.24896958 | G37: 0.17220031 | H37: 0.35988592 | I37: TRUE
A38: weekly | B38: Oct 2019 - Oct 2026 (weekly) | C38: ILS 1y1y + OIS 1y1y | D38: 362 | E38: Total: TTF -> Bund 2Y | F38: -0.092303954 | G38: -0.24551646 | H38: 0.073074369 | I38: FALSE | J38: -0.87975064 | K38: 1
A39: weekly | B39: Oct 2019 - Oct 2026 (weekly) | C39: ILS 1y1y + OIS 1y1y | D39: 362 | E39: Direct: TTF -> Bund 2Y (not via ILS/OIS) | F39: -0.028946946 | G39: -0.12460793 | H39: 0.044900353 | I39: FALSE | J39: -0.27589386 | K39: 0.31360461
A40: weekly | B40: Oct 2019 - Oct 2026 (weekly) | C40: ILS 1y1y + OIS 1y1y | D40: 362 | E40: Indirect: TTF -> ILS 1y1y -> Bund 2Y | F40: -0.0051433133 | G40: -0.018895005 | H40: 0.020576557 | I40: FALSE | J40: -0.049021012 | K40: 0.055721484
A41: weekly | B41: Oct 2019 - Oct 2026 (weekly) | C41: ILS 1y1y + OIS 1y1y | D41: 362 | E41: Indirect: TTF -> OIS 1y1y -> Bund 2Y | F41: -0.072426285 | G41: -0.21301807 | H41: 0.081584077 | I41: FALSE | J41: -0.69029623 | K41: 0.78464987
A42: weekly | B42: Oct 2019 - Oct 2026 (weekly) | C42: ILS 1y1y + OIS 1y1y | D42: 362 | E42: Indirect: TTF -> ILS 1y1y -> OIS 1y1y -> Bund 2Y | F42: 0.01421259 | G42: -0.035711413 | H42: 0.058178201 | I42: FALSE | J42: 0.13546045 | K42: -0.15397596
A43: weekly | B43: Oct 2019 - Oct 2026 (weekly) | C43: ILS 1y1y + OIS 1y1y | D43: 362 | E43: Total indirect | F43: -0.063357008 | G43: -0.19822439 | H43: 0.084416851 | I43: FALSE | J43: -0.60385678 | K43: 0.68639539
A44: weekly | B44: Oct 2019 - Oct 2026 (weekly) | C44: ILS 1y1y + OIS 1y1y | D44: 362 | E44: a1: TTF -> ILS 1y1y (bp per 1%) | F44: 0.062470831 | G44: -0.14941381 | H44: 0.21773896 | I44: FALSE
A45: weekly | B45: Oct 2019 - Oct 2026 (weekly) | C45: ILS 1y1y + OIS 1y1y | D45: 362 | E45: a2: TTF -> OIS 1y1y direct (bp per 1%) | F45: -0.10476835 | G45: -0.32195788 | H45: 0.11864406 | I45: FALSE
A46: weekly | B46: Oct 2019 - Oct 2026 (weekly) | C46: ILS 1y1y + OIS 1y1y | D46: 362 | E46: d21: ILS 1y1y -> OIS 1y1y (bp per bp) | F46: 0.32910148 | G46: 0.11023433 | H46: 0.58530319 | I46: TRUE
A47: weekly | B47: Oct 2019 - Oct 2026 (weekly) | C47: ILS 1y1y + OIS 1y1y | D47: 362 | E47: b1: ILS 1y1y -> Bund 2Y (bp per bp) | F47: -0.082331437 | G47: -0.17344467 | H47: 0.038664341 | I47: FALSE
A48: weekly | B48: Oct 2019 - Oct 2026 (weekly) | C48: ILS 1y1y + OIS 1y1y | D48: 362 | E48: b2: OIS 1y1y -> Bund 2Y (bp per bp) | F48: 0.69129929 | G48: 0.60640115 | H48: 0.77960642 | I48: TRUE
A49: weekly | B49: Apr 2022 - Oct 2026 (weekly) | C49: ILS 1y1y + OIS 1y1y | D49: 232 | E49: Total: TTF -> Bund 2Y | F49: -0.0087288387 | G49: -0.2104964 | H49: 0.20665101 | I49: FALSE | J49: -0.083194718 | K49: 1
A50: weekly | B50: Apr 2022 - Oct 2026 (weekly) | C50: ILS 1y1y + OIS 1y1y | D50: 232 | E50: Direct: TTF -> Bund 2Y (not via ILS/OIS) | F50: -0.046985049 | G50: -0.17941854 | H50: 0.079768753 | I50: FALSE | J50: -0.44781535 | K50: 5.3827377
A51: weekly | B51: Apr 2022 - Oct 2026 (weekly) | C51: ILS 1y1y + OIS 1y1y | D51: 232 | E51: Indirect: TTF -> ILS 1y1y -> Bund 2Y | F51: 0.005889764 | G51: -0.01335562 | H51: 0.055385286 | I51: FALSE | J51: 0.056135446 | K51: -0.67474772
A52: weekly | B52: Apr 2022 - Oct 2026 (weekly) | C52: ILS 1y1y + OIS 1y1y | D52: 232 | E52: Indirect: TTF -> OIS 1y1y -> Bund 2Y | F52: 0.054375277 | G52: -0.10950984 | H52: 0.21889327 | I52: FALSE | J52: 0.51825174 | K52: -6.2293827
A53: weekly | B53: Apr 2022 - Oct 2026 (weekly) | C53: ILS 1y1y + OIS 1y1y | D53: 232 | E53: Indirect: TTF -> ILS 1y1y -> OIS 1y1y -> Bund 2Y | F53: -0.02200883 | G53: -0.11604792 | H53: 0.059453866 | I53: FALSE | J53: -0.20976656 | K53: 2.5213927
A54: weekly | B54: Apr 2022 - Oct 2026 (weekly) | C54: ILS 1y1y + OIS 1y1y | D54: 232 | E54: Total indirect | F54: 0.03825621 | G54: -0.10621346 | H54: 0.19537224 | I54: FALSE | J54: 0.36462063 | K54: -4.3827377
A55: weekly | B55: Apr 2022 - Oct 2026 (weekly) | C55: ILS 1y1y + OIS 1y1y | D55: 232 | E55: a1: TTF -> ILS 1y1y (bp per 1%) | F55: -0.062431236 | G55: -0.31833818 | H55: 0.14730809 | I55: FALSE
A56: weekly | B56: Apr 2022 - Oct 2026 (weekly) | C56: ILS 1y1y + OIS 1y1y | D56: 232 | E56: a2: TTF -> OIS 1y1y direct (bp per 1%) | F56: 0.076740422 | G56: -0.16242697 | H56: 0.30279945 | I56: FALSE
A57: weekly | B57: Apr 2022 - Oct 2026 (weekly) | C57: ILS 1y1y + OIS 1y1y | D57: 232 | E57: d21: ILS 1y1y -> OIS 1y1y (bp per bp) | F57: 0.49752823 | G57: 0.24617404 | H57: 0.88213729 | I57: TRUE
A58: weekly | B58: Apr 2022 - Oct 2026 (weekly) | C58: ILS 1y1y + OIS 1y1y | D58: 232 | E58: b1: ILS 1y1y -> Bund 2Y (bp per bp) | F58: -0.094340018 | G58: -0.22958556 | H58: 0.11146648 | I58: FALSE
A59: weekly | B59: Apr 2022 - Oct 2026 (weekly) | C59: ILS 1y1y + OIS 1y1y | D59: 232 | E59: b2: OIS 1y1y -> Bund 2Y (bp per bp) | F59: 0.70856108 | G59: 0.60437796 | H59: 0.81814955 | I59: TRUE
A60: weekly | B60: Iran war (Mar 2026+) (weekly) | C60: ILS 1y1y + OIS 1y1y | D60: 32 | E60: Total: TTF -> Bund 2Y | F60: 0.24014911 | G60: -0.25674803 | H60: 0.64848635 | I60: FALSE | J60: 2.2888655 | K60: 1
A61: weekly | B61: Iran war (Mar 2026+) (weekly) | C61: ILS 1y1y + OIS 1y1y | D61: 32 | E61: Direct: TTF -> Bund 2Y (not via ILS/OIS) | F61: -0.095759674 | G61: -0.54602018 | H61: 0.017341686 | I61: FALSE | J61: -0.91268717 | K61: -0.3987509
A62: weekly | B62: Iran war (Mar 2026+) (weekly) | C62: ILS 1y1y + OIS 1y1y | D62: 32 | E62: Indirect: TTF -> ILS 1y1y -> Bund 2Y | F62: -0.018828346 | G62: -0.084536577 | H62: 0.066473164 | I62: FALSE | J62: -0.1794533 | K62: -0.078402729
A63: weekly | B63: Iran war (Mar 2026+) (weekly) | C63: ILS 1y1y + OIS 1y1y | D63: 32 | E63: Indirect: TTF -> OIS 1y1y -> Bund 2Y | F63: 0.27502556 | G63: -0.056477542 | H63: 0.81119424 | I63: FALSE | J63: 2.6212736 | K63: 1.1452283
A64: weekly | B64: Iran war (Mar 2026+) (weekly) | C64: ILS 1y1y + OIS 1y1y | D64: 32 | E64: Indirect: TTF -> ILS 1y1y -> OIS 1y1y -> Bund 2Y | F64: 0.079711565 | G64: -0.04159586 | H64: 0.19242167 | I64: FALSE | J64: 0.75973236 | K64: 0.3319253
A65: weekly | B65: Iran war (Mar 2026+) (weekly) | C65: ILS 1y1y + OIS 1y1y | D65: 32 | E65: Total indirect | F65: 0.33590878 | G65: 0.020392061 | H65: 0.86037514 | I65: TRUE | J65: 3.2015527 | K65: 1.3987509
A66: weekly | B66: Iran war (Mar 2026+) (weekly) | C66: ILS 1y1y + OIS 1y1y | D66: 32 | E66: a1: TTF -> ILS 1y1y (bp per 1%) | F66: 0.26962247 | G66: -0.077998817 | H66: 0.54173783 | I66: FALSE
A67: weekly | B67: Iran war (Mar 2026+) (weekly) | C67: ILS 1y1y + OIS 1y1y | D67: 32 | E67: a2: TTF -> OIS 1y1y direct (bp per 1%) | F67: 0.38840229 | G67: -0.090112233 | H67: 1.2119229 | I67: FALSE
A68: weekly | B68: Iran war (Mar 2026+) (weekly) | C68: ILS 1y1y + OIS 1y1y | D68: 32 | E68: d21: ILS 1y1y -> OIS 1y1y (bp per bp) | F68: 0.41751682 | G68: -0.14812526 | H68: 1.0137476 | I68: FALSE
A69: weekly | B69: Iran war (Mar 2026+) (weekly) | C69: ILS 1y1y + OIS 1y1y | D69: 32 | E69: b1: ILS 1y1y -> Bund 2Y (bp per bp) | F69: -0.069832258 | G69: -0.31465821 | H69: 0.28835002 | I69: FALSE
A70: weekly | B70: Iran war (Mar 2026+) (weekly) | C70: ILS 1y1y + OIS 1y1y | D70: 32 | E70: b2: OIS 1y1y -> Bund 2Y (bp per bp) | F70: 0.70809461 | G70: 0.42351928 | H70: 0.90852207 | I70: TRUE

Sheet VAR_Diagnostics
A1: VAR specification & diagnostics
A2: Lag order by BIC. Stable = all roots inside unit circle. Portmanteau H0: residual whiteness.
A3: Source: src/econometrics.py -> output/tables/11a_var_diagnostics.csv. Green cells: p < 0.05.
A5: frequency | B5: sample | C5: variables | D5: n | E5: lag_order_bic | F5: lag_aic | G5: lag_hqic | H5: stable | I5: max_root_modulus | J5: portmanteau_p | K5: normality_p
A6: daily | B6: Oct 2019 - Oct 2026 | C6: Brent, TTF, ILS 1y1y, OIS 1y1y, OIS 2Y | D6: 1632 | E6: 1 | F6: 3 | G6: 0 | H6: TRUE | I6: 0.10683422 | J6: 1.802602e-15 | K6: 0
A7: daily | B7: Iran war (Mar 2026+) | C7: Brent, TTF, ILS 1y1y, OIS 1y1y, OIS 2Y | D7: 142 | E7: 1 | F7: 2 | G7: 0 | H7: TRUE | I7: 0.35934441 | J7: 0.0078163886 | K7: 1.1703107e-26
A8: weekly | B8: Oct 2019 - Oct 2026 (weekly) | C8: Brent, TTF, ILS 1y1y, OIS 1y1y, Bund 2Y, Slope 2s10s | D8: 361 | E8: 1 | F8: 1 | G8: 0 | H8: TRUE | I8: 0.25727135 | J8: 1.038154e-06 | K8: 0

Sheet Granger
A1: Granger causality (VAR-based F tests)
A2: H0: lags of 'cause' do not help predict 'effect'. Daily VAR uses LSEG-synchronous series only.
A3: Source: src/econometrics.py -> output/tables/11b_granger_causality.csv. Green cells: p < 0.05.
A5: frequency | B5: sample | C5: lags | D5: cause | E5: effect | F5: granger_F | G5: granger_p | H5: verdict
A6: daily | B6: Oct 2019 - Oct 2026 | C6: 1 | D6: Brent | E6: TTF | F6: 0.23329906 | G6: 0.62910135 | H6: no predictive content
A7: daily | B7: Oct 2019 - Oct 2026 | C7: 1 | D7: Brent | E7: ILS 1y1y | F7: 6.371464 | G7: 0.01161587 | H7: predicts
A8: daily | B8: Oct 2019 - Oct 2026 | C8: 1 | D8: Brent | E8: OIS 1y1y | F8: 0.45747359 | G8: 0.49882631 | H8: no predictive content
A9: daily | B9: Oct 2019 - Oct 2026 | C9: 1 | D9: Brent | E9: OIS 2Y | F9: 0.33812136 | G9: 0.56093174 | H9: no predictive content
A10: daily | B10: Oct 2019 - Oct 2026 | C10: 1 | D10: TTF | E10: Brent | F10: 0.019116065 | G10: 0.89003768 | H10: no predictive content
A11: daily | B11: Oct 2019 - Oct 2026 | C11: 1 | D11: TTF | E11: ILS 1y1y | F11: 1.3886225 | G11: 0.23867235 | H11: no predictive content
A12: daily | B12: Oct 2019 - Oct 2026 | C12: 1 | D12: TTF | E12: OIS 1y1y | F12: 8.2914475 | G12: 0.003993622 | H12: predicts
A13: daily | B13: Oct 2019 - Oct 2026 | C13: 1 | D13: TTF | E13: OIS 2Y | F13: 7.4933525 | G13: 0.0062061826 | H13: predicts
A14: daily | B14: Oct 2019 - Oct 2026 | C14: 1 | D14: ILS 1y1y | E14: Brent | F14: 0.026883086 | G14: 0.86976622 | H14: no predictive content
A15: daily | B15: Oct 2019 - Oct 2026 | C15: 1 | D15: ILS 1y1y | E15: TTF | F15: 2.2178755 | G15: 0.13645946 | H15: no predictive content
A16: daily | B16: Oct 2019 - Oct 2026 | C16: 1 | D16: ILS 1y1y | E16: OIS 1y1y | F16: 0.21259257 | G16: 0.64475525 | H16: no predictive content
A17: daily | B17: Oct 2019 - Oct 2026 | C17: 1 | D17: ILS 1y1y | E17: OIS 2Y | F17: 0.46758113 | G17: 0.49412156 | H17: no predictive content
... A75: weekly | B75: Oct 2019 - Oct 2026 (weekly) | C75: 1 | D75: Slope 2s10s | E75: Bund 2Y | F75: 1.5977032 | G75: 0.2063677 | H75: no predictive content

Sheet VAR_FEVD
A1: Forecast-error variance decomposition (Cholesky, two orderings)
A2: Share of each variable's forecast-error variance due to each shock. 'Brent first' vs 'TTF first' bounds the gas contribution when oil and gas shocks are correlated.
A3: Source: src/econometrics.py -> output/tables/11c_var_fevd.csv. Green cells: p < 0.05.
A5: frequency | B5: sample | C5: ordering | D5: variable | E5: horizon | F5: share_Brent | G5: share_TTF | H5: share_ILS 1y1y | I5: share_OIS 1y1y | J5: share_OIS 2Y | K5: share_Bund 2Y | L5: share_Slope 2s10s
A6: daily | B6: Oct 2019 - Oct 2026 | C6: Brent first | D6: ILS 1y1y | E6: 1 | F6: 0.1841357 | G6: 0.034890747 | H6: 0.78097355 | I6: 0 | J6: 0
A7: daily | B7: Oct 2019 - Oct 2026 | C7: Brent first | D7: ILS 1y1y | E7: 5 | F7: 0.18835469 | G7: 0.034317749 | H7: 0.77003538 | I7: 0.00074385856 | J7: 0.006548321
A8: daily | B8: Oct 2019 - Oct 2026 | C8: Brent first | D8: ILS 1y1y | E8: 10 | F8: 0.18835469 | G8: 0.034317749 | H8: 0.77003538 | I8: 0.00074385856 | J8: 0.0065483211
A9: daily | B9: Oct 2019 - Oct 2026 | C9: Brent first | D9: OIS 1y1y | E9: 1 | F9: 0.046502077 | G9: 0.00028806282 | H9: 0.039650302 | I9: 0.91355956 | J9: 0
A10: daily | B10: Oct 2019 - Oct 2026 | C10: Brent first | D10: OIS 1y1y | E10: 5 | F10: 0.046009491 | G10: 0.0052826479 | H10: 0.039352653 | I10: 0.90365165 | J10: 0.0057035546
A11: daily | B11: Oct 2019 - Oct 2026 | C11: Brent first | D11: OIS 1y1y | E11: 10 | F11: 0.046009491 | G11: 0.005282648 | H11: 0.039352653 | I11: 0.90365165 | J11: 0.0057035546
A12: daily | B12: Oct 2019 - Oct 2026 | C12: Brent first | D12: OIS 2Y | E12: 1 | F12: 0.051749516 | G12: 0.00033495116 | H12: 0.037683808 | I12: 0.87306393 | J12: 0.037167795
A13: daily | B13: Oct 2019 - Oct 2026 | C13: Brent first | D13: OIS 2Y | E13: 5 | F13: 0.051222129 | G13: 0.0047195717 | H13: 0.037474179 | I13: 0.86424544 | J13: 0.042338682
A14: daily | B14: Oct 2019 - Oct 2026 | C14: Brent first | D14: OIS 2Y | E14: 10 | F14: 0.051222129 | G14: 0.0047195717 | H14: 0.037474179 | I14: 0.86424544 | J14: 0.042338682
A15: daily | B15: Oct 2019 - Oct 2026 | C15: TTF first | D15: ILS 1y1y | E15: 1 | F15: 0.14318258 | G15: 0.075843868 | H15: 0.78097355 | I15: 0 | J15: 0
A16: daily | B16: Oct 2019 - Oct 2026 | C16: TTF first | D16: ILS 1y1y | E16: 5 | F16: 0.14841544 | G16: 0.074256999 | H16: 0.77003538 | I16: 0.00074385856 | J16: 0.006548321
A17: daily | B17: Oct 2019 - Oct 2026 | C17: TTF first | D17: ILS 1y1y | E17: 10 | F17: 0.14841544 | G17: 0.074256999 | H17: 0.77003538 | I17: 0.00074385856 | J17: 0.0065483211
... A41: daily | B41: Iran war (Mar 2026+) | C41: TTF first | D41: OIS 2Y | E41: 10 | F41: 0.19391011 | G41: 0.41307492 | H41: 0.038847159 | I41: 0.33493711 | J41: 0.019230704
A42: weekly | B42: Oct 2019 - Oct 2026 (weekly) | C42: Brent first | D42: ILS 1y1y | E42: 1 | F42: 0.18977826 | G42: 0.0054717507 | H42: 0.80474999 | I42: 0 | K42: 0 | L42: 0
A43: weekly | B43: Oct 2019 - Oct 2026 (weekly) | C43: Brent first | D43: ILS 1y1y | E43: 5 | F43: 0.18635464 | G43: 0.0075806978 | H43: 0.80570093 | I43: 8.895348e-05 | K43: 8.0740399e-06 | L43: 0.00026670527
A44: weekly | B44: Oct 2019 - Oct 2026 (weekly) | C44: Brent first | D44: ILS 1y1y | E44: 10 | F44: 0.18635463 | G44: 0.0075806984 | H44: 0.80570091 | I44: 8.8965358e-05 | K44: 8.0938017e-06 | L44: 0.00026670546
A45: weekly | B45: Oct 2019 - Oct 2026 (weekly) | C45: Brent first | D45: OIS 1y1y | E45: 1 | F45: 0.029973342 | G45: 0.0027414773 | H45: 0.070372079 | I45: 0.8969131 | K45: 0 | L45: 0
A46: weekly | B46: Oct 2019 - Oct 2026 (weekly) | C46: Brent first | D46: OIS 1y1y | E46: 5 | F46: 0.036462653 | G46: 0.0044994637 | H46: 0.087991434 | I46: 0.86667253 | K46: 0.00029279262 | L46: 0.0040811307
A47: weekly | B47: Oct 2019 - Oct 2026 (weekly) | C47: Brent first | D47: OIS 1y1y | E47: 10 | F47: 0.036462648 | G47: 0.0044994772 | H47: 0.087991435 | I47: 0.86667242 | K47: 0.00029288642 | L47: 0.0040811303
A48: weekly | B48: Oct 2019 - Oct 2026 (weekly) | C48: Brent first | D48: Bund 2Y | E48: 1 | F48: 0.020969882 | G48: 0.0076355383 | H48: 0.028802677 | I48: 0.62032625 | K48: 0.32226565 | L48: 0
A49: weekly | B49: Oct 2019 - Oct 2026 (weekly) | C49: Brent first | D49: Bund 2Y | E49: 5 | F49: 0.024784357 | G49: 0.0070017817 | H49: 0.074787214 | I49: 0.57351032 | K49: 0.31611052 | L49: 0.0038058023
A50: weekly | B50: Oct 2019 - Oct 2026 (weekly) | C50: Brent first | D50: Bund 2Y | E50: 10 | F50: 0.024784342 | G50: 0.0070018563 | H50: 0.074787252 | I50: 0.57350991 | K50: 0.31611084 | L50: 0.003805801
A51: weekly | B51: Oct 2019 - Oct 2026 (weekly) | C51: Brent first | D51: Slope 2s10s | E51: 1 | F51: 0.00012508361 | G51: 0.0025027307 | H51: 0.015524379 | I51: 0.027660965 | K51: 0.12493306 | L51: 0.82925379
A52: weekly | B52: Oct 2019 - Oct 2026 (weekly) | C52: Brent first | D52: Slope 2s10s | E52: 5 | F52: 0.0037879217 | G52: 0.0051791535 | H52: 0.04163553 | I52: 0.03314211 | K52: 0.12549627 | L52: 0.79075901
A53: weekly | B53: Oct 2019 - Oct 2026 (weekly) | C53: Brent first | D53: Slope 2s10s | E53: 10 | F53: 0.0037879262 | G53: 0.0051791638 | H53: 0.041635533 | I53: 0.03314214 | K53: 0.12549634 | L53: 0.7907589
... A65: weekly | B65: Oct 2019 - Oct 2026 (weekly) | C65: TTF first | D65: Slope 2s10s | E65: 10 | F65: 0.005640696 | G65: 0.003326394 | H65: 0.041635533 | I65: 0.03314214 | K65: 0.12549634 | L65: 0.7907589

Sheet VAR_IRF
A1: Impulse responses to a 1-s.d. orthogonalised TTF shock
A2: Units: bp (rates) per 1-s.d. TTF shock.
A3: Source: src/econometrics.py -> output/tables/11d_var_irf_ttf_shock.csv. Green cells: p < 0.05.
A5: frequency | B5: sample | C5: ordering | D5: response | E5: horizon | F5: orth_irf | G5: cumulative_irf
A6: daily | B6: Oct 2019 - Oct 2026 | C6: Brent first | D6: ILS 1y1y | E6: 0 | F6: 0.76319128 | G6: 0.76319128
A7: daily | B7: Oct 2019 - Oct 2026 | C7: Brent first | D7: ILS 1y1y | E7: 1 | F7: -0.055233209 | G7: 0.70795807
A8: daily | B8: Oct 2019 - Oct 2026 | C8: Brent first | D8: ILS 1y1y | E8: 2 | F8: 0.00012478581 | G8: 0.70808286
A9: daily | B9: Oct 2019 - Oct 2026 | C9: Brent first | D9: ILS 1y1y | E9: 3 | F9: -0.0018409386 | G9: 0.70624192
A10: daily | B10: Oct 2019 - Oct 2026 | C10: Brent first | D10: ILS 1y1y | E10: 4 | F10: -9.9125053e-05 | G10: 0.7061428
A11: daily | B11: Oct 2019 - Oct 2026 | C11: Brent first | D11: ILS 1y1y | E11: 5 | F11: -2.3657373e-05 | G11: 0.70611914
A12: daily | B12: Oct 2019 - Oct 2026 | C12: Brent first | D12: ILS 1y1y | E12: 6 | F12: -1.3480738e-06 | G12: 0.70611779
A13: daily | B13: Oct 2019 - Oct 2026 | C13: Brent first | D13: ILS 1y1y | E13: 7 | F13: -2.5748492e-07 | G13: 0.70611753
A14: daily | B14: Oct 2019 - Oct 2026 | C14: Brent first | D14: ILS 1y1y | E14: 8 | F14: -1.6169404e-08 | G14: 0.70611752
A15: daily | B15: Oct 2019 - Oct 2026 | C15: Brent first | D15: ILS 1y1y | E15: 9 | F15: -2.8077847e-09 | G15: 0.70611751
A16: daily | B16: Oct 2019 - Oct 2026 | C16: Brent first | D16: ILS 1y1y | E16: 10 | F16: -1.9391881e-10 | G16: 0.70611751
A17: daily | B17: Oct 2019 - Oct 2026 | C17: Brent first | D17: OIS 1y1y | E17: 0 | F17: 0.10200739 | G17: 0.10200739
... A225: weekly | B225: Oct 2019 - Oct 2026 (weekly) | C225: TTF first | D225: Slope 2s10s | E225: 10 | F225: 7.320449e-07 | G225: 0.011779606

Sheet Local_Projections
A1: Local projections: persistence and predictivity
A2: cum_*: y(t+h) - y(t-1) on gas(t) = impact and persistence. pred_*: y(t+h) - y(t+s) on gas(t) = does gas forecast LATER moves? (s=1 for Bundesbank yields to skip the overlapping day). HAC lags h+1.
A3: Source: src/econometrics.py -> output/tables/12_local_projections.csv. Green cells: p < 0.05.
A5: dependent | B5: sample | C5: horizon_days | D5: n | E5: cum_bp_per_10pct | F5: cum_lo95_bp10 | G5: cum_hi95_bp10 | H5: cum_p | I5: pred_window | J5: pred_bp_per_10pct | K5: pred_p | L5: pred_r2
A6: €STR OIS 2Y | B6: Full sample | C6: 0 | D6: 1545 | E6: -0.039626272 | F6: -0.6129176 | G6: 0.53366506 | H6: 0.89223516
A7: €STR OIS 2Y | B7: Full sample | C7: 1 | D7: 1544 | E7: -0.64488475 | F7: -1.4353636 | G7: 0.14559408 | H7: 0.10982104 | I7: t+0 to t+1 | J7: -0.60195146 | K7: 0.05573074 | L7: 0.011716463
A8: €STR OIS 2Y | B8: Full sample | C8: 2 | D8: 1543 | E8: -0.49882342 | F8: -1.4351193 | G8: 0.4374725 | H8: 0.29638609 | I8: t+0 to t+2 | J8: -0.45574063 | K8: 0.24289818 | L8: 0.01107131
A9: €STR OIS 2Y | B9: Full sample | C9: 3 | D9: 1542 | E9: -0.5337363 | F9: -1.7031379 | G9: 0.6356653 | H9: 0.37101171 | I9: t+0 to t+3 | J9: -0.49234978 | K9: 0.28997542 | L9: 0.011610342
A10: €STR OIS 2Y | B10: Full sample | C10: 4 | D10: 1541 | E10: -0.33801095 | F10: -1.6041746 | G10: 0.92815269 | H10: 0.60081055 | I10: t+0 to t+4 | J10: -0.29656125 | K10: 0.57148642 | L10: 0.015437952
A11: €STR OIS 2Y | B11: Full sample | C11: 5 | D11: 1540 | E11: -0.090713368 | F11: -1.4356504 | G11: 1.2542236 | H11: 0.89482755 | I11: t+0 to t+5 | J11: -0.048825877 | K11: 0.93167872 | L11: 0.015367871
A12: €STR OIS 2Y | B12: Full sample | C12: 6 | D12: 1540 | E12: -0.16117115 | F12: -1.8893778 | G12: 1.5670355 | H12: 0.85496436 | I12: t+0 to t+6 | J12: -0.11928366 | K12: 0.87264213 | L12: 0.010096318
A13: €STR OIS 2Y | B13: Full sample | C13: 7 | D13: 1540 | E13: 0.11239056 | F13: -1.7504491 | G13: 1.9752302 | H13: 0.90586757 | I13: t+0 to t+7 | J13: 0.15427805 | K13: 0.84876671 | L13: 0.0079545098
A14: €STR OIS 2Y | B14: Full sample | C14: 8 | D14: 1540 | E14: 0.069256851 | F14: -1.8077081 | G14: 1.9462218 | H14: 0.94234669 | I14: t+0 to t+8 | J14: 0.11114434 | K14: 0.89064927 | L14: 0.0065671746
A15: €STR OIS 2Y | B15: Full sample | C15: 9 | D15: 1539 | E15: 0.060188837 | F15: -1.8468216 | G15: 1.9671993 | H15: 0.9506733 | I15: t+0 to t+9 | J15: 0.098854874 | K15: 0.90273166 | L15: 0.0063436629
A16: €STR OIS 2Y | B16: Full sample | C16: 10 | D16: 1538 | E16: -0.10674061 | F16: -2.1590225 | G16: 1.9455412 | H16: 0.91880354 | I16: t+0 to t+10 | J16: -0.069117704 | K16: 0.93944944 | L16: 0.005726622
A17: €STR OIS 2Y | B17: Full sample | C17: 11 | D17: 1537 | E17: -0.4385332 | F17: -2.6504745 | G17: 1.7734081 | H17: 0.69758387 | I17: t+0 to t+11 | J17: -0.39888334 | K17: 0.68464332 | L17: 0.0076962463
A18: €STR OIS 2Y | B18: Full sample | C18: 12 | D18: 1536 | E18: -0.49846524 | F18: -2.9054979 | G18: 1.9085674 | H18: 0.684823 | I18: t+0 to t+12 | J18: -0.46460863 | K18: 0.67246659 | L18: 0.0074146586
... A26: €STR OIS 2Y | B26: Full sample | C26: 20 | D26: 1528 | E26: -0.44107041 | F26: -3.716415 | G26: 2.8342742 | H26: 0.79182531 | I26: t+0 to t+20 | J26: -0.40205077 | K26: 0.79503603 | L26: 0.0042072941
A27: €STR OIS 2Y | B27: Iran war (Mar 2026+) | C27: 0 | D27: 134 | E27: 2.805443 | F27: -0.023668176 | G27: 5.6345542 | H27: 0.051943373
A28: €STR OIS 2Y | B28: Iran war (Mar 2026+) | C28: 1 | D28: 133 | E28: 1.8536574 | F28: -4.137491 | G28: 7.8448058 | H28: 0.54423408 | I28: t+0 to t+1 | J28: -0.89554873 | K28: 0.72406775 | L28: 0.10461189
A29: €STR OIS 2Y | B29: Iran war (Mar 2026+) | C29: 2 | D29: 132 | E29: 0.62453396 | F29: -4.327127 | G29: 5.5761949 | H29: 0.80474782 | I29: t+0 to t+2 | J29: -2.0749539 | K29: 0.33821466 | L29: 0.097591627
A30: €STR OIS 2Y | B30: Iran war (Mar 2026+) | C30: 3 | D30: 131 | E30: 3.6868949 | F30: -1.9420522 | G30: 9.3158421 | H30: 0.19921992 | I30: t+0 to t+3 | J30: 0.73880702 | K30: 0.7614355 | L30: 0.09297783
A31: €STR OIS 2Y | B31: Iran war (Mar 2026+) | C31: 4 | D31: 130 | E31: 3.4018592 | F31: -2.2879618 | G31: 9.0916803 | H31: 0.24125536 | I31: t+0 to t+4 | J31: 0.4388277 | K31: 0.86489045 | L31: 0.051759495
A32: €STR OIS 2Y | B32: Iran war (Mar 2026+) | C32: 5 | D32: 129 | E32: 2.1039519 | F32: -4.1403895 | G32: 8.3482933 | H32: 0.50899896 | I32: t+0 to t+5 | J32: -0.89382005 | K32: 0.76328343 | L32: 0.075338285
A33: €STR OIS 2Y | B33: Iran war (Mar 2026+) | C33: 6 | D33: 129 | E33: 3.8222869 | F33: -4.2249864 | G33: 11.86956 | H33: 0.35187472 | I33: t+0 to t+6 | J33: 0.82451494 | K33: 0.83357117 | L33: 0.069111272
A34: €STR OIS 2Y | B34: Iran war (Mar 2026+) | C34: 7 | D34: 129 | E34: 2.1799185 | F34: -6.9434648 | G34: 11.303302 | H34: 0.63955754 | I34: t+0 to t+7 | J34: -0.81785344 | K34: 0.85622201 | L34: 0.060367886
A35: €STR OIS 2Y | B35: Iran war (Mar 2026+) | C35: 8 | D35: 129 | E35: 0.12272382 | F35: -9.5586642 | G35: 9.8041118 | H35: 0.98017822 | I35: t+0 to t+8 | J35: -2.8750481 | K35: 0.55398751 | L35: 0.041602762
A36: €STR OIS 2Y | B36: Iran war (Mar 2026+) | C36: 9 | D36: 128 | E36: -0.13323542 | F36: -9.5504665 | G36: 9.2839957 | H36: 0.97787736 | I36: t+0 to t+9 | J36: -3.1810914 | K36: 0.49895012 | L36: 0.05384045
A37: €STR OIS 2Y | B37: Iran war (Mar 2026+) | C37: 10 | D37: 127 | E37: -0.97272128 | F37: -13.135673 | G37: 11.190231 | H37: 0.87544247 | I37: t+0 to t+10 | J37: -4.0712504 | K37: 0.50609502 | L37: 0.069337348
A38: €STR OIS 2Y | B38: Iran war (Mar 2026+) | C38: 11 | D38: 126 | E38: 1.93841 | F38: -9.3753246 | G38: 13.252145 | H38: 0.73701292 | I38: t+0 to t+11 | J38: -1.1568004 | K38: 0.83781792 | L38: 0.090241654
A39: €STR OIS 2Y | B39: Iran war (Mar 2026+) | C39: 12 | D39: 125 | E39: -0.29678176 | F39: -13.469043 | G39: 12.875479 | H39: 0.96477655 | I39: t+0 to t+12 | J39: -3.359459 | K39: 0.61382721 | L39: 0.093549323
... A47: €STR OIS 2Y | B47: Iran war (Mar 2026+) | C47: 20 | D47: 117 | E47: -1.3378602 | F47: -13.220379 | G47: 10.544659 | H47: 0.82534346 | I47: t+0 to t+20 | J47: -4.4492536 | K47: 0.4711402 | L47: 0.071303829
A48: €STR OIS 1y1y | B48: Full sample | C48: 0 | D48: 1545 | E48: -0.079121554 | F48: -0.83823593 | G48: 0.67999282 | H48: 0.83812815
A49: €STR OIS 1y1y | B49: Full sample | C49: 1 | D49: 1544 | E49: -0.87723737 | F49: -1.8965291 | G49: 0.14205438 | H49: 0.091633526 | I49: t+0 to t+1 | J49: -0.79432597 | K49: 0.05201102 | L49: 0.013911885
A50: €STR OIS 1y1y | B50: Full sample | C50: 2 | D50: 1543 | E50: -0.64419638 | F50: -1.9317169 | G50: 0.64332414 | H50: 0.32675851 | I50: t+0 to t+2 | J50: -0.56118592 | K50: 0.29945524 | L50: 0.0096800588
A51: €STR OIS 1y1y | B51: Full sample | C51: 3 | D51: 1542 | E51: -0.64673123 | F51: -2.1705942 | G51: 0.87713171 | H51: 0.40550554 | I51: t+0 to t+3 | J51: -0.56560582 | K51: 0.33847867 | L51: 0.0086566887
A52: €STR OIS 1y1y | B52: Full sample | C52: 4 | D52: 1541 | E52: -0.33999057 | F52: -1.9609068 | G52: 1.2809257 | H52: 0.68098888 | I52: t+0 to t+4 | J52: -0.25920503 | K52: 0.69146655 | L52: 0.012984769
A53: €STR OIS 1y1y | B53: Full sample | C53: 5 | D53: 1540 | E53: -0.064629155 | F53: -1.7909713 | G53: 1.6617129 | H53: 0.94150642 | I53: t+0 to t+5 | J53: 0.016997582 | K53: 0.98109751 | L53: 0.011648513
A54: €STR OIS 1y1y | B54: Full sample | C54: 6 | D54: 1540 | E54: -0.16877055 | F54: -2.4222656 | G54: 2.0847245 | H54: 0.88329787 | I54: t+0 to t+6 | J54: -0.087143814 | K54: 0.92693975 | L54: 0.0073348748
A55: €STR OIS 1y1y | B55: Full sample | C55: 7 | D55: 1540 | E55: 0.11481809 | F55: -2.3672596 | G55: 2.5968958 | H55: 0.9277569 | I55: t+0 to t+7 | J55: 0.19644483 | K55: 0.85188468 | L55: 0.0055417171
A56: €STR OIS 1y1y | B56: Full sample | C56: 8 | D56: 1540 | E56: 0.038842641 | F56: -2.48392 | G56: 2.5616053 | H56: 0.97592521 | I56: t+0 to t+8 | J56: 0.12046938 | K56: 0.90906544 | L56: 0.0042608921
A57: €STR OIS 1y1y | B57: Full sample | C57: 9 | D57: 1539 | E57: 0.013367474 | F57: -2.5818634 | G57: 2.6085984 | H57: 0.99194506 | I57: t+0 to t+9 | J57: 0.089587784 | K57: 0.93295271 | L57: 0.0037620981
A58: €STR OIS 1y1y | B58: Full sample | C58: 10 | D58: 1538 | E58: -0.30065509 | F58: -3.0448596 | G58: 2.4435494 | H58: 0.82997188 | I58: t+0 to t+10 | J58: -0.22565887 | K58: 0.84756328 | L58: 0.0031951342
A59: €STR OIS 1y1y | B59: Full sample | C59: 11 | D59: 1537 | E59: -0.74413768 | F59: -3.7477406 | G59: 2.2594652 | H59: 0.62726018 | I59: t+0 to t+11 | J59: -0.66772726 | K59: 0.6065659 | L59: 0.0047614838
A60: €STR OIS 1y1y | B60: Full sample | C60: 12 | D60: 1536 | E60: -0.82463196 | F60: -4.1103665 | G60: 2.4611026 | H60: 0.62278448 | I60: t+0 to t+12 | J60: -0.75541482 | K60: 0.60687439 | L60: 0.0044484419
... A68: €STR OIS 1y1y | B68: Full sample | C68: 20 | D68: 1528 | E68: -0.80016518 | F68: -5.2863203 | G68: 3.68599 | H68: 0.72664495 | I68: t+0 to t+20 | J68: -0.7239705 | K68: 0.72763379 | L68: 0.0023112427
A69: €STR OIS 1y1y | B69: Iran war (Mar 2026+) | C69: 0 | D69: 134 | E69: 3.1671033 | F69: 0.15623431 | G69: 6.1779723 | H69: 0.039235868
A70: €STR OIS 1y1y | B70: Iran war (Mar 2026+) | C70: 1 | D70: 133 | E70: 1.5986501 | F70: -5.0810064 | G70: 8.2783066 | H70: 0.63900594 | I70: t+0 to t+1 | J70: -1.502602 | K70: 0.61154833 | L70: 0.10686286
A71: €STR OIS 1y1y | B71: Iran war (Mar 2026+) | C71: 2 | D71: 132 | E71: 0.021621457 | F71: -5.6122382 | G71: 5.6554811 | H71: 0.99399835 | I71: t+0 to t+2 | J71: -3.0246618 | K71: 0.23709312 | L71: 0.10315852
A72: €STR OIS 1y1y | B72: Iran war (Mar 2026+) | C72: 3 | D72: 131 | E72: 3.7320854 | F72: -2.3676732 | G72: 9.8318441 | H72: 0.23044656 | I72: t+0 to t+3 | J72: 0.36376039 | K72: 0.89257324 | L72: 0.088632447
A73: €STR OIS 1y1y | B73: Iran war (Mar 2026+) | C73: 4 | D73: 130 | E73: 3.8189938 | F73: -2.3561001 | G73: 9.9940876 | H73: 0.22544953 | I73: t+0 to t+4 | J73: 0.41321105 | K73: 0.88777578 | L73: 0.05689081
A74: €STR OIS 1y1y | B74: Iran war (Mar 2026+) | C74: 5 | D74: 129 | E74: 2.3778728 | F74: -4.3513645 | G74: 9.1071101 | H74: 0.48856425 | I74: t+0 to t+5 | J74: -1.0827852 | K74: 0.74087901 | L74: 0.088520742
A75: €STR OIS 1y1y | B75: Iran war (Mar 2026+) | C75: 6 | D75: 129 | E75: 4.6075305 | F75: -4.4397337 | G75: 13.654795 | H75: 0.31819414 | I75: t+0 to t+6 | J75: 1.1468725 | K75: 0.79683427 | L75: 0.083502164
A76: €STR OIS 1y1y | B76: Iran war (Mar 2026+) | C76: 7 | D76: 129 | E76: 3.3029844 | F76: -6.7554754 | G76: 13.361444 | H76: 0.51982036 | I76: t+0 to t+7 | J76: -0.15767359 | K76: 0.97483528 | L76: 0.074588366
A77: €STR OIS 1y1y | B77: Iran war (Mar 2026+) | C77: 8 | D77: 129 | E77: 0.51424659 | F77: -10.132064 | G77: 11.160557 | H77: 0.92457418 | I77: t+0 to t+8 | J77: -2.9464114 | K77: 0.58293095 | L77: 0.048740704
A78: €STR OIS 1y1y | B78: Iran war (Mar 2026+) | C78: 9 | D78: 128 | E78: 0.21499801 | F78: -10.104823 | G78: 10.534819 | H78: 0.9674285 | I78: t+0 to t+9 | J78: -3.3254832 | K78: 0.51814703 | L78: 0.060105764
A79: €STR OIS 1y1y | B79: Iran war (Mar 2026+) | C79: 10 | D79: 127 | E79: -1.0076094 | F79: -14.705931 | G79: 12.690712 | H79: 0.88536466 | I79: t+0 to t+10 | J79: -4.6050454 | K79: 0.50287245 | L79: 0.075251678
A80: €STR OIS 1y1y | B80: Iran war (Mar 2026+) | C80: 11 | D80: 126 | E80: 2.6687169 | F80: -10.156775 | G80: 15.494209 | H80: 0.68339477 | I80: t+0 to t+11 | J80: -0.95010367 | K80: 0.88163777 | L80: 0.085341583
A81: €STR OIS 1y1y | B81: Iran war (Mar 2026+) | C81: 12 | D81: 125 | E81: -0.09521494 | F81: -15.331277 | G81: 15.140847 | H81: 0.99022723 | I81: t+0 to t+12 | J81: -3.6699854 | K81: 0.63174856 | L81: 0.089160026
... A89: €STR OIS 1y1y | B89: Iran war (Mar 2026+) | C89: 20 | D89: 117 | E89: -0.68664255 | F89: -14.64776 | G89: 13.274475 | H89: 0.92320473 | I89: t+0 to t+20 | J89: -4.3324369 | K89: 0.54859023 | L89: 0.064796817
A90: Infl. swap 1y1y | B90: Full sample | C90: 0 | D90: 2364 | E90: 1.3298799 | F90: 0.73817807 | G90: 1.9215817 | H90: 1.056865e-05
A91: Infl. swap 1y1y | B91: Full sample | C91: 1 | D91: 2363 | E91: 1.1925194 | F91: 0.43726914 | G91: 1.9477697 | H91: 0.0019695489 | I91: t+0 to t+1 | J91: -0.13820818 | K91: 0.61720319 | L91: 0.0080587323
A92: Infl. swap 1y1y | B92: Full sample | C92: 2 | D92: 2362 | E92: 1.084099 | F92: 0.1273067 | G92: 2.0408913 | H92: 0.026365239 | I92: t+0 to t+2 | J92: -0.24651718 | K92: 0.53590471 | L92: 0.0032517696
A93: Infl. swap 1y1y | B93: Full sample | C93: 3 | D93: 2361 | E93: 0.68930797 | F93: -0.48695355 | G93: 1.8655695 | H93: 0.25072459 | I93: t+0 to t+3 | J93: -0.6411824 | K93: 0.21649495 | L93: 0.0037401591
A94: Infl. swap 1y1y | B94: Full sample | C94: 4 | D94: 2360 | E94: 1.0118057 | F94: -0.22784612 | G94: 2.2514576 | H94: 0.10965295 | I94: t+0 to t+4 | J94: -0.3202603 | K94: 0.54406889 | L94: 0.0040119363
A95: Infl. swap 1y1y | B95: Full sample | C95: 5 | D95: 2359 | E95: 1.1680482 | F95: -0.04464161 | G95: 2.380738 | H95: 0.059046311 | I95: t+0 to t+5 | J95: -0.16499948 | K95: 0.74918088 | L95: 0.0060609463
A96: Infl. swap 1y1y | B96: Full sample | C96: 6 | D96: 2359 | E96: 0.80598171 | F96: -0.49658435 | G96: 2.1085478 | H96: 0.22521451 | I96: t+0 to t+6 | J96: -0.52706594 | K96: 0.37788668 | L96: 0.0079521755
A97: Infl. swap 1y1y | B97: Full sample | C97: 7 | D97: 2359 | E97: 0.32430632 | F97: -1.094727 | G97: 1.7433397 | H97: 0.65419721 | I97: t+0 to t+7 | J97: -1.0087413 | K97: 0.13654838 | L97: 0.011222993
A98: Infl. swap 1y1y | B98: Full sample | C98: 8 | D98: 2359 | E98: 0.61064906 | F98: -1.0469643 | G98: 2.2682624 | H98: 0.47026654 | I98: t+0 to t+8 | J98: -0.72239859 | K98: 0.30959819 | L98: 0.012335046
A99: Infl. swap 1y1y | B99: Full sample | C99: 9 | D99: 2358 | E99: 0.49240653 | F99: -0.99569397 | G99: 1.980507 | H99: 0.51662527 | I99: t+0 to t+9 | J99: -0.84155699 | K99: 0.22048706 | L99: 0.013606443
A100: Infl. swap 1y1y | B100: Full sample | C100: 10 | D100: 2357 | E100: 0.15967009 | F100: -1.2329501 | G100: 1.5522903 | H100: 0.822195 | I100: t+0 to t+10 | J100: -1.1746765 | K100: 0.10820849 | L100: 0.01341357
A101: Infl. swap 1y1y | B101: Full sample | C101: 11 | D101: 2356 | E101: -0.069816187 | F101: -1.5636127 | G101: 1.4239804 | H101: 0.92701162 | I101: t+0 to t+11 | J101: -1.4065369 | K101: 0.049602047 | L101: 0.012614398
A102: Infl. swap 1y1y | B102: Full sample | C102: 12 | D102: 2355 | E102: -0.18326272 | F102: -1.8636579 | G102: 1.4971324 | H102: 0.83073716 | I102: t+0 to t+12 | J102: -1.5213759 | K102: 0.05001475 | L102: 0.011712905
... A110: Infl. swap 1y1y | B110: Full sample | C110: 20 | D110: 2347 | E110: -0.38369007 | F110: -2.3580285 | G110: 1.5906484 | H110: 0.70327481 | I110: t+0 to t+20 | J110: -1.7067457 | K110: 0.079071206 | L110: 0.0079544886
A111: Infl. swap 1y1y | B111: Iran war (Mar 2026+) | C111: 0 | D111: 134 | E111: 1.8101064 | F111: 0.17504487 | G111: 3.4451679 | H111: 0.030019589
A112: Infl. swap 1y1y | B112: Iran war (Mar 2026+) | C112: 1 | D112: 133 | E112: 0.27746062 | F112: -2.9673286 | G112: 3.5222498 | H112: 0.86689891 | I112: t+0 to t+1 | J112: -1.5597539 | K112: 0.28644164 | L112: 0.11132237
A113: Infl. swap 1y1y | B113: Iran war (Mar 2026+) | C113: 2 | D113: 132 | E113: -1.6246599 | F113: -5.5444681 | G113: 2.2951482 | H113: 0.41657952 | I113: t+0 to t+2 | J113: -3.4291792 | K113: 0.05801375 | L113: 0.11351815
A114: Infl. swap 1y1y | B114: Iran war (Mar 2026+) | C114: 3 | D114: 131 | E114: 0.30665614 | F114: -3.9385916 | G114: 4.5519039 | H114: 0.88741105 | I114: t+0 to t+3 | J114: -1.5440813 | K114: 0.44082641 | L114: 0.06770441
A115: Infl. swap 1y1y | B115: Iran war (Mar 2026+) | C115: 4 | D115: 130 | E115: -1.387712 | F115: -5.2303787 | G115: 2.4549547 | H115: 0.47905718 | I115: t+0 to t+4 | J115: -3.2510774 | K115: 0.057641535 | L115: 0.065202881
A116: Infl. swap 1y1y | B116: Iran war (Mar 2026+) | C116: 5 | D116: 129 | E116: -1.6144303 | F116: -5.9328284 | G116: 2.7039678 | H116: 0.46371414 | I116: t+0 to t+5 | J116: -3.4545845 | K116: 0.081533793 | L116: 0.10439057
A117: Infl. swap 1y1y | B117: Iran war (Mar 2026+) | C117: 6 | D117: 129 | E117: -1.3997701 | F117: -8.0986874 | G117: 5.2991471 | H117: 0.68213521 | I117: t+0 to t+6 | J117: -3.2399244 | K117: 0.28858089 | L117: 0.08935798
A118: Infl. swap 1y1y | B118: Iran war (Mar 2026+) | C118: 7 | D118: 129 | E118: -1.5887032 | F118: -9.2575566 | G118: 6.0801501 | H118: 0.68471349 | I118: t+0 to t+7 | J118: -3.4288574 | K118: 0.31874237 | L118: 0.054854987
A119: Infl. swap 1y1y | B119: Iran war (Mar 2026+) | C119: 8 | D119: 129 | E119: -2.8518878 | F119: -11.142117 | G119: 5.4383415 | H119: 0.5001514 | I119: t+0 to t+8 | J119: -4.692042 | K119: 0.2304168 | L119: 0.055095559
A120: Infl. swap 1y1y | B120: Iran war (Mar 2026+) | C120: 9 | D120: 128 | E120: -3.3860145 | F120: -11.044121 | G120: 4.2720918 | H120: 0.38615595 | I120: t+0 to t+9 | J120: -5.2304176 | K120: 0.14006794 | L120: 0.07020408
A121: Infl. swap 1y1y | B121: Iran war (Mar 2026+) | C121: 10 | D121: 127 | E121: -4.374791 | F121: -13.146649 | G121: 4.3970673 | H121: 0.3283161 | I121: t+0 to t+10 | J121: -6.2193246 | K121: 0.13019325 | L121: 0.064636104
A122: Infl. swap 1y1y | B122: Iran war (Mar 2026+) | C122: 11 | D122: 126 | E122: -4.0027678 | F122: -13.29896 | G122: 5.2934247 | H122: 0.39870316 | I122: t+0 to t+11 | J122: -5.8871693 | K122: 0.18285689 | L122: 0.07180082
A123: Infl. swap 1y1y | B123: Iran war (Mar 2026+) | C123: 12 | D123: 125 | E123: -7.1739558 | F123: -16.481227 | G123: 2.1333152 | H123: 0.13085233 | I123: t+0 to t+12 | J123: -9.0775574 | K123: 0.034574539 | L123: 0.09906846
... A131: Infl. swap 1y1y | B131: Iran war (Mar 2026+) | C131: 20 | D131: 117 | E131: -8.4505778 | F131: -14.12582 | G131: -2.7753354 | H131: 0.0035173229 | I131: t+0 to t+20 | J131: -9.8231378 | K131: 0.00013537758 | L131: 0.10228324
A132: Bund 2Y | B132: Full sample | C132: 0 | D132: 2631 | E132: -0.072896105 | F132: -0.6265382 | G132: 0.48074599 | H132: 0.79635574
A133: Bund 2Y | B133: Full sample | C133: 1 | D133: 2630 | E133: -0.40248911 | F133: -1.219191 | G133: 0.41421274 | H133: 0.33407808
A134: Bund 2Y | B134: Full sample | C134: 2 | D134: 2629 | E134: -0.63129576 | F134: -1.6108291 | G134: 0.34823761 | H134: 0.20651983 | I134: t+1 to t+2 | J134: -0.22880528 | K134: 0.40915319 | L134: 0.01352162
A135: Bund 2Y | B135: Full sample | C135: 3 | D135: 2628 | E135: -0.79349752 | F135: -1.8952298 | G135: 0.30823476 | H135: 0.15805444 | I135: t+1 to t+3 | J135: -0.39005598 | K135: 0.29445094 | L135: 0.015630499
A136: Bund 2Y | B136: Full sample | C136: 4 | D136: 2627 | E136: -0.65230552 | F136: -1.8717702 | G136: 0.56715911 | H136: 0.29444223 | I136: t+1 to t+4 | J136: -0.24511198 | K136: 0.56265854 | L136: 0.00721753
A137: Bund 2Y | B137: Full sample | C137: 5 | D137: 2626 | E137: -0.30163478 | F137: -1.5779612 | G137: 0.97469166 | H137: 0.64321553 | I137: t+1 to t+5 | J137: 0.10286568 | K137: 0.82973406 | L137: 0.0042363312
A138: Bund 2Y | B138: Full sample | C138: 6 | D138: 2626 | E138: -0.39359818 | F138: -1.9451081 | G138: 1.1579118 | H138: 0.61902908 | I138: t+1 to t+6 | J138: 0.010902277 | K138: 0.98527734 | L138: 0.0027367042
A139: Bund 2Y | B139: Full sample | C139: 7 | D139: 2626 | E139: -0.50275901 | F139: -2.153297 | G139: 1.1477789 | H139: 0.55049261 | I139: t+1 to t+7 | J139: -0.098258557 | K139: 0.88187695 | L139: 0.0035264254
A140: Bund 2Y | B140: Full sample | C140: 8 | D140: 2626 | E140: -0.53732987 | F140: -2.1727271 | G140: 1.0980673 | H140: 0.51958702 | I140: t+1 to t+8 | J140: -0.13282942 | K140: 0.8461412 | L140: 0.003780351
A141: Bund 2Y | B141: Full sample | C141: 9 | D141: 2625 | E141: -0.24627879 | F141: -1.9372316 | G141: 1.444674 | H141: 0.77528856 | I141: t+1 to t+9 | J141: 0.16553192 | K141: 0.80923731 | L141: 0.0018040207
A142: Bund 2Y | B142: Full sample | C142: 10 | D142: 2624 | E142: -0.49265152 | F142: -2.3124964 | G142: 1.3271933 | H142: 0.59570083 | I142: t+1 to t+10 | J142: -0.080589433 | K142: 0.91229736 | L142: 0.0014922361
A143: Bund 2Y | B143: Full sample | C143: 11 | D143: 2623 | E143: -0.58344489 | F143: -2.4569922 | G143: 1.2901024 | H143: 0.54161853 | I143: t+1 to t+11 | J143: -0.17325947 | K143: 0.82792624 | L143: 0.0014755488
...

Sheet OOS_Forecast
A1: Out-of-sample forecasting of next week's move
A2: Expanding window. OOS R2 > 0 = beats benchmark. Clark-West: one-sided test for nested models (H0 equal accuracy).
A3: Source: src/econometrics.py -> output/tables/13_oos_forecast.csv. Green cells: p < 0.05.
A5: target | B5: evaluation | C5: n_forecasts | D5: predictor_timing | E5: model | F5: benchmark | G5: rmse_model | H5: rmse_benchmark | I5: oos_r2 | J5: clark_west_t | K5: clark_west_p | L5: beats_benchmark_5pct
A6: €STR OIS 2Y (next week) | B6: Oct 2020 - Oct 2026 | C6: 310 | D6: Fri-Fri | E6: gas only | F6: no change | G6: 11.25362 | H6: 11.218816 | I6: -0.0062142299 | J6: 0.47280172 | K6: 0.31817732 | L6: FALSE
A7: €STR OIS 2Y (next week) | B7: Oct 2020 - Oct 2026 | C7: 310 | D7: Fri-Fri | E7: gas + Brent + own lag | F7: no change | G7: 11.332216 | H7: 11.218816 | I7: -0.020318146 | J7: 0.57248255 | K7: 0.28349755 | L7: FALSE
A8: €STR OIS 2Y (next week) | B8: Oct 2020 - Oct 2026 | C8: 310 | D8: Fri-Fri | E8: gas only | F8: historical mean | G8: 11.25362 | H8: 11.199074 | I8: -0.0097649866 | J8: -1.8816666 | K8: 0.97005935 | L8: FALSE
A9: €STR OIS 2Y (next week) | B9: Oct 2020 - Oct 2026 | C9: 310 | D9: Fri-Fri | E9: gas + Brent + own lag | F9: historical mean | G9: 11.332216 | H9: 11.199074 | I9: -0.023918673 | J9: 0.0084980692 | K9: 0.4966098 | L9: FALSE
A10: €STR OIS 2Y (next week) | B10: Iran war only | C10: 31 | D10: Fri-Fri | E10: gas only | F10: no change | G10: 11.332992 | H10: 11.563168 | I10: 0.039415606 | J10: 1.6965133 | K10: 0.044894358 | L10: TRUE
A11: €STR OIS 2Y (next week) | B11: Iran war only | C11: 31 | D11: Fri-Fri | E11: gas + Brent + own lag | F11: no change | G11: 11.147185 | H11: 11.563168 | I11: 0.070655376 | J11: 1.539018 | K11: 0.061899948 | L11: FALSE
A12: €STR OIS 2Y (next week) | B12: Iran war only | C12: 31 | D12: Fri-Fri | E12: gas only | F12: historical mean | G12: 11.332992 | H12: 11.400838 | I12: 0.011866439 | J12: 1.8140521 | K12: 0.03483485 | L12: TRUE
A13: €STR OIS 2Y (next week) | B13: Iran war only | C13: 31 | D13: Fri-Fri | E13: gas + Brent + own lag | F13: historical mean | G13: 11.147185 | H13: 11.400838 | I13: 0.044002152 | J13: 1.1590696 | K13: 0.12321392 | L13: FALSE
A14: €STR OIS 1y1y (next week) | B14: Oct 2020 - Oct 2026 | C14: 309 | D14: Fri-Fri | E14: gas only | F14: no change | G14: 14.697813 | H14: 14.62819 | I14: -0.0095417704 | J14: -0.038976413 | K14: 0.5155454 | L14: FALSE
A15: €STR OIS 1y1y (next week) | B15: Oct 2020 - Oct 2026 | C15: 309 | D15: Fri-Fri | E15: gas + Brent + own lag | F15: no change | G15: 14.848997 | H15: 14.62819 | I15: -0.030417192 | J15: -0.48942507 | K15: 0.6877296 | L15: FALSE
A16: €STR OIS 1y1y (next week) | B16: Oct 2020 - Oct 2026 | C16: 309 | D16: Fri-Fri | E16: gas only | F16: historical mean | G16: 14.697813 | H16: 14.628852 | I16: -0.0094503512 | J16: -1.0567874 | K16: 0.85469569 | L16: FALSE
A17: €STR OIS 1y1y (next week) | B17: Oct 2020 - Oct 2026 | C17: 309 | D17: Fri-Fri | E17: gas + Brent + own lag | F17: historical mean | G17: 14.848997 | H17: 14.628852 | I17: -0.030323883 | J17: -0.99166489 | K17: 0.83931949 | L17: FALSE
... A53: Slope 2s10s (next week) | B53: Iran war only | C53: 31 | D53: Fri-Thu (lagged 1 day) | E53: gas + Brent + own lag | F53: historical mean | G53: 5.7549333 | H53: 5.7263781 | I53: -0.0099980704 | J53: -0.32431172 | K53: 0.62714898 | L53: FALSE

Sheet HICP_Passthrough
A1: Gas and oil pass-through to realised euro-area HICP
A2: Model A: m/m HICP on 0-12 monthly lags of TTF and Brent (EUR) + month dummies; cumulative effect in pp of price level per +10%.
A3: Model B: HICP y/y on 12-month energy price changes lagged L months (lag scan).
A4: Source: src/econometrics.py -> output/tables/14_hicp_passthrough.csv. Green cells: p < 0.05.
A6: model | B6: lag_months | C6: gas_coef | D6: gas_p | E6: cum_gas_pp_per_10pct | F6: oil_coef | G6: oil_p | H6: cum_oil_pp_per_10pct | I6: joint_gas_all_lags_p | J6: granger_gas_lags1to12_p | K6: gas_lags0to6_p | L6: joint_oil_p | M6: r2 | N6: n_months
A7: A: m/m distributed lag | B7: 0 | C7: -0.0025061763 | D7: 0.16631693 | E7: -0.023886411 | F7: 0.015888336 | G7: 7.5992053e-06 | H7: 0.15143201
A8: A: m/m distributed lag | B8: 1 | C8: 0.00093110387 | D8: 0.49893821 | E8: -0.015012044 | F8: 0.0031415164 | G8: 0.13954474 | H8: 0.18137386
A9: A: m/m distributed lag | B9: 2 | C9: 0.00061805956 | D9: 0.73788619 | E9: -0.0091213067 | F9: 0.0036245064 | G9: 0.18581188 | H9: 0.2159191
A10: A: m/m distributed lag | B10: 3 | C10: 0.0039157858 | D10: 0.070202478 | E10: 0.028200118 | F10: -0.0033982074 | G10: 0.17033082 | H10: 0.18353072
A11: A: m/m distributed lag | B11: 4 | C11: -0.0019304466 | D11: 0.099411613 | E11: 0.009800997 | F11: 0.0076962021 | G11: 0.0024083066 | H11: 0.25688336
A12: A: m/m distributed lag | B12: 5 | C12: 0.0013932955 | D12: 0.34454522 | E12: 0.023080522 | F12: 0.0030845487 | G12: 0.25606497 | H12: 0.28628225
A13: A: m/m distributed lag | B13: 6 | C13: 0.00071271638 | D13: 0.67092948 | E13: 0.029873434 | F13: 0.0018687984 | G13: 0.48837695 | H13: 0.3040938
A14: A: m/m distributed lag | B14: 7 | C14: 0.0015586365 | D14: 0.36083127 | E14: 0.044728827 | F14: 0.0016041532 | G14: 0.6673809 | H14: 0.31938302
A15: A: m/m distributed lag | B15: 8 | C15: 0.0017285028 | D15: 0.16501524 | E15: 0.061203218 | F15: 0.0088274499 | G15: 0.0021488225 | H15: 0.4035176
A16: A: m/m distributed lag | B16: 9 | C16: -0.00038668485 | D16: 0.77419391 | E16: 0.057517718 | F16: -0.0043760202 | G16: 0.082305875 | H16: 0.36180967
A17: A: m/m distributed lag | B17: 10 | C17: 0.0012501963 | D17: 0.48510721 | E17: 0.069433361 | F17: -0.00072780322 | G17: 0.77092882 | H17: 0.35487297
A18: A: m/m distributed lag | B18: 11 | C18: 0.0017938426 | D18: 0.16544836 | E18: 0.086530507 | F18: 0.0037945308 | G18: 0.13559041 | H18: 0.39103871
A19: A: m/m distributed lag | B19: 12 | C19: 0.0013675709 | D19: 0.37155186 | E19: 0.09956485 | F19: 0.0043540359 | G19: 0.037509129 | H19: 0.4325371
A20: A: joint tests | I20: 0.00045287037 | J20: 0.00028093663 | K20: 0.068439035 | L20: 4.1038888e-10 | M20: 0.80711471 | N20: 129
A21: B: y/y on 12m changes, lag scan | B21: 0 | C21: -0.00086341317 | D21: 0.91780129 | E21: -0.0082292064 | F21: 0.031611121 | G21: 0.011306099 | H21: 0.30128616 | M21: 0.16881158 | N21: 130
A22: B: y/y on 12m changes, lag scan | B22: 1 | C22: 0.0025486759 | D22: 0.75073906 | E22: 0.024291476 | F22: 0.029417638 | G22: 0.013023085 | H22: 0.28038004 | M22: 0.21772723 | N22: 129
A23: B: y/y on 12m changes, lag scan | B23: 2 | C23: 0.0065791222 | D23: 0.40469292 | E23: 0.062705732 | F23: 0.024926998 | G23: 0.029963146 | H23: 0.23757966 | M23: 0.27023783 | N23: 128
A24: B: y/y on 12m changes, lag scan | B24: 3 | C24: 0.010004927 | D24: 0.21550732 | E24: 0.09535714 | F24: 0.020959371 | G24: 0.076071737 | H24: 0.19976414 | M24: 0.32768355 | N24: 127
A25: B: y/y on 12m changes, lag scan | B25: 4 | C25: 0.011740246 | D25: 0.14684357 | E25: 0.1118965 | F25: 0.020655757 | G25: 0.093478825 | H25: 0.19687039 | M25: 0.38982638 | N25: 126
A26: B: y/y on 12m changes, lag scan | B26: 5 | C26: 0.013494459 | D26: 0.10162728 | E26: 0.12861593 | F26: 0.019754236 | G26: 0.1299853 | H26: 0.18827798 | M26: 0.44884789 | N26: 125
A27: B: y/y on 12m changes, lag scan | B27: 6 | C27: 0.015492686 | D27: 0.064724881 | E27: 0.14766107 | F27: 0.017482107 | G27: 0.18522796 | H27: 0.16662228 | M27: 0.50102354 | N27: 124
A28: B: y/y on 12m changes, lag scan | B28: 7 | C28: 0.017648205 | D28: 0.040166722 | E28: 0.16820536 | F28: 0.013729634 | G28: 0.30408217 | H28: 0.13085739 | M28: 0.53979883 | N28: 123
A29: B: y/y on 12m changes, lag scan | B29: 8 | C29: 0.019578422 | D29: 0.027567612 | E29: 0.18660229 | F29: 0.009658786 | G29: 0.47196685 | H29: 0.092058063 | M29: 0.56512334 | N29: 122
A30: B: y/y on 12m changes, lag scan | B30: 9 | C30: 0.02165374 | D30: 0.020186679 | E30: 0.20638219 | F30: 0.004025706 | G30: 0.76729144 | H30: 0.038369077 | M30: 0.57521861 | N30: 121
A31: B: y/y on 12m changes, lag scan | B31: 10 | C31: 0.023445985 | D31: 0.016022549 | E31: 0.2234641 | F31: -0.0011863995 | G31: 0.93164212 | H31: -0.011307595 | M31: 0.58204543 | N31: 120
A32: B: y/y on 12m changes, lag scan | B32: 11 | C32: 0.024510808 | D32: 0.011262739 | E32: 0.23361295 | F32: -0.0052351898 | G32: 0.70262702 | H32: -0.049896688 | M32: 0.57509887 | N32: 119
A33: B: y/y on 12m changes, lag scan | B33: 12 | C33: 0.025416637 | D33: 0.0073237663 | E33: 0.24224643 | F33: -0.0097434696 | G33: 0.47114037 | H33: -0.092865184 | M33: 0.55695452 | N33: 118

Sheet Curve_PCA
A1: Bund curve principal components and their gas sensitivity
A2: PC1 = level, PC2 = slope (+ = steepening), PC3 = curvature. Sensitivities in bp per +10% TTF.
A3: Source: src/econometrics.py -> output/tables/16_curve_pca.csv. Green cells: p < 0.05.
A5: block | B5: item | C5: PC1_level | D5: PC2_slope | E5: PC3_curvature | F5: PC1_level_p | G5: PC2_slope_p | H5: PC3_curvature_p
A6: loadings | B6: bun2y | C6: 0.43254918 | D6: -0.62839244 | E6: -0.64449108
A7: loadings | B7: bun5y | C7: 0.52556055 | D7: -0.3238525 | E7: 0.63091748
A8: loadings | B8: bun10y | C8: 0.53920244 | D8: 0.1942534 | E8: 0.23524673
A9: loadings | B9: bun30y | C9: 0.49593148 | D9: 0.68007949 | E9: -0.36226146
A10: variance share | B10: share of daily curve variance | C10: 0.84511539 | D10: 0.12207178 | E10: 0.021373123
A11: TTF total effect, bp per +10% | B11: 2014-21 pre-crisis | C11: 1.6241769 | D11: 0.7487022 | E11: -0.12237925 | F11: 0.0092990267 | G11: 0.0021671207 | H11: 0.31503266
A12: TTF total effect, bp per +10% | B12: 2021-22 gas crisis | C12: -2.5841622 | D12: 0.1171949 | E12: 0.074882549 | F12: 0.034237265 | G12: 0.75610985 | H12: 0.61150187
A13: TTF total effect, bp per +10% | B13: 2023-Feb26 normalisation | C13: -1.0938676 | D13: -0.28110899 | E13: 0.052028081 | F13: 0.55049926 | G13: 0.56035509 | H13: 0.76186115
A14: TTF total effect, bp per +10% | B14: Iran war (Mar 2026+) | C14: 3.6265118 | D14: -2.8310276 | E14: -1.1167339 | F14: 0.11753263 | G14: 0.016198308 | H14: 0.0044500945

Sheet Curve_Slopes
A1: Which flattener carries gas? All Bund slopes compared
A2: Slope = long yield minus short yield, bp. Sensitivities in bp of slope change per +10% TTF (negative = flattening). Daily = same + previous day (timing-adjusted); weekly = Fri-Fri.
A3: Lower rows: how each slope actually moved during the war. Tenor moves: second table below.
A4: Source: src/econometrics.py -> output/tables/17_curve_slopes.csv. Green cells: p < 0.05.
A6: slope | B6: 2014-21 pre-crisis: bp per +10% TTF | C6: 2014-21 pre-crisis: p | D6: 2021-22 gas crisis: bp per +10% TTF | E6: 2021-22 gas crisis: p | F6: 2023-Feb26 normalisation: bp per +10% TTF | G6: 2023-Feb26 normalisation: p | H6: Iran war (Mar 2026+): bp per +10% TTF | I6: Iran war (Mar 2026+): p | J6: war weekly: bp per +10% TTF | K6: war weekly: p | L6: war daily: Brent bp per +10% | M6: war daily: Brent p | N6: war daily: R2 | O6: war vs base: p | P6: level 27 Feb 2026 (bp) | Q6: level 9 Oct 2026 (bp) | R6: change during war (bp) | S6: war onset 2-day (bp) | T6: ceasefire 2-day (bp) | U6: percentile since 2014 (now)
A7: 2s5s | B7: 0.22353593 | C7: 0.20492606 | D7: -0.11302175 | E7: 0.70796039 | F7: -0.066523899 | G7: 0.79947031 | H7: -2.0687261 | I7: 0.0064782215 | J7: -0.37173987 | K7: 0.48332077 | L7: 0.20301399 | M7: 0.75769388 | N7: 0.10643827 | O7: 0.006523934 | P7: 25 | Q7: 14 | R7: -11 | S7: -1 | T7: 4 | U7: 0.48589239
A8: 2s10s | B8: 0.68071539 | C8: 0.015943059 | D8: -0.10789108 | E8: 0.7817904 | F8: -0.37875752 | G8: 0.3713471 | H8: -2.7564003 | I8: 0.031231742 | J8: -1.5195558 | K8: 0.092154401 | L8: -0.471958 | M8: 0.6255376 | N8: 0.15240947 | O8: 0.040860266 | P8: 66 | Q8: 38 | R8: -28 | S8: -5 | T8: 7 | U8: 0.38090551
A9: 5s10s | B9: 0.45717946 | C9: 0.013281001 | D9: 0.0051306633 | E9: 0.98103203 | F9: -0.31223362 | G9: 0.18951101 | H9: -0.68767415 | I9: 0.28522164 | J9: -1.147816 | K9: 0.007807478 | L9: -0.67497199 | M9: 0.20307663 | N9: 0.15366535 | O9: 0.30526925 | P9: 41 | Q9: 24 | R9: -17 | S9: -4 | T9: 3 | U9: 0.34448819
A10: 10s30s | B10: 0.36781586 | C10: 0.05575866 | D10: 0.1152347 | E10: 0.60987386 | F10: 0.0034908587 | G10: 0.98911391 | H10: -1.1368683 | I10: 0.07130765 | J10: -1.4901101 | K10: 9.7690227e-06 | L10: -1.7173529 | M10: 0.011910746 | N10: 0.28459178 | O10: 0.036848143 | P10: 67 | Q10: 38 | R10: -29 | S10: -5 | T10: 3 | U10: 0.29658793
A11: 2s30s | B11: 1.0485313 | C11: 0.0023984975 | D11: 0.0073436132 | E11: 0.98903047 | F11: -0.37526666 | G11: 0.52202195 | H11: -3.8932685 | I11: 0.014863687 | J11: -3.009666 | K11: 0.0092828569 | L11: -2.1893109 | M11: 0.1148193 | N11: 0.25323678 | O11: 0.017524365 | P11: 133 | Q11: 76 | R11: -57 | S11: -10 | T11: 10 | U11: 0.33169291
A12: 5s30s | B12: 0.82499532 | C12: 0.0032426279 | D12: 0.12036536 | E12: 0.74460134 | F12: -0.30874277 | G12: 0.48145175 | H12: -1.8245424 | I12: 0.072024703 | J12: -2.6379261 | K12: 0.00022200501 | L12: -2.3923249 | M12: 0.016315122 | N12: 0.29502064 | O12: 0.067772966 | P12: 108 | Q12: 62 | R12: -46 | S12: -9 | T12: 6 | U12: 0.32185039
A14: Bund yield change by tenor, 27 Feb - 9 Oct 2026
A15: tenor | B15: yield 27 Feb 2026 (%) | C15: yield 9 Oct 2026 (%) | D15: change (bp)
A16: 2Y | B16: 2.03 | C16: 3.09 | D16: 106
A17: 5Y | B17: 2.28 | C17: 3.23 | D17: 95
A18: 7Y | B18: 2.43 | C18: 3.35 | D18: 92
A19: 10Y | B19: 2.69 | C19: 3.47 | D19: 78
A20: 15Y | B20: 3.07 | C20: 3.73 | D20: 66
A21: 20Y | B21: 3.26 | C21: 3.84 | D21: 58
A22: 30Y | B22: 3.36 | C22: 3.85 | D22: 49

Sheet OLS_Fit
A1: OLS transmission regressions: specification and fit statistics
A2: One row per regression. Daily: dy(t) = a + b g(t) + c o(t) + d e(t) [+ the same at t-1 for Bundesbank series] + u(t); g, o, e = 100 x log change of TTF, Brent, EURUSD; dy in bp. Weekly: Fri-Fri changes.
A3: hac_lags = Newey-West lags floor(4 (T/100)^(2/9)). robust_F = HAC Wald test that all slopes are zero. ttf_total = (b0 + b1) x 100 ln(1.1), bp per +10% TTF.
A4: Source: src/econometrics.py -> output/tables/18b_ols_fit.csv. Green cells: p < 0.05.
A6: frequency | B6: regime | C6: dependent | D6: n | E6: sample_start | F6: sample_end | G6: regressors | H6: hac_lags | I6: r2 | J6: adj_r2 | K6: robust_F | L6: robust_F_p | M6: resid_se_bp | N6: durbin_watson | O6: aic | P6: bic | Q6: ttf_total_bp_per_10pct | R6: ttf_total_se | S6: ttf_total_p
A7: daily | B7: 2014-21 pre-crisis | C7: Infl. swap 1y1y | D7: 1271 | E7: 2016-01-05 | F7: 2021-06-29 | G7: 3 | H7: 7 | I7: 0.19489918 | J7: 0.19299286 | K7: 24.939646 | L7: 1.1151086e-15 | M7: 2.0372484 | N7: 1.9244924 | O7: 5419.8228 | P7: 5440.413 | Q7: 0.34640216 | R7: 0.18551837 | S7: 0.061871969
A8: daily | B8: 2014-21 pre-crisis | C8: €STR OIS 1y1y | D8: 403 | E8: 2019-10-04 | F8: 2021-06-29 | G8: 3 | H8: 5 | I8: 0.031897092 | J8: 0.024618123 | K8: 1.5337926 | L8: 0.205198 | M8: 1.5943838 | N8: 1.98607 | O8: 1523.6333 | P8: 1539.629 | Q8: 0.24952772 | R8: 0.17948369 | S8: 0.1644521
A9: daily | B9: 2014-21 pre-crisis | C9: €STR OIS 2Y | D9: 404 | E9: 2019-09-27 | F9: 2021-06-29 | G9: 3 | H9: 5 | I9: 0.04063163 | J9: 0.033436368 | K9: 1.523732 | L9: 0.20779099 | M9: 1.1354887 | N9: 2.0195719 | O9: 1253.1494 | P9: 1269.1551 | Q9: 0.14378236 | R9: 0.12092244 | S9: 0.23442151
A10: daily | B10: 2014-21 pre-crisis | C10: Bund 2Y | D10: 1473 | E10: 2014-10-14 | F10: 2021-06-29 | G10: 6 | H10: 7 | I10: 0.02394434 | J10: 0.019949569 | K10: 1.7792844 | L10: 0.099762483 | M10: 1.8057437 | N10: 2.1515117 | O10: 5928.1812 | P10: 5965.2466 | Q10: 0.31087629 | R10: 0.19512708 | S10: 0.11111553
A11: daily | B11: 2014-21 pre-crisis | C11: Bund 5Y | D11: 1473 | E11: 2014-10-14 | F11: 2021-06-29 | G11: 6 | H11: 7 | I11: 0.025207525 | J11: 0.021217924 | K11: 2.3736658 | L11: 0.027557463 | M11: 2.6958249 | N11: 2.0305021 | O11: 7108.7369 | P11: 7145.8023 | Q11: 0.53441222 | R11: 0.28000521 | S11: 0.056316347
A12: daily | B12: 2014-21 pre-crisis | C12: Bund 10Y | D12: 1473 | E12: 2014-10-14 | F12: 2021-06-29 | G12: 6 | H12: 7 | I12: 0.024830494 | J12: 0.02083935 | K12: 2.0647954 | L12: 0.05453103 | M12: 3.5766291 | N12: 2.0200124 | O12: 7941.6198 | P12: 7978.6852 | Q12: 0.99159168 | R12: 0.39011574 | S12: 0.011028691
A13: daily | B13: 2014-21 pre-crisis | C13: Bund 30Y | D13: 1473 | E13: 2014-10-14 | F13: 2021-06-29 | G13: 6 | H13: 7 | I13: 0.02788453 | J13: 0.023905885 | K13: 2.8737883 | L13: 0.0086939794 | M13: 4.3043855 | N13: 2.0422062 | O13: 8487.2591 | P13: 8524.3245 | Q13: 1.3594075 | R13: 0.45285726 | S13: 0.0026834828
A14: daily | B14: 2014-21 pre-crisis | C14: Slope 2s5s | D14: 1473 | E14: 2014-10-14 | F14: 2021-06-29 | G14: 6 | H14: 7 | I14: 0.0087180287 | J14: 0.0046609401 | K14: 1.9182728 | L14: 0.074618669 | M14: 1.7644998 | N14: 2.2522288 | O14: 5860.1132 | P14: 5897.1786 | Q14: 0.22353593 | R14: 0.17634004 | S14: 0.20492606
A15: daily | B15: 2014-21 pre-crisis | C15: Slope 2s10s | D15: 1473 | E15: 2014-10-14 | F15: 2021-06-29 | G15: 6 | H15: 7 | I15: 0.012554618 | J15: 0.0085132314 | K15: 1.9105555 | L15: 0.075845952 | M15: 2.7869729 | N15: 2.0883519 | O15: 7206.6967 | P15: 7243.7621 | Q15: 0.68071539 | R15: 0.28242915 | S15: 0.015943059
A16: daily | B16: 2014-21 pre-crisis | C16: Slope 2s30s | D16: 1473 | E16: 2014-10-14 | F16: 2021-06-29 | G16: 6 | H16: 7 | I16: 0.016729523 | J16: 0.012705223 | K16: 3.0817692 | L16: 0.0053065755 | M16: 3.7384137 | N16: 2.1152236 | O16: 8071.9526 | P16: 8109.018 | Q16: 1.0485313 | R16: 0.34538182 | S16: 0.0023984975
A17: daily | B17: 2014-21 pre-crisis | C17: Slope 5s30s | D17: 1473 | E17: 2014-10-14 | F17: 2021-06-29 | G17: 6 | H17: 7 | I17: 0.016490646 | J17: 0.012465369 | K17: 3.2432603 | L17: 0.0036000531 | M17: 3.0552948 | N17: 2.1449197 | O17: 7477.4931 | P17: 7514.5585 | Q17: 0.82499532 | R17: 0.28025328 | S17: 0.0032426279
A18: daily | B18: 2021-22 gas crisis | C18: Infl. swap 1Y | D18: 169 | E18: 2022-04-11 | F18: 2022-12-29 | G18: 3 | H18: 4 | I18: 0.20154335 | J18: 0.18702595 | K18: 3.7939972 | L18: 0.011513293 | M18: 13.08159 | N18: 1.5888079 | O18: 1352.6207 | P18: 1365.1403 | Q18: 6.4891979 | R18: 2.2206845 | S18: 0.0034761174
... A101: weekly | B101: Full sample | C101: Slope 5s30s | D101: 620 | E101: 2014-10-17 | F101: 2026-10-09 | G101: 3 | H101: 5 | I101: 0.0056462538 | J101: 0.00080362189 | K101: 0.728311 | L101: 0.53533709 | M101: 6.557948 | N101: 2.1572727 | O101: 4095.5112 | P101: 4113.2301 | Q101: -0.30487518 | R101: 0.35599255 | S101: 0.39177167

Sheet OLS_Coefficients
A1: OLS transmission regressions: every coefficient
A2: Coefficients in bp per 1% move of the regressor; Newey-West HAC standard errors. Filter by frequency, regime and dependent variable.
A3: Source: src/econometrics.py -> output/tables/18_ols_coefficients.csv. Green cells: p < 0.05.
A5: frequency | B5: regime | C5: dependent | D5: regressor | E5: coef | F5: hac_se | G5: t | H5: p
A6: daily | B6: 2014-21 pre-crisis | C6: Infl. swap 1y1y | D6: Constant | E6: 0.01505285 | F6: 0.060640194 | G6: 0.24823222 | H6: 0.80395474
A7: daily | B7: 2014-21 pre-crisis | C7: Infl. swap 1y1y | D7: TTF (t) | E7: 0.036344717 | F7: 0.019464696 | G7: 1.8672121 | H7: 0.061871969
A8: daily | B8: 2014-21 pre-crisis | C8: Infl. swap 1y1y | D8: Brent (t) | E8: 0.35747478 | F8: 0.051123756 | G8: 6.9923419 | H8: 2.7033501e-12
A9: daily | B9: 2014-21 pre-crisis | C9: Infl. swap 1y1y | D9: EURUSD (t) | E9: 0.45069476 | F9: 0.20920636 | G9: 2.1543071 | H9: 0.031216093
A10: daily | B10: 2014-21 pre-crisis | C10: €STR OIS 1y1y | D10: Constant | E10: 0.079915919 | F10: 0.079802339 | G10: 1.0014233 | H10: 0.31662222
A11: daily | B11: 2014-21 pre-crisis | C11: €STR OIS 1y1y | D11: TTF (t) | E11: 0.026180595 | F11: 0.018831534 | G11: 1.3902529 | H11: 0.1644521
A12: daily | B12: 2014-21 pre-crisis | C12: €STR OIS 1y1y | D12: Brent (t) | E12: 0.029582581 | F12: 0.04880484 | G12: 0.60614031 | H12: 0.54442159
A13: daily | B13: 2014-21 pre-crisis | C13: €STR OIS 1y1y | D13: EURUSD (t) | E13: -0.53661356 | F13: 0.38057437 | G13: -1.4100097 | H13: 0.15853681
A14: daily | B14: 2014-21 pre-crisis | C14: €STR OIS 2Y | D14: Constant | E14: 0.063090247 | F14: 0.057606003 | G14: 1.0952026 | H14: 0.27342787
A15: daily | B15: 2014-21 pre-crisis | C15: €STR OIS 2Y | D15: TTF (t) | E15: 0.01508573 | F15: 0.012687254 | G15: 1.1890461 | H15: 0.23442151
A16: daily | B16: 2014-21 pre-crisis | C16: €STR OIS 2Y | D16: Brent (t) | E16: 0.034340712 | F16: 0.039579477 | G16: 0.86763935 | H16: 0.3855918
A17: daily | B17: 2014-21 pre-crisis | C17: €STR OIS 2Y | D17: EURUSD (t) | E17: -0.39821196 | F17: 0.3140451 | G17: -1.2680088 | H17: 0.2047948
... A505: weekly | B505: Full sample | C505: Slope 5s30s | D505: EURUSD (t) | E505: 0.33013931 | F505: 0.33836117 | G505: 0.97570095 | H505: 0.32921268

Sheet Rolling_Betas
A1: Rolling 120-day TTF sensitivity (bp per +10%)
A2: Stepped weekly. 95% band from HAC SEs.
A3: Source: src/econometrics.py -> output/tables/08_rolling_betas_120d.csv. Green cells: p < 0.05.
A5: date | B5: dependent | C5: bp_per_10pct_ttf | D5: lo95_bp10 | E5: hi95_bp10
A6: 2016-07-20 | B6: Bund 2Y | C6: 1.0889339 | D6: -0.02290809 | E6: 2.2007758
A7: 2016-07-27 | B7: Bund 2Y | C7: 1.8398677 | D7: 0.80205132 | E7: 2.8776841
A8: 2016-08-08 | B8: Bund 2Y | C8: 1.8393078 | D8: 0.79266778 | E8: 2.8859478
A9: 2016-08-15 | B9: Bund 2Y | C9: 1.4953238 | D9: 0.35434767 | E9: 2.6362999
A10: 2016-08-22 | B10: Bund 2Y | C10: 1.1683931 | D10: 0.081083109 | E10: 2.255703
A11: 2016-08-29 | B11: Bund 2Y | C11: 0.80414232 | D11: -0.23478088 | E11: 1.8430655
A12: 2016-09-08 | B12: Bund 2Y | C12: 1.0036924 | D12: -0.20984425 | E12: 2.217229
A13: 2016-09-15 | B13: Bund 2Y | C13: 0.7932646 | D13: -0.36169042 | E13: 1.9482196
A14: 2016-09-22 | B14: Bund 2Y | C14: 0.68803562 | D14: -0.40068771 | E14: 1.776759
A15: 2016-09-29 | B15: Bund 2Y | C15: 1.0453486 | D15: -0.07615108 | E15: 2.1668483
A16: 2016-10-11 | B16: Bund 2Y | C16: 1.1123817 | D16: 0.022748847 | E16: 2.2020145
A17: 2016-10-18 | B17: Bund 2Y | C17: 1.1538042 | D17: 0.068579458 | E17: 2.2390289
... A1689: 2026-10-08 | B1689: Slope 2s10s | C1689: -0.67379174 | D1689: -3.0791375 | E1689: 1.731554

Sheet Event_Study
A1: Event study: key war and policy dates (levels; changes computed by formula)
A2: Bund yields are snapshotted before the close, so the 2-day change (t-1 -> t+1) is the comparable window for them. Rates (%) converted to bp; spreads already in bp; prices as % change.
A3: Source: output/tables/15_event_study.csv (levels). Change columns are live formulas.
A5: event_date | B5: event | C5: variable | D5: level_t-1 | E5: level_t | F5: level_t+1 | G5: 1-day change | H5: 2-day change | I5: unit
A6: 2026-03-02 | B6: War onset: Hormuz closure / Qatar LNG halt (first trading day) | C6: TTF (EUR/MWh) | D6: 31.959 | E6: 44.506 | F6: 54.29 | G6: =IF(COUNT(D6,E6)=2,E6/D6-1,"") | H6: =IF(COUNT(D6,F6)=2,F6/D6-1,"") | I6: %
A7: 2026-03-02 | B7: War onset: Hormuz closure / Qatar LNG halt (first trading day) | C7: Brent (USD/bbl) | D7: 72.48 | E7: 77.74 | F7: 81.4 | G7: =IF(COUNT(D7,E7)=2,E7/D7-1,"") | H7: =IF(COUNT(D7,F7)=2,F7/D7-1,"") | I7: %
A8: 2026-03-02 | B8: War onset: Hormuz closure / Qatar LNG halt (first trading day) | C8: ILS 1Y (%) | D8: 1.817 | E8: 1.977 | F8: 2.219 | G8: =IF(COUNT(D8,E8)=2,(E8-D8)*100,"") | H8: =IF(COUNT(D8,F8)=2,(F8-D8)*100,"") | I8: bp
A9: 2026-03-02 | B9: War onset: Hormuz closure / Qatar LNG halt (first trading day) | C9: ILS 1y1y (%) | D9: 1.7424 | E9: 1.8122 | F9: 1.8844 | G9: =IF(COUNT(D9,E9)=2,(E9-D9)*100,"") | H9: =IF(COUNT(D9,F9)=2,(F9-D9)*100,"") | I9: bp
A10: 2026-03-02 | B10: War onset: Hormuz closure / Qatar LNG halt (first trading day) | C10: OIS 1y1y (%) | D10: 1.9462059 | E10: 2.0102104 | F10: 2.0885212 | G10: =IF(COUNT(D10,E10)=2,(E10-D10)*100,"") | H10: =IF(COUNT(D10,F10)=2,(F10-D10)*100,"") | I10: bp
A11: 2026-03-02 | B11: War onset: Hormuz closure / Qatar LNG halt (first trading day) | C11: OIS 2Y (%) | D11: 1.9216 | E11: 1.9776 | F11: 2.042 | G11: =IF(COUNT(D11,E11)=2,(E11-D11)*100,"") | H11: =IF(COUNT(D11,F11)=2,(F11-D11)*100,"") | I11: bp
A12: 2026-03-02 | B12: War onset: Hormuz closure / Qatar LNG halt (first trading day) | C12: Bund 2Y (%) | D12: 2.03 | E12: 2.03 | F12: 2.19 | G12: =IF(COUNT(D12,E12)=2,(E12-D12)*100,"") | H12: =IF(COUNT(D12,F12)=2,(F12-D12)*100,"") | I12: bp
A13: 2026-03-02 | B13: War onset: Hormuz closure / Qatar LNG halt (first trading day) | C13: Bund 5Y (%) | D13: 2.28 | E13: 2.27 | F13: 2.43 | G13: =IF(COUNT(D13,E13)=2,(E13-D13)*100,"") | H13: =IF(COUNT(D13,F13)=2,(F13-D13)*100,"") | I13: bp
A14: 2026-03-02 | B14: War onset: Hormuz closure / Qatar LNG halt (first trading day) | C14: Bund 10Y (%) | D14: 2.69 | E14: 2.66 | F14: 2.8 | G14: =IF(COUNT(D14,E14)=2,(E14-D14)*100,"") | H14: =IF(COUNT(D14,F14)=2,(F14-D14)*100,"") | I14: bp
A15: 2026-03-02 | B15: War onset: Hormuz closure / Qatar LNG halt (first trading day) | C15: Bund 30Y (%) | D15: 3.36 | E15: 3.33 | F15: 3.42 | G15: =IF(COUNT(D15,E15)=2,(E15-D15)*100,"") | H15: =IF(COUNT(D15,F15)=2,(F15-D15)*100,"") | I15: bp
A16: 2026-03-02 | B16: War onset: Hormuz closure / Qatar LNG halt (first trading day) | C16: 2s10s (bp) | D16: 66 | E16: 63 | F16: 61 | G16: =IF(COUNT(D16,E16)=2,E16-D16,"") | H16: =IF(COUNT(D16,F16)=2,F16-D16,"") | I16: bp
A17: 2026-03-02 | B17: War onset: Hormuz closure / Qatar LNG halt (first trading day) | C17: 5Y swap spread (bp) | D17: 7.045 | F17: 21.15 | G17: =IF(COUNT(D17,E17)=2,E17-D17,"") | H17: =IF(COUNT(D17,F17)=2,F17-D17,"") | I17: bp
A18: 2026-03-03 | B18: Day 2: TTF +22%, Ras Laffan output halted | C18: TTF (EUR/MWh) | D18: 44.506 | E18: 54.29 | F18: 48.767 | G18: =IF(COUNT(D18,E18)=2,E18/D18-1,"") | H18: =IF(COUNT(D18,F18)=2,F18/D18-1,"") | I18: %
A19: 2026-03-03 | B19: Day 2: TTF +22%, Ras Laffan output halted | C19: Brent (USD/bbl) | D19: 77.74 | E19: 81.4 | F19: 81.4 | G19: =IF(COUNT(D19,E19)=2,E19/D19-1,"") | H19: =IF(COUNT(D19,F19)=2,F19/D19-1,"") | I19: %
A20: 2026-03-03 | B20: Day 2: TTF +22%, Ras Laffan output halted | C20: ILS 1Y (%) | D20: 1.977 | E20: 2.219 | F20: 2.159 | G20: =IF(COUNT(D20,E20)=2,(E20-D20)*100,"") | H20: =IF(COUNT(D20,F20)=2,(F20-D20)*100,"") | I20: bp
A21: 2026-03-03 | B21: Day 2: TTF +22%, Ras Laffan output halted | C21: ILS 1y1y (%) | D21: 1.8122 | E21: 1.8844 | F21: 1.8232 | G21: =IF(COUNT(D21,E21)=2,(E21-D21)*100,"") | H21: =IF(COUNT(D21,F21)=2,(F21-D21)*100,"") | I21: bp
A22: 2026-03-03 | B22: Day 2: TTF +22%, Ras Laffan output halted | C22: OIS 1y1y (%) | D22: 2.0102104 | E22: 2.0885212 | F22: 2.0576136 | G22: =IF(COUNT(D22,E22)=2,(E22-D22)*100,"") | H22: =IF(COUNT(D22,F22)=2,(F22-D22)*100,"") | I22: bp
A23: 2026-03-03 | B23: Day 2: TTF +22%, Ras Laffan output halted | C23: OIS 2Y (%) | D23: 1.9776 | E23: 2.042 | F23: 2.0203 | G23: =IF(COUNT(D23,E23)=2,(E23-D23)*100,"") | H23: =IF(COUNT(D23,F23)=2,(F23-D23)*100,"") | I23: bp
A24: 2026-03-03 | B24: Day 2: TTF +22%, Ras Laffan output halted | C24: Bund 2Y (%) | D24: 2.03 | E24: 2.19 | F24: 2.17 | G24: =IF(COUNT(D24,E24)=2,(E24-D24)*100,"") | H24: =IF(COUNT(D24,F24)=2,(F24-D24)*100,"") | I24: bp
A25: 2026-03-03 | B25: Day 2: TTF +22%, Ras Laffan output halted | C25: Bund 5Y (%) | D25: 2.27 | E25: 2.43 | F25: 2.39 | G25: =IF(COUNT(D25,E25)=2,(E25-D25)*100,"") | H25: =IF(COUNT(D25,F25)=2,(F25-D25)*100,"") | I25: bp
A26: 2026-03-03 | B26: Day 2: TTF +22%, Ras Laffan output halted | C26: Bund 10Y (%) | D26: 2.66 | E26: 2.8 | F26: 2.76 | G26: =IF(COUNT(D26,E26)=2,(E26-D26)*100,"") | H26: =IF(COUNT(D26,F26)=2,(F26-D26)*100,"") | I26: bp
A27: 2026-03-03 | B27: Day 2: TTF +22%, Ras Laffan output halted | C27: Bund 30Y (%) | D27: 3.33 | E27: 3.42 | F27: 3.41 | G27: =IF(COUNT(D27,E27)=2,(E27-D27)*100,"") | H27: =IF(COUNT(D27,F27)=2,(F27-D27)*100,"") | I27: bp
A28: 2026-03-03 | B28: Day 2: TTF +22%, Ras Laffan output halted | C28: 2s10s (bp) | D28: 63 | E28: 61 | F28: 59 | G28: =IF(COUNT(D28,E28)=2,E28-D28,"") | H28: =IF(COUNT(D28,F28)=2,F28-D28,"") | I28: bp
A29: 2026-03-03 | B29: Day 2: TTF +22%, Ras Laffan output halted | C29: 5Y swap spread (bp) | E29: 21.15 | F29: 10.81 | G29: =IF(COUNT(D29,E29)=2,E29-D29,"") | H29: =IF(COUNT(D29,F29)=2,F29-D29,"") | I29: bp
A30: 2026-03-04 | B30: Large TTF day (-10.7%) | C30: TTF (EUR/MWh) | D30: 54.29 | E30: 48.767 | F30: 50.731 | G30: =IF(COUNT(D30,E30)=2,E30/D30-1,"") | H30: =IF(COUNT(D30,F30)=2,F30/D30-1,"") | I30: %
A31: 2026-03-04 | B31: Large TTF day (-10.7%) | C31: Brent (USD/bbl) | D31: 81.4 | E31: 81.4 | F31: 85.41 | G31: =IF(COUNT(D31,E31)=2,E31/D31-1,"") | H31: =IF(COUNT(D31,F31)=2,F31/D31-1,"") | I31: %
A32: 2026-03-04 | B32: Large TTF day (-10.7%) | C32: ILS 1Y (%) | D32: 2.219 | E32: 2.159 | F32: 2.259 | G32: =IF(COUNT(D32,E32)=2,(E32-D32)*100,"") | H32: =IF(COUNT(D32,F32)=2,(F32-D32)*100,"") | I32: bp
A33: 2026-03-04 | B33: Large TTF day (-10.7%) | C33: ILS 1y1y (%) | D33: 1.8844 | E33: 1.8232 | F33: 1.8605 | G33: =IF(COUNT(D33,E33)=2,(E33-D33)*100,"") | H33: =IF(COUNT(D33,F33)=2,(F33-D33)*100,"") | I33: bp
A34: 2026-03-04 | B34: Large TTF day (-10.7%) | C34: OIS 1y1y (%) | D34: 2.0885212 | E34: 2.0576136 | F34: 2.2066541 | G34: =IF(COUNT(D34,E34)=2,(E34-D34)*100,"") | H34: =IF(COUNT(D34,F34)=2,(F34-D34)*100,"") | I34: bp
A35: 2026-03-04 | B35: Large TTF day (-10.7%) | C35: OIS 2Y (%) | D35: 2.042 | E35: 2.0203 | F35: 2.1323 | G35: =IF(COUNT(D35,E35)=2,(E35-D35)*100,"") | H35: =IF(COUNT(D35,F35)=2,(F35-D35)*100,"") | I35: bp
A36: 2026-03-04 | B36: Large TTF day (-10.7%) | C36: Bund 2Y (%) | D36: 2.19 | E36: 2.17 | F36: 2.18 | G36: =IF(COUNT(D36,E36)=2,(E36-D36)*100,"") | H36: =IF(COUNT(D36,F36)=2,(F36-D36)*100,"") | I36: bp
A37: 2026-03-04 | B37: Large TTF day (-10.7%) | C37: Bund 5Y (%) | D37: 2.43 | E37: 2.39 | F37: 2.42 | G37: =IF(COUNT(D37,E37)=2,(E37-D37)*100,"") | H37: =IF(COUNT(D37,F37)=2,(F37-D37)*100,"") | I37: bp
A38: 2026-03-04 | B38: Large TTF day (-10.7%) | C38: Bund 10Y (%) | D38: 2.8 | E38: 2.76 | F38: 2.79 | G38: =IF(COUNT(D38,E38)=2,(E38-D38)*100,"") | H38: =IF(COUNT(D38,F38)=2,(F38-D38)*100,"") | I38: bp
A39: 2026-03-04 | B39: Large TTF day (-10.7%) | C39: Bund 30Y (%) | D39: 3.42 | E39: 3.41 | F39: 3.42 | G39: =IF(COUNT(D39,E39)=2,(E39-D39)*100,"") | H39: =IF(COUNT(D39,F39)=2,(F39-D39)*100,"") | I39: bp
A40: 2026-03-04 | B40: Large TTF day (-10.7%) | C40: 2s10s (bp) | D40: 61 | E40: 59 | F40: 61 | G40: =IF(COUNT(D40,E40)=2,E40-D40,"") | H40: =IF(COUNT(D40,F40)=2,F40-D40,"") | I40: bp
A41: 2026-03-04 | B41: Large TTF day (-10.7%) | C41: 5Y swap spread (bp) | D41: 21.15 | E41: 10.81 | F41: 20.505 | G41: =IF(COUNT(D41,E41)=2,E41-D41,"") | H41: =IF(COUNT(D41,F41)=2,F41-D41,"") | I41: bp
A42: 2026-03-10 | B42: Large TTF day (-17.5%) | C42: TTF (EUR/MWh) | D42: 56.453 | E42: 47.393 | F42: 49.989 | G42: =IF(COUNT(D42,E42)=2,E42/D42-1,"") | H42: =IF(COUNT(D42,F42)=2,F42/D42-1,"") | I42: %
A43: 2026-03-10 | B43: Large TTF day (-17.5%) | C43: Brent (USD/bbl) | D43: 98.96 | E43: 87.8 | F43: 91.98 | G43: =IF(COUNT(D43,E43)=2,E43/D43-1,"") | H43: =IF(COUNT(D43,F43)=2,F43/D43-1,"") | I43: %
A44: 2026-03-10 | B44: Large TTF day (-17.5%) | C44: ILS 1Y (%) | D44: 2.756 | E44: 2.5775 | F44: 2.71 | G44: =IF(COUNT(D44,E44)=2,(E44-D44)*100,"") | H44: =IF(COUNT(D44,F44)=2,(F44-D44)*100,"") | I44: bp
A45: 2026-03-10 | B45: Large TTF day (-17.5%) | C45: ILS 1y1y (%) | D45: 1.9815 | E45: 1.9705 | F45: 2.0773 | G45: =IF(COUNT(D45,E45)=2,(E45-D45)*100,"") | H45: =IF(COUNT(D45,F45)=2,(F45-D45)*100,"") | I45: bp
A46: 2026-03-10 | B46: Large TTF day (-17.5%) | C46: OIS 1y1y (%) | D46: 2.3440865 | E46: 2.2075537 | F46: 2.3959617 | G46: =IF(COUNT(D46,E46)=2,(E46-D46)*100,"") | H46: =IF(COUNT(D46,F46)=2,(F46-D46)*100,"") | I46: bp
A47: 2026-03-10 | B47: Large TTF day (-17.5%) | C47: OIS 2Y (%) | D47: 2.25 | E47: 2.1335 | F47: 2.289 | G47: =IF(COUNT(D47,E47)=2,(E47-D47)*100,"") | H47: =IF(COUNT(D47,F47)=2,(F47-D47)*100,"") | I47: bp
A48: 2026-03-10 | B48: Large TTF day (-17.5%) | C48: Bund 2Y (%) | D48: 2.4 | E48: 2.26 | F48: 2.33 | G48: =IF(COUNT(D48,E48)=2,(E48-D48)*100,"") | H48: =IF(COUNT(D48,F48)=2,(F48-D48)*100,"") | I48: bp
A49: 2026-03-10 | B49: Large TTF day (-17.5%) | C49: Bund 5Y (%) | D49: 2.57 | E49: 2.49 | F49: 2.55 | G49: =IF(COUNT(D49,E49)=2,(E49-D49)*100,"") | H49: =IF(COUNT(D49,F49)=2,(F49-D49)*100,"") | I49: bp
A50: 2026-03-10 | B50: Large TTF day (-17.5%) | C50: Bund 10Y (%) | D50: 2.89 | E50: 2.85 | F50: 2.89 | G50: =IF(COUNT(D50,E50)=2,(E50-D50)*100,"") | H50: =IF(COUNT(D50,F50)=2,(F50-D50)*100,"") | I50: bp
A51: 2026-03-10 | B51: Large TTF day (-17.5%) | C51: Bund 30Y (%) | D51: 3.42 | E51: 3.44 | F51: 3.48 | G51: =IF(COUNT(D51,E51)=2,(E51-D51)*100,"") | H51: =IF(COUNT(D51,F51)=2,(F51-D51)*100,"") | I51: bp
A52: 2026-03-10 | B52: Large TTF day (-17.5%) | C52: 2s10s (bp) | D52: 49 | E52: 59 | F52: 56 | G52: =IF(COUNT(D52,E52)=2,E52-D52,"") | H52: =IF(COUNT(D52,F52)=2,F52-D52,"") | I52: bp
A53: 2026-03-10 | B53: Large TTF day (-17.5%) | C53: 5Y swap spread (bp) | D53: 14.12 | E53: 11.42 | F53: 18.35 | G53: =IF(COUNT(D53,E53)=2,E53-D53,"") | H53: =IF(COUNT(D53,F53)=2,F53-D53,"") | I53: bp
A54: 2026-03-19 | B54: Large TTF day (+12.4%) | C54: TTF (EUR/MWh) | D54: 54.662 | E54: 61.852 | F54: 59.255 | G54: =IF(COUNT(D54,E54)=2,E54/D54-1,"") | H54: =IF(COUNT(D54,F54)=2,F54/D54-1,"") | I54: %
A55: 2026-03-19 | B55: Large TTF day (+12.4%) | C55: Brent (USD/bbl) | D55: 107.38 | E55: 108.65 | F55: 112.19 | G55: =IF(COUNT(D55,E55)=2,E55/D55-1,"") | H55: =IF(COUNT(D55,F55)=2,F55/D55-1,"") | I55: %
A56: 2026-03-19 | B56: Large TTF day (+12.4%) | C56: ILS 1Y (%) | D56: 3.478 | E56: 3.674 | F56: 3.5855 | G56: =IF(COUNT(D56,E56)=2,(E56-D56)*100,"") | H56: =IF(COUNT(D56,F56)=2,(F56-D56)*100,"") | I56: bp
A57: 2026-03-19 | B57: Large TTF day (+12.4%) | C57: ILS 1y1y (%) | D57: 2.0787 | E57: 2.0994 | F57: 2.2005 | G57: =IF(COUNT(D57,E57)=2,(E57-D57)*100,"") | H57: =IF(COUNT(D57,F57)=2,(F57-D57)*100,"") | I57: bp
A58: 2026-03-19 | B58: Large TTF day (+12.4%) | C58: OIS 1y1y (%) | D58: 2.4726099 | E58: 2.6265957 | F58: 2.7151055 | G58: =IF(COUNT(D58,E58)=2,(E58-D58)*100,"") | H58: =IF(COUNT(D58,F58)=2,(F58-D58)*100,"") | I58: bp
A59: 2026-03-19 | B59: Large TTF day (+12.4%) | C59: OIS 2Y (%) | D59: 2.3665 | E59: 2.5275 | F59: 2.611 | G59: =IF(COUNT(D59,E59)=2,(E59-D59)*100,"") | H59: =IF(COUNT(D59,F59)=2,(F59-D59)*100,"") | I59: bp
A60: 2026-03-19 | B60: Large TTF day (+12.4%) | C60: Bund 2Y (%) | D60: 2.37 | E60: 2.51 | F60: 2.62 | G60: =IF(COUNT(D60,E60)=2,(E60-D60)*100,"") | H60: =IF(COUNT(D60,F60)=2,(F60-D60)*100,"") | I60: bp
A61: 2026-03-19 | B61: Large TTF day (+12.4%) | C61: Bund 5Y (%) | D61: 2.55 | E61: 2.66 | F61: 2.72 | G61: =IF(COUNT(D61,E61)=2,(E61-D61)*100,"") | H61: =IF(COUNT(D61,F61)=2,(F61-D61)*100,"") | I61: bp
A62: 2026-03-19 | B62: Large TTF day (+12.4%) | C62: Bund 10Y (%) | D62: 2.88 | E62: 2.97 | F62: 2.99 | G62: =IF(COUNT(D62,E62)=2,(E62-D62)*100,"") | H62: =IF(COUNT(D62,F62)=2,(F62-D62)*100,"") | I62: bp
A63: 2026-03-19 | B63: Large TTF day (+12.4%) | C63: Bund 30Y (%) | D63: 3.45 | E63: 3.5 | F63: 3.49 | G63: =IF(COUNT(D63,E63)=2,(E63-D63)*100,"") | H63: =IF(COUNT(D63,F63)=2,(F63-D63)*100,"") | I63: bp
A64: 2026-03-19 | B64: Large TTF day (+12.4%) | C64: 2s10s (bp) | D64: 51 | E64: 46 | F64: 37 | G64: =IF(COUNT(D64,E64)=2,E64-D64,"") | H64: =IF(COUNT(D64,F64)=2,F64-D64,"") | I64: bp
A65: 2026-03-19 | B65: Large TTF day (+12.4%) | C65: 5Y swap spread (bp) | D65: 17.63 | E65: 14.28 | F65: 23.86 | G65: =IF(COUNT(D65,E65)=2,E65-D65,"") | H65: =IF(COUNT(D65,F65)=2,F65-D65,"") | I65: bp
A66: 2026-04-08 | B66: US-Iran ceasefire | C66: TTF (EUR/MWh) | D66: 53.247 | E66: 45.301 | F66: 46.175 | G66: =IF(COUNT(D66,E66)=2,E66/D66-1,"") | H66: =IF(COUNT(D66,F66)=2,F66/D66-1,"") | I66: %
A67: 2026-04-08 | B67: US-Iran ceasefire | C67: Brent (USD/bbl) | D67: 109.27 | E67: 94.75 | F67: 95.92 | G67: =IF(COUNT(D67,E67)=2,E67/D67-1,"") | H67: =IF(COUNT(D67,F67)=2,F67/D67-1,"") | I67: %
A68: 2026-04-08 | B68: US-Iran ceasefire | C68: ILS 1Y (%) | D68: 3.495 | E68: 3.109 | F68: 3.2525 | G68: =IF(COUNT(D68,E68)=2,(E68-D68)*100,"") | H68: =IF(COUNT(D68,F68)=2,(F68-D68)*100,"") | I68: bp
A69: 2026-04-08 | B69: US-Iran ceasefire | C69: ILS 1y1y (%) | D69: 2.2084 | E69: 2.0873 | F69: 2.0556 | G69: =IF(COUNT(D69,E69)=2,(E69-D69)*100,"") | H69: =IF(COUNT(D69,F69)=2,(F69-D69)*100,"") | I69: bp
A70: 2026-04-08 | B70: US-Iran ceasefire | C70: OIS 1y1y (%) | D70: 2.7356035 | E70: 2.4535376 | F70: 2.5051569 | G70: =IF(COUNT(D70,E70)=2,(E70-D70)*100,"") | H70: =IF(COUNT(D70,F70)=2,(F70-D70)*100,"") | I70: bp
A71: 2026-04-08 | B71: US-Iran ceasefire | C71: OIS 2Y (%) | D71: 2.6325 | E71: 2.3915 | F71: 2.4288 | G71: =IF(COUNT(D71,E71)=2,(E71-D71)*100,"") | H71: =IF(COUNT(D71,F71)=2,(F71-D71)*100,"") | I71: bp
A72: 2026-04-08 | B72: US-Iran ceasefire | C72: Bund 2Y (%) | D72: 2.64 | E72: 2.5 | F72: 2.56 | G72: =IF(COUNT(D72,E72)=2,(E72-D72)*100,"") | H72: =IF(COUNT(D72,F72)=2,(F72-D72)*100,"") | I72: bp
A73: 2026-04-08 | B73: US-Iran ceasefire | C73: Bund 5Y (%) | D73: 2.73 | E73: 2.62 | F73: 2.69 | G73: =IF(COUNT(D73,E73)=2,(E73-D73)*100,"") | H73: =IF(COUNT(D73,F73)=2,(F73-D73)*100,"") | I73: bp
A74: 2026-04-08 | B74: US-Iran ceasefire | C74: Bund 10Y (%) | D74: 3 | E74: 2.92 | F74: 2.99 | G74: =IF(COUNT(D74,E74)=2,(E74-D74)*100,"") | H74: =IF(COUNT(D74,F74)=2,(F74-D74)*100,"") | I74: bp
A75: 2026-04-08 | B75: US-Iran ceasefire | C75: Bund 30Y (%) | D75: 3.47 | E75: 3.45 | F75: 3.49 | G75: =IF(COUNT(D75,E75)=2,(E75-D75)*100,"") | H75: =IF(COUNT(D75,F75)=2,(F75-D75)*100,"") | I75: bp
A76: 2026-04-08 | B76: US-Iran ceasefire | C76: 2s10s (bp) | D76: 36 | E76: 42 | F76: 43 | G76: =IF(COUNT(D76,E76)=2,E76-D76,"") | H76: =IF(COUNT(D76,F76)=2,F76-D76,"") | I76: bp
A77: 2026-04-08 | B77: US-Iran ceasefire | C77: 5Y swap spread (bp) | D77: 22.94 | E77: -2.36 | F77: 19.28 | G77: =IF(COUNT(D77,E77)=2,E77-D77,"") | H77: =IF(COUNT(D77,F77)=2,F77-D77,"") | I77: bp
A78: 2026-06-11 | B78: ECB hike #1 (DFR 2.00 -> 2.25) | C78: TTF (EUR/MWh) | D78: 49.989 | E78: 49.69 | F78: 46.773 | G78: =IF(COUNT(D78,E78)=2,E78/D78-1,"") | H78: =IF(COUNT(D78,F78)=2,F78/D78-1,"") | I78: %
A79: 2026-06-11 | B79: ECB hike #1 (DFR 2.00 -> 2.25) | C79: Brent (USD/bbl) | D79: 93.1 | E79: 90.38 | F79: 87.33 | G79: =IF(COUNT(D79,E79)=2,E79/D79-1,"") | H79: =IF(COUNT(D79,F79)=2,F79/D79-1,"") | I79: %
A80: 2026-06-11 | B80: ECB hike #1 (DFR 2.00 -> 2.25) | C80: ILS 1Y (%) | D80: 2.981 | E80: 2.9665 | F80: 2.83 | G80: =IF(COUNT(D80,E80)=2,(E80-D80)*100,"") | H80: =IF(COUNT(D80,F80)=2,(F80-D80)*100,"") | I80: bp
A81: 2026-06-11 | B81: ECB hike #1 (DFR 2.00 -> 2.25) | C81: ILS 1y1y (%) | D81: 2.1525 | E81: 2.1498 | F81: 2.0892 | G81: =IF(COUNT(D81,E81)=2,(E81-D81)*100,"") | H81: =IF(COUNT(D81,F81)=2,(F81-D81)*100,"") | I81: bp
A82: 2026-06-11 | B82: ECB hike #1 (DFR 2.00 -> 2.25) | C82: OIS 1y1y (%) | D82: 2.6935527 | E82: 2.6190317 | F82: 2.5435189 | G82: =IF(COUNT(D82,E82)=2,(E82-D82)*100,"") | H82: =IF(COUNT(D82,F82)=2,(F82-D82)*100,"") | I82: bp
A83: 2026-06-11 | B83: ECB hike #1 (DFR 2.00 -> 2.25) | C83: OIS 2Y (%) | D83: 2.62 | E83: 2.562 | F83: 2.4995 | G83: =IF(COUNT(D83,E83)=2,(E83-D83)*100,"") | H83: =IF(COUNT(D83,F83)=2,(F83-D83)*100,"") | I83: bp
A84: 2026-06-11 | B84: ECB hike #1 (DFR 2.00 -> 2.25) | C84: Bund 2Y (%) | D84: 2.69 | E84: 2.7 | F84: 2.6 | G84: =IF(COUNT(D84,E84)=2,(E84-D84)*100,"") | H84: =IF(COUNT(D84,F84)=2,(F84-D84)*100,"") | I84: bp
A85: 2026-06-11 | B85: ECB hike #1 (DFR 2.00 -> 2.25) | C85: Bund 5Y (%) | D85: 2.77 | E85: 2.78 | F85: 2.7 | G85: =IF(COUNT(D85,E85)=2,(E85-D85)*100,"") | H85: =IF(COUNT(D85,F85)=2,(F85-D85)*100,"") | I85: bp
A86: 2026-06-11 | B86: ECB hike #1 (DFR 2.00 -> 2.25) | C86: Bund 10Y (%) | D86: 3.05 | E86: 3.06 | F86: 2.98 | G86: =IF(COUNT(D86,E86)=2,(E86-D86)*100,"") | H86: =IF(COUNT(D86,F86)=2,(F86-D86)*100,"") | I86: bp
A87: 2026-06-11 | B87: ECB hike #1 (DFR 2.00 -> 2.25) | C87: Bund 30Y (%) | D87: 3.6 | E87: 3.6 | F87: 3.53 | G87: =IF(COUNT(D87,E87)=2,(E87-D87)*100,"") | H87: =IF(COUNT(D87,F87)=2,(F87-D87)*100,"") | I87: bp
A88: 2026-06-11 | B88: ECB hike #1 (DFR 2.00 -> 2.25) | C88: 2s10s (bp) | D88: 36 | E88: 36 | F88: 38 | G88: =IF(COUNT(D88,E88)=2,E88-D88,"") | H88: =IF(COUNT(D88,F88)=2,F88-D88,"") | I88: bp
A89: 2026-06-11 | B89: ECB hike #1 (DFR 2.00 -> 2.25) | C89: 5Y swap spread (bp) | D89: 14.485 | E89: 9.785 | F89: 15.125 | G89: =IF(COUNT(D89,E89)=2,E89-D89,"") | H89: =IF(COUNT(D89,F89)=2,F89-D89,"") | I89: bp
A90: 2026-09-10 | B90: ECB hike #2 (DFR 2.25 -> 2.50) | C90: TTF (EUR/MWh) | D90: 79.246 | E90: 82.047 | F90: 79.52 | G90: =IF(COUNT(D90,E90)=2,E90/D90-1,"") | H90: =IF(COUNT(D90,F90)=2,F90/D90-1,"") | I90: %
A91: 2026-09-10 | B91: ECB hike #2 (DFR 2.25 -> 2.50) | C91: Brent (USD/bbl) | D91: 101.21 | E91: 107.63 | F91: 104.61 | G91: =IF(COUNT(D91,E91)=2,E91/D91-1,"") | H91: =IF(COUNT(D91,F91)=2,F91/D91-1,"") | I91: %
A92: 2026-09-10 | B92: ECB hike #2 (DFR 2.25 -> 2.50) | C92: ILS 1Y (%) | D92: 3.462 | E92: 3.587 | F92: 3.499 | G92: =IF(COUNT(D92,E92)=2,(E92-D92)*100,"") | H92: =IF(COUNT(D92,F92)=2,(F92-D92)*100,"") | I92: bp
A93: 2026-09-10 | B93: ECB hike #2 (DFR 2.25 -> 2.50) | C93: ILS 1y1y (%) | D93: 2.3023 | E93: 2.3178 | F93: 2.2736 | G93: =IF(COUNT(D93,E93)=2,(E93-D93)*100,"") | H93: =IF(COUNT(D93,F93)=2,(F93-D93)*100,"") | I93: bp
A94: 2026-09-10 | B94: ECB hike #2 (DFR 2.25 -> 2.50) | C94: OIS 1y1y (%) | D94: 3.0981947 | E94: 3.3317393 | F94: 3.2477456 | G94: =IF(COUNT(D94,E94)=2,(E94-D94)*100,"") | H94: =IF(COUNT(D94,F94)=2,(F94-D94)*100,"") | I94: bp
A95: 2026-09-10 | B95: ECB hike #2 (DFR 2.25 -> 2.50) | C95: OIS 2Y (%) | D95: 2.9565 | E95: 3.1745 | F95: 3.0885 | G95: =IF(COUNT(D95,E95)=2,(E95-D95)*100,"") | H95: =IF(COUNT(D95,F95)=2,(F95-D95)*100,"") | I95: bp
A96: 2026-09-10 | B96: ECB hike #2 (DFR 2.25 -> 2.50) | C96: Bund 2Y (%) | D96: 3.03 | E96: 3.06 | F96: 3.18 | G96: =IF(COUNT(D96,E96)=2,(E96-D96)*100,"") | H96: =IF(COUNT(D96,F96)=2,(F96-D96)*100,"") | I96: bp
A97: 2026-09-10 | B97: ECB hike #2 (DFR 2.25 -> 2.50) | C97: Bund 5Y (%) | D97: 3.15 | E97: 3.2 | F97: 3.29 | G97: =IF(COUNT(D97,E97)=2,(E97-D97)*100,"") | H97: =IF(COUNT(D97,F97)=2,(F97-D97)*100,"") | I97: bp
A98: 2026-09-10 | B98: ECB hike #2 (DFR 2.25 -> 2.50) | C98: Bund 10Y (%) | D98: 3.39 | E98: 3.45 | F98: 3.51 | G98: =IF(COUNT(D98,E98)=2,(E98-D98)*100,"") | H98: =IF(COUNT(D98,F98)=2,(F98-D98)*100,"") | I98: bp
A99: 2026-09-10 | B99: ECB hike #2 (DFR 2.25 -> 2.50) | C99: Bund 30Y (%) | D99: 3.83 | E99: 3.9 | F99: 3.9 | G99: =IF(COUNT(D99,E99)=2,(E99-D99)*100,"") | H99: =IF(COUNT(D99,F99)=2,(F99-D99)*100,"") | I99: bp
A100: 2026-09-10 | B100: ECB hike #2 (DFR 2.25 -> 2.50) | C100: 2s10s (bp) | D100: 36 | E100: 39 | F100: 33 | G100: =IF(COUNT(D100,E100)=2,E100-D100,"") | H100: =IF(COUNT(D100,F100)=2,F100-D100,"") | I100: bp
A101: 2026-09-10 | B101: ECB hike #2 (DFR 2.25 -> 2.50) | C101: 5Y swap spread (bp) | D101: 22.355 | E101: 24.84 | F101: 18.35 | G101: =IF(COUNT(D101,E101)=2,E101-D101,"") | H101: =IF(COUNT(D101,F101)=2,F101-D101,"") | I101: bp

Sheet Data_Quality
A1: Data quality log: issues found and treatment
A2: Source: data/clean/data_quality_log.csv (built by src/clean.py).
A4: series | B4: issue | C4: treatment | D4: n_affected
A5: bund_30y | B5: Bundesbank quality flags: {'Estimated value': 1} | C5: Kept (flags are informational); listed in daily_levels *_flag columns | D5: 1
A6: bund_30y | B6: '.' placeholders for weekends/holidays (calendar-day file) | C6: Dropped; panel built on Bundesbank business days | D6: 3664
A7: bund_7y | B7: '.' placeholders for weekends/holidays (calendar-day file) | C7: Dropped; panel built on Bundesbank business days | D7: 707
A8: bund_15y | B8: Bundesbank quality flags: {'Estimated value': 4} | C8: Kept (flags are informational); listed in daily_levels *_flag columns | D8: 4
A9: bund_15y | B9: '.' placeholders for weekends/holidays (calendar-day file) | C9: Dropped; panel built on Bundesbank business days | D9: 707
A10: bund_20y | B10: '.' placeholders for weekends/holidays (calendar-day file) | C10: Dropped; panel built on Bundesbank business days | D10: 75
A11: bund_2y | B11: '.' placeholders for weekends/holidays (calendar-day file) | C11: Dropped; panel built on Bundesbank business days | D11: 1425
A12: bund_5y | B12: Bundesbank quality flags: {'Provisional value': 1} | C12: Kept (flags are informational); listed in daily_levels *_flag columns | D12: 1
A13: bund_5y | B13: '.' placeholders for weekends/holidays (calendar-day file) | C13: Dropped; panel built on Bundesbank business days | D13: 2234
A14: bund_10y | B14: Bundesbank quality flags: {'Corrected value': 20} | C14: Kept (flags are informational); listed in daily_levels *_flag columns | D14: 20
A15: bund_10y | B15: '.' placeholders for weekends/holidays (calendar-day file) | C15: Dropped; panel built on Bundesbank business days | D15: 2784
A16: gas_ttf_m1_eurmwh | B16: Missing bid or ask / close in export | C16: Left as NaN (no forward fill) | D16: 1
... A36: ois_estr_2y | B36: Dates not in Bundesbank business-day calendar (UK/US trading days) | C36: Dropped from daily panel (calendar = German bond market days) | D36: 41
A37: ils_eur_1y1y | B37: File named '1Y inflation swap' is RIC EUIL1YF1Y=R, i.e. the 1y1y FORWARD | C37: Renamed ils_eur_1y1y; spot 1Y added separately from EUCPIZ1Y=TWEB
A38: ils_eur_1y | B38: Tradeweb 1Y ILS history only starts 2022-04-08 | C38: Used in post-2022 tests only
A39: hicp_ea_idx | B39: Two index bases spliced: fake -34.2% m/m at 1999-12 | C39: Truncated: only data from the break onward (2025=100 base) kept | D39: 47
A40: hicp_ea_idx | B40: Not seasonally adjusted | C40: Use y/y, or m/m with calendar-month dummies
A41: gas_eu_imf_usdmmbtu_mavg | B41: Monthly average, USD, revised by FRED, ends 2026-07 | C41: Used only for monthly cross-checks; TTF (EUR) is the primary gas variable
A42: stock_data.csv | B42: Unknown source; weekend rows duplicating Fridays; High<Open rows; does not match NGc1 closes | C42: Excluded from all analysis | D42: 24
A43: Price History_20261010_1208.xlsx | B43: 2-year NBP export is an exact subset of the 10-year export | C43: Excluded (redundant) | D43: 506
A44: bund_* | B44: Asynchronous snapshot: daily Bund change loads ~equally on the previous and the same day's LSEG OIS change (0.53 / 0.49, t>10); corr(Bund2Y, OIS2Y) rises from 0.44 (1-day) to 0.67 (2-day) to 0.87 (weekly) => Bundesbank yields are observed roughly half a trading day before LSEG closes / TTF settlement | C44: Daily Bund regressions include same-day and previous-day market moves (Dimson); total effect = sum. Full-chain mediation and VAR with Bunds run weekly; predictive tests for Bund targets skip the overlapping day

Sheet Data_Dictionary
A1: Data dictionary (clean variable names)
A2: Source: data/clean/data_dictionary.csv (built by src/clean.py).
A4: variable | B4: description | C4: unit | D4: source | E4: frequency
A5: bund_{t} | B5: Yield of the current (on-the-run) German federal security, {t} maturity bucket | C5: % | D5: Bundesbank BBSSY.D.REN.EUR.A6xx | E5: daily
A6: ois_estr_1m/3m/1y/2y | B6: EUR €STR overnight index swap par rate | C6: % | D6: LSEG EUREST1M=/3M=/1Y=/2Y= (mid) | E6: daily, from 2019-09
A7: ois_estr_1y1y | B7: 1-year €STR rate 1 year forward = ((1+OIS2y)^2/(1+OIS1y))-1 | C7: % | D7: Derived | E7: daily
A8: ils_eur_1y | B8: EUR zero-coupon inflation swap 1Y (HICPxT) | C8: % | D8: LSEG/Tradeweb EUCPIZ1Y=TWEB (mid) | E8: daily, from 2022-04
A9: ils_eur_1y1y | B9: EUR inflation swap 1y forward 1y (HICPxT) | C9: % | D9: LSEG EUIL1YF1Y=R (mid) | E9: daily, from 2016
A10: gas_ttf_m1_eurmwh | B10: ICE Endex Dutch TTF front-month futures settlement | C10: EUR/MWh | D10: LSEG TFMBMc1 | E10: daily
A11: gas_ttf_m1_usdmmbtu | B11: TTF converted at EURUSD; 1 MWh = 3.41214 MMBtu | C11: USD/MMBtu | D11: Derived | E11: daily
A12: gas_nbp_m1_gbppth | B12: ICE UK NBP front-month futures | C12: GBp/therm | D12: LSEG NGLNMc1 | E12: daily, from 2016-11
A13: gas_nbp_m1_eurmwh | B13: NBP converted: p/th /100 x 34.12 th/MWh / EURGBP | C13: EUR/MWh | D13: Derived | E13: daily
A14: gas_hh_m1_usdmmbtu | B14: NYMEX Henry Hub front-month futures | C14: USD/MMBtu | D14: LSEG NGc1 | E14: daily, from 2024-10
A15: oil_brent_m1_usdbbl | B15: ICE Brent front-month futures | C15: USD/bbl | D15: LSEG LCOc1 | E15: daily
... A28: gas_eu_imf_usdmmbtu_mavg | B28: IMF Global price of natural gas, EU (monthly average) | C28: USD/MMBtu | D28: FRED PNGASEUUSDM | E28: monthly

Sheet Coverage
A1: Series coverage
A2: Source: data/clean/coverage.csv (built by src/clean.py).
A4: series | B4: first | C4: last | D4: n_obs
A5: bund_2y | B5: 2014-01-02 00:00:00 | C5: 2026-10-09 00:00:00 | D5: 3239
A6: bund_5y | B6: 2014-01-02 00:00:00 | C6: 2026-10-09 00:00:00 | D6: 3239
A7: bund_7y | B7: 2020-05-12 00:00:00 | C7: 2026-10-09 00:00:00 | D7: 1635
A8: bund_10y | B8: 2014-01-02 00:00:00 | C8: 2026-10-09 00:00:00 | D8: 3239
A9: bund_15y | B9: 2020-05-11 00:00:00 | C9: 2026-10-09 00:00:00 | D9: 1636
A10: bund_20y | B10: 2026-01-30 00:00:00 | C10: 2026-10-09 00:00:00 | D10: 178
A11: bund_30y | B11: 2014-01-02 00:00:00 | C11: 2026-10-09 00:00:00 | D11: 3239
A12: gas_ttf_m1_eurmwh | B12: 2014-10-10 00:00:00 | C12: 2026-10-09 00:00:00 | D12: 3042
A13: oil_brent_m1_usdbbl | B13: 2014-10-10 00:00:00 | C13: 2026-10-09 00:00:00 | D13: 3041
A14: gas_nbp_m1_gbppth | B14: 2016-11-01 00:00:00 | C14: 2026-10-09 00:00:00 | D14: 2489
A15: gas_hh_m1_usdmmbtu | B15: 2024-10-10 00:00:00 | C15: 2026-10-09 00:00:00 | D15: 492
A16: fx_eurusd | B16: 2014-10-10 00:00:00 | C16: 2026-10-09 00:00:00 | D16: 3042
... A42: roll_gas_hh_m1_usdmmbtu | B42: 2014-01-02 00:00:00 | C42: 2026-10-09 00:00:00 | D42: 3239
